Workbook

Sheet INÍCIO
B2: GESTÃO DOCUMENTAL — LCQ RJ | K2: DATA DE REFERÊNCIA
B4: Cockpit Executivo de Instruções · Fonte: NDocs Rev.28 | K4: =DataRef -> 46301
B5: Bem-vindo! Escolha abaixo o que você precisa fazer — cada cartão abre a aba certa.
B8: SITUAÇÃO HOJE · carteira completa de instruções
B10: INSTRUÇÕES | E10: APROVADAS | G10: AÇÃO IMEDIATA | J10: VENCEM EM 12 MESES | L10: SAÚDE DOCUMENTAL
B11: =COUNTA('BASE CONSOLIDADA'!$A$5:$A$129) -> 125 | E11: =COUNTIF('BASE CONSOLIDADA'!$N$5:$N$129,"Aprovado") -> 117 | G11: =COUNTIF('BASE CONSOLIDADA'!$R$5:$R$129,"Ação imediata") -> 1 | J11: =COUNTIFS('BASE CONSOLIDADA'!$N$5:$N$129,"Aprovado",'BASE CONSOLIDADA'!$O$5:$O$129,">="&DataRef,'BASE CONSOLIDADA'!$O$5:$O$129,"<="&EDATE(DataRef,12)) -> 12 | L11: =IFERROR((COUNTIF('BASE CONSOLIDADA'!$R$5:$R$129,"Regular")+COUNTIF('BASE CONSOLIDADA'!$R$5:$R$129,"Planejar revisão"))/COUNTIF('BASE CONSOLIDADA'!$R$5:$R$129,"<>Inativo"),0) -> 0.95081967
B12: ="únicas · "&COUNTIF('BASE CONSOLIDADA'!$R$5:$R$129,"<>Inativo")&" ativas" -> únicas · 122 ativas | E12: ="status oficial NDocs" -> status oficial NDocs | G12: ="vencidas e ativas" -> vencidas e ativas | J12: ="planejar revisão" -> planejar revisão | L12: ="aprovadas e válidas ÷ ativas" -> aprovadas e válidas ÷ ativas
B15: O QUE VOCÊ QUER FAZER?
B17: ▦ | F17: ⚑ | J17: ⌕
B18: Ver o panorama geral | F18: Ver o que precisa de ação | J18: Encontrar um documento
B19: Indicadores, riscos, agenda de vencimentos e carteira por área e responsável | F19: Lista curta, priorizada, com a ação recomendada para cada documento | J19: Busque por código NDocs, número antigo (IT …) ou palavra do título
F20: =COUNTIF('BASE CONSOLIDADA'!$U$5:$U$129,">0")&" documento(s) pedem atenção" -> 6 documento(s) pedem atenção
B21: Abrir Dashboard ▸ | F21: Ver ações ▸ | J21: Pesquisar ▸
B23: ☰ | F23: ✓ | J23: ▤
B24: Consultar a base completa | F24: Conferir a qualidade dos dados | J24: Outros controles documentais
B25: Uma linha por código NDocs, com origem rastreável e situação gerencial | F25: Duplicidades, divergências, campos vazios, erros legados e regras de cálculo | J25: FMG/ANX, Transversais, LPP, AST, RT e MO — fora dos KPIs de instruções
B26: =COUNTA('BASE CONSOLIDADA'!$A$5:$A$129)&" códigos únicos" -> 125 códigos únicos | F26: ='QUALIDADE BASE'!E6&" crítico · "&'QUALIDADE BASE'!F6&" atenção" -> 1 crítico · 10 atenção
B27: Abrir Base ▸ | F27: Abrir Qualidade ▸ | J27: Abrir Outros ▸
B30: INSTRUÇÕES POR ÁREA · abas de origem do NDocs
B32: Q4 | E32: PE / PP | H32: AOL | K32: Comuns
B33: =COUNTIF('BASE CONSOLIDADA'!$G$5:$G$129,"*Q4*") -> 61 | E33: =SUMPRODUCT(--((ISNUMBER(SEARCH("PE",'BASE CONSOLIDADA'!$G$5:$G$129))+ISNUMBER(SEARCH("PP",'BASE CONSOLIDADA'!$G$5:$G$129)))>0)) -> 30 | H33: =COUNTIF('BASE CONSOLIDADA'!$G$5:$G$129,"*AOL*") -> 26 | K33: =COUNTIF('BASE CONSOLIDADA'!$G$5:$G$129,"*COMUM*") -> 11
B34: Área Q4 · inclui compartilhadas | E34: PE, PP e PE/PP | H34: Analisadores em linha · inclui Q4/AOL | K34: Comuns ao LCQ
B35: Abrir aba ▸ | E35: Abrir aba ▸ | H35: Abrir aba ▸ | K35: Abrir aba ▸
B37: COMO USAR · 3 passos
B39: 1 | C39: Abra o Dashboard | F39: 2 | G39: Filtre o que importa | J39: 3 | K39: Aprofunde
C40: Veja os números do dia e o painel "Ação necessária agora". | G40: Use as listas suspensas (Área, Situação, Responsável…). Volte a "Todas" para limpar. | K40: Use a Pesquisa ou a Base Consolidada para ver o detalhe de cada documento.
B43: LEGENDA DE CORES | D43: ● Vermelho — agir agora | F43: ● Âmbar — atenção | H43: ● Verde — regular | J43: ● Cinza — inativo
B45: Histórico (versões anteriores, não usadas nos KPIs): abas NDocs, NDocs (2) e NDocs Salvação ▸

Sheet DASHBOARD EXECUTIVO
B2: GESTÃO DOCUMENTAL — LCQ RJ | R2: DATA DE REFERÊNCIA | V2: FONTE
B3: Cockpit Executivo de Instruções | R3: =DataRef -> 46301 | V3: NDocs Rev.28
B4: ⌂ Início | E4: ▦ Dashboard | H4: ⌕ Pesquisa | K4: ☰ Base | N4: ✓ Qualidade | Q4: ▤ Outros | T4: Os filtros abaixo afetam todos os blocos
B6: ÁREA | F6: STATUS NDOCS | J6: SITUAÇÃO GERENCIAL | N6: RESPONSÁVEL | S6: HORIZONTE DE VALIDADE | W6: ↺ Para limpar, volte cada filtro a "Todas/Todos"
B7: Todas | F7: Todos | J7: Todas | N7: Todos | S7: Todos
B9: INSTRUÇÕES ÚNICAS | F9: APROVADAS | J9: EM PROCESSO | N9: AÇÃO IMEDIATA | R9: VENCEM EM 12 MESES | V9: SAÚDE DOCUMENTAL
B10: =SUM('BASE CONSOLIDADA'!$W$5:$W$129) -> 125 | F10: =COUNTIFS('BASE CONSOLIDADA'!$W$5:$W$129,1,'BASE CONSOLIDADA'!$N$5:$N$129,"Aprovado") -> 117 | J10: =COUNTIFS('BASE CONSOLIDADA'!$W$5:$W$129,1,'BASE CONSOLIDADA'!$R$5:$R$129,"Em tratamento") -> 3 | N10: =COUNTIFS('BASE CONSOLIDADA'!$W$5:$W$129,1,'BASE CONSOLIDADA'!$R$5:$R$129,"Ação imediata") -> 1 | R10: =COUNTIFS('BASE CONSOLIDADA'!$W$5:$W$129,1,'BASE CONSOLIDADA'!$N$5:$N$129,"Aprovado",'BASE CONSOLIDADA'!$O$5:$O$129,">="&DataRef,'BASE CONSOLIDADA'!$O$5:$O$129,"<="&EDATE(DataRef,12)) -> 12 | V10: =IFERROR((COUNTIFS('BASE CONSOLIDADA'!$W$5:$W$129,1,'BASE CONSOLIDADA'!$R$5:$R$129,"Regular")+COUNTIFS('BASE CONSOLIDADA'!$W$5:$W$129,1,'BASE CONSOLIDADA'!$R$5:$R$129,"Planejar revisão"))/COUNTIFS('BASE CONSOLIDADA'!$W$5:$W$129,1,'BASE CONSOLIDADA'!$R$5:$R$129,"<>Inativo"),"–") -> 0.95081967
B11: =COUNTIFS('BASE CONSOLIDADA'!$W$5:$W$129,1,'BASE CONSOLIDADA'!$R$5:$R$129,"<>Inativo")&" ativas · "&COUNTIFS('BASE CONSOLIDADA'!$W$5:$W$129,1,'BASE CONSOLIDADA'!$R$5:$R$129,"Inativo")&" inativas" -> 122 ativas · 3 inativas | F11: =IFERROR(TEXT(COUNTIFS('BASE CONSOLIDADA'!$W$5:$W$129,1,'BASE CONSOLIDADA'!$N$5:$N$129,"Aprovado")/COUNTIFS('BASE CONSOLIDADA'!$W$5:$W$129,1,'BASE CONSOLIDADA'!$R$5:$R$129,"<>Inativo"),"0%"),"–")&" das instruções ativas" -> 96% das instruções ativas | J11: ="Revisão "&COUNTIFS('BASE CONSOLIDADA'!$W$5:$W$129,1,'BASE CONSOLIDADA'!$N$5:$N$129,"Revisão")&" · Elaboração "&COUNTIFS('BASE CONSOLIDADA'!$W$5:$W$129,1,'BASE CONSOLIDADA'!$N$5:$N$129,"Em Elaboração") -> Revisão 2 · Elaboração 1 | N11: ="vencida(s) e ativa(s) · +"&COUNTIFS('BASE CONSOLIDADA'!$W$5:$W$129,1,'BASE CONSOLIDADA'!$R$5:$R$129,"Validar cadastro")&" a validar" -> vencida(s) e ativa(s) · +2 a validar | R11: ="até 90 dias: "&COUNTIFS('BASE CONSOLIDADA'!$W$5:$W$129,1,'BASE CONSOLIDADA'!$N$5:$N$129,"Aprovado",'BASE CONSOLIDADA'!$S$5:$S$129,"Até 90 dias") -> até 90 dias: 0 | V11: ="aprovadas e válidas ÷ ativas" -> aprovadas e válidas ÷ ativas
B14: ⚑ AÇÃO NECESSÁRIA AGORA | R14: ◷ AGENDA DE VENCIMENTOS — 12 MESES
B15: Somente o que exige tratamento. Ordem: 1 vencida ativa · 2 não encontrada · 3 revisão · 4 elaboração · 5 vence ≤ 90 dias · 6 validar cadastro | R15: Aprovadas que vencem por mês · barra escura = mês de concentração
B16: P | C16: Código | F16: Título | J16: Área | K16: Situação | M16: Responsável | O16: Ação recomendada
B17: =IF('_AUX DASH'!$C$75="","",INDEX('BASE CONSOLIDADA'!$U$5:$U$129,'_AUX DASH'!$C$75)) -> 1 | C17: =IF('_AUX DASH'!$C$75="","✓ Nenhum item exige ação com os filtros atuais",INDEX('BASE CONSOLIDADA'!$A$5:$A$129,'_AUX DASH'!$C$75)) -> BRK-INS-01-010133-PT | F17: =IF('_AUX DASH'!$C$75="","",INDEX('BASE CONSOLIDADA'!$D$5:$D$129,'_AUX DASH'!$C$75)) -> MANUAL DE SEGURANÇA DO LABORATÓRIO | J17: =IF('_AUX DASH'!$C$75="","",INDEX('BASE CONSOLIDADA'!$G$5:$G$129,'_AUX DASH'!$C$75)) -> COMUM | K17: =IF('_AUX DASH'!$C$75="","",INDEX('BASE CONSOLIDADA'!$R$5:$R$129,'_AUX DASH'!$C$75)) -> Ação imediata | M17: =IF('_AUX DASH'!$C$75="","",INDEX('BASE CONSOLIDADA'!$P$5:$P$129,'_AUX DASH'!$C$75)) -> Ana Carla Da Cruz Araujo | O17: =IF('_AUX DASH'!$C$75="","",INDEX('BASE CONSOLIDADA'!$V$5:$V$129,'_AUX DASH'!$C$75)) -> Revisar ou prorrogar validade
B18: =IF('_AUX DASH'!$C$76="","",INDEX('BASE CONSOLIDADA'!$U$5:$U$129,'_AUX DASH'!$C$76)) -> 2 | C18: =IF('_AUX DASH'!$C$76="","",INDEX('BASE CONSOLIDADA'!$A$5:$A$129,'_AUX DASH'!$C$76)) -> BRK-INS-01-016228-PT | F18: =IF('_AUX DASH'!$C$76="","",INDEX('BASE CONSOLIDADA'!$D$5:$D$129,'_AUX DASH'!$C$76)) -> DETERMINAÇÃO DE CARBONO ORGÂNICO TOTAL (TOC) | J18: =IF('_AUX DASH'!$C$76="","",INDEX('BASE CONSOLIDADA'!$G$5:$G$129,'_AUX DASH'!$C$76)) -> Q4 | K18: =IF('_AUX DASH'!$C$76="","",INDEX('BASE CONSOLIDADA'!$R$5:$R$129,'_AUX DASH'!$C$76)) -> Validar cadastro | M18: =IF('_AUX DASH'!$C$76="","",INDEX('BASE CONSOLIDADA'!$P$5:$P$129,'_AUX DASH'!$C$76)) -> Ana Carla Da Cruz Araujo | O18: =IF('_AUX DASH'!$C$76="","",INDEX('BASE CONSOLIDADA'!$V$5:$V$129,'_AUX DASH'!$C$76)) -> Confirmar status no NDocs
B19: =IF('_AUX DASH'!$C$77="","",INDEX('BASE CONSOLIDADA'!$U$5:$U$129,'_AUX DASH'!$C$77)) -> 3 | C19: =IF('_AUX DASH'!$C$77="","",INDEX('BASE CONSOLIDADA'!$A$5:$A$129,'_AUX DASH'!$C$77)) -> BRK-INS-01-018898-PT | F19: =IF('_AUX DASH'!$C$77="","",INDEX('BASE CONSOLIDADA'!$D$5:$D$129,'_AUX DASH'!$C$77)) -> DETERMINAÇÃO DE ÓLEOS E GRAXAS | J19: =IF('_AUX DASH'!$C$77="","",INDEX('BASE CONSOLIDADA'!$G$5:$G$129,'_AUX DASH'!$C$77)) -> Q4 | K19: =IF('_AUX DASH'!$C$77="","",INDEX('BASE CONSOLIDADA'!$R$5:$R$129,'_AUX DASH'!$C$77)) -> Em tratamento | M19: =IF('_AUX DASH'!$C$77="","",INDEX('BASE CONSOLIDADA'!$P$5:$P$129,'_AUX DASH'!$C$77)) -> Ana Carla Da Cruz Araujo | O19: =IF('_AUX DASH'!$C$77="","",INDEX('BASE CONSOLIDADA'!$V$5:$V$129,'_AUX DASH'!$C$77)) -> Acompanhar revisão
B20: =IF('_AUX DASH'!$C$78="","",INDEX('BASE CONSOLIDADA'!$U$5:$U$129,'_AUX DASH'!$C$78)) -> 3 | C20: =IF('_AUX DASH'!$C$78="","",INDEX('BASE CONSOLIDADA'!$A$5:$A$129,'_AUX DASH'!$C$78)) -> BRK-INS-01-013358-PT | F20: =IF('_AUX DASH'!$C$78="","",INDEX('BASE CONSOLIDADA'!$D$5:$D$129,'_AUX DASH'!$C$78)) -> DETERMINAÇÃO DO TEOR DE SOLÚVEIS EM XILENO TOTAL, AMORFO E OLIGÔMEROS | J20: =IF('_AUX DASH'!$C$78="","",INDEX('BASE CONSOLIDADA'!$G$5:$G$129,'_AUX DASH'!$C$78)) -> PP | K20: =IF('_AUX DASH'!$C$78="","",INDEX('BASE CONSOLIDADA'!$R$5:$R$129,'_AUX DASH'!$C$78)) -> Em tratamento | M20: =IF('_AUX DASH'!$C$78="","",INDEX('BASE CONSOLIDADA'!$P$5:$P$129,'_AUX DASH'!$C$78)) -> Bruna Luisa Goldschmidt | O20: =IF('_AUX DASH'!$C$78="","",INDEX('BASE CONSOLIDADA'!$V$5:$V$129,'_AUX DASH'!$C$78)) -> Acompanhar revisão
B21: =IF('_AUX DASH'!$C$79="","",INDEX('BASE CONSOLIDADA'!$U$5:$U$129,'_AUX DASH'!$C$79)) -> 4 | C21: =IF('_AUX DASH'!$C$79="","",INDEX('BASE CONSOLIDADA'!$A$5:$A$129,'_AUX DASH'!$C$79)) -> BRK-INS-01-015837-PT | F21: =IF('_AUX DASH'!$C$79="","",INDEX('BASE CONSOLIDADA'!$D$5:$D$129,'_AUX DASH'!$C$79)) -> DETERMINAÇÃO DE INORGÂNICOS POR CROMATOGRAFIA GASOSA | J21: =IF('_AUX DASH'!$C$79="","",INDEX('BASE CONSOLIDADA'!$G$5:$G$129,'_AUX DASH'!$C$79)) -> Q4 | K21: =IF('_AUX DASH'!$C$79="","",INDEX('BASE CONSOLIDADA'!$R$5:$R$129,'_AUX DASH'!$C$79)) -> Em tratamento | M21: =IF('_AUX DASH'!$C$79="","",INDEX('BASE CONSOLIDADA'!$P$5:$P$129,'_AUX DASH'!$C$79)) -> Isabel Teixeira Malvar Pinto | O21: =IF('_AUX DASH'!$C$79="","",INDEX('BASE CONSOLIDADA'!$V$5:$V$129,'_AUX DASH'!$C$79)) -> Concluir elaboração
B22: =IF('_AUX DASH'!$C$80="","",INDEX('BASE CONSOLIDADA'!$U$5:$U$129,'_AUX DASH'!$C$80)) -> 6 | C22: =IF('_AUX DASH'!$C$80="","",INDEX('BASE CONSOLIDADA'!$A$5:$A$129,'_AUX DASH'!$C$80)) -> BRK-INS-01-012704-PT | F22: =IF('_AUX DASH'!$C$80="","",INDEX('BASE CONSOLIDADA'!$D$5:$D$129,'_AUX DASH'!$C$80)) -> ONTROLE DE QUALIDADE DE RESINAS DE PE, PP E EVA - REGIONAL RS | J22: =IF('_AUX DASH'!$C$80="","",INDEX('BASE CONSOLIDADA'!$G$5:$G$129,'_AUX DASH'!$C$80)) -> PE/PP | K22: =IF('_AUX DASH'!$C$80="","",INDEX('BASE CONSOLIDADA'!$R$5:$R$129,'_AUX DASH'!$C$80)) -> Validar cadastro | M22: =IF('_AUX DASH'!$C$80="","",INDEX('BASE CONSOLIDADA'!$P$5:$P$129,'_AUX DASH'!$C$80)) -> Cleiton Leandro Zimmermann Pereira | O22: =IF('_AUX DASH'!$C$80="","",INDEX('BASE CONSOLIDADA'!$V$5:$V$129,'_AUX DASH'!$C$80)) -> Validar aplicabilidade
B23: =IF('_AUX DASH'!$C$81="","",INDEX('BASE CONSOLIDADA'!$U$5:$U$129,'_AUX DASH'!$C$81)) | C23: =IF('_AUX DASH'!$C$81="","",INDEX('BASE CONSOLIDADA'!$A$5:$A$129,'_AUX DASH'!$C$81)) | F23: =IF('_AUX DASH'!$C$81="","",INDEX('BASE CONSOLIDADA'!$D$5:$D$129,'_AUX DASH'!$C$81)) | J23: =IF('_AUX DASH'!$C$81="","",INDEX('BASE CONSOLIDADA'!$G$5:$G$129,'_AUX DASH'!$C$81)) | K23: =IF('_AUX DASH'!$C$81="","",INDEX('BASE CONSOLIDADA'!$R$5:$R$129,'_AUX DASH'!$C$81)) | M23: =IF('_AUX DASH'!$C$81="","",INDEX('BASE CONSOLIDADA'!$P$5:$P$129,'_AUX DASH'!$C$81)) | O23: =IF('_AUX DASH'!$C$81="","",INDEX('BASE CONSOLIDADA'!$V$5:$V$129,'_AUX DASH'!$C$81))
B24: =IF('_AUX DASH'!$C$82="","",INDEX('BASE CONSOLIDADA'!$U$5:$U$129,'_AUX DASH'!$C$82)) | C24: =IF('_AUX DASH'!$C$82="","",INDEX('BASE CONSOLIDADA'!$A$5:$A$129,'_AUX DASH'!$C$82)) | F24: =IF('_AUX DASH'!$C$82="","",INDEX('BASE CONSOLIDADA'!$D$5:$D$129,'_AUX DASH'!$C$82)) | J24: =IF('_AUX DASH'!$C$82="","",INDEX('BASE CONSOLIDADA'!$G$5:$G$129,'_AUX DASH'!$C$82)) | K24: =IF('_AUX DASH'!$C$82="","",INDEX('BASE CONSOLIDADA'!$R$5:$R$129,'_AUX DASH'!$C$82)) | M24: =IF('_AUX DASH'!$C$82="","",INDEX('BASE CONSOLIDADA'!$P$5:$P$129,'_AUX DASH'!$C$82)) | O24: =IF('_AUX DASH'!$C$82="","",INDEX('BASE CONSOLIDADA'!$V$5:$V$129,'_AUX DASH'!$C$82))
B27: ▤ CARTEIRA POR ÁREA | J27: ▦ MATRIZ ÁREA × SITUAÇÃO | S27: ◉ CARTEIRA POR RESPONSÁVEL
B28: Código único · compartilhados em categoria própria | J28: Onde está concentrado o risco | S28: Para acompanhamento — não é ranking de desempenho
J29: Área | L29: Ação imed. | M29: Validar | N29: Em trat. | O29: Planejar | P29: Regular | Q29: Inativo | S29: Responsável | V29: Total | W29: Em trat. | X29: Ação/ valid. | Y29: 12 m
J30: Q4 | L30: =COUNTIFS('BASE CONSOLIDADA'!$W$5:$W$129,1,'BASE CONSOLIDADA'!$G$5:$G$129,$J30,'BASE CONSOLIDADA'!$R$5:$R$129,"Ação imediata") -> 0 | M30: =COUNTIFS('BASE CONSOLIDADA'!$W$5:$W$129,1,'BASE CONSOLIDADA'!$G$5:$G$129,$J30,'BASE CONSOLIDADA'!$R$5:$R$129,"Validar cadastro") -> 1 | N30: =COUNTIFS('BASE CONSOLIDADA'!$W$5:$W$129,1,'BASE CONSOLIDADA'!$G$5:$G$129,$J30,'BASE CONSOLIDADA'!$R$5:$R$129,"Em tratamento") -> 2 | O30: =COUNTIFS('BASE CONSOLIDADA'!$W$5:$W$129,1,'BASE CONSOLIDADA'!$G$5:$G$129,$J30,'BASE CONSOLIDADA'!$R$5:$R$129,"Planejar revisão") -> 2 | P30: =COUNTIFS('BASE CONSOLIDADA'!$W$5:$W$129,1,'BASE CONSOLIDADA'!$G$5:$G$129,$J30,'BASE CONSOLIDADA'!$R$5:$R$129,"Regular") -> 51 | Q30: =COUNTIFS('BASE CONSOLIDADA'!$W$5:$W$129,1,'BASE CONSOLIDADA'!$G$5:$G$129,$J30,'BASE CONSOLIDADA'!$R$5:$R$129,"Inativo") -> 2 | S30: =IF('_AUX DASH'!$J$50="","",INDEX('_AUX DASH'!$K$50:$K$69,'_AUX DASH'!$J$50)) -> Ana Araujo | V30: =IF('_AUX DASH'!$J$50="","",INDEX('_AUX DASH'!$B$50:$B$69,'_AUX DASH'!$J$50)) -> 46 | W30: =IF('_AUX DASH'!$J$50="","",INDEX('_AUX DASH'!$C$50:$C$69,'_AUX DASH'!$J$50)) -> 1 | X30: =IF('_AUX DASH'!$J$50="","",INDEX('_AUX DASH'!$D$50:$D$69,'_AUX DASH'!$J$50)) -> 2 | Y30: =IF('_AUX DASH'!$J$50="","",INDEX('_AUX DASH'!$E$50:$E$69,'_AUX DASH'!$J$50)) -> 3
J31: AOL | L31: =COUNTIFS('BASE CONSOLIDADA'!$W$5:$W$129,1,'BASE CONSOLIDADA'!$G$5:$G$129,$J31,'BASE CONSOLIDADA'!$R$5:$R$129,"Ação imediata") -> 0 | M31: =COUNTIFS('BASE CONSOLIDADA'!$W$5:$W$129,1,'BASE CONSOLIDADA'!$G$5:$G$129,$J31,'BASE CONSOLIDADA'!$R$5:$R$129,"Validar cadastro") -> 0 | N31: =COUNTIFS('BASE CONSOLIDADA'!$W$5:$W$129,1,'BASE CONSOLIDADA'!$G$5:$G$129,$J31,'BASE CONSOLIDADA'!$R$5:$R$129,"Em tratamento") -> 0 | O31: =COUNTIFS('BASE CONSOLIDADA'!$W$5:$W$129,1,'BASE CONSOLIDADA'!$G$5:$G$129,$J31,'BASE CONSOLIDADA'!$R$5:$R$129,"Planejar revisão") -> 3 | P31: =COUNTIFS('BASE CONSOLIDADA'!$W$5:$W$129,1,'BASE CONSOLIDADA'!$G$5:$G$129,$J31,'BASE CONSOLIDADA'!$R$5:$R$129,"Regular") -> 20 | Q31: =COUNTIFS('BASE CONSOLIDADA'!$W$5:$W$129,1,'BASE CONSOLIDADA'!$G$5:$G$129,$J31,'BASE CONSOLIDADA'!$R$5:$R$129,"Inativo") -> 0 | S31: =IF('_AUX DASH'!$J$51="","",INDEX('_AUX DASH'!$K$50:$K$69,'_AUX DASH'!$J$51)) -> Cleiton Pereira | V31: =IF('_AUX DASH'!$J$51="","",INDEX('_AUX DASH'!$B$50:$B$69,'_AUX DASH'!$J$51)) -> 1 | W31: =IF('_AUX DASH'!$J$51="","",INDEX('_AUX DASH'!$C$50:$C$69,'_AUX DASH'!$J$51)) -> 0 | X31: =IF('_AUX DASH'!$J$51="","",INDEX('_AUX DASH'!$D$50:$D$69,'_AUX DASH'!$J$51)) -> 1 | Y31: =IF('_AUX DASH'!$J$51="","",INDEX('_AUX DASH'!$E$50:$E$69,'_AUX DASH'!$J$51)) -> 0
J32: PE | L32: =COUNTIFS('BASE CONSOLIDADA'!$W$5:$W$129,1,'BASE CONSOLIDADA'!$G$5:$G$129,$J32,'BASE CONSOLIDADA'!$R$5:$R$129,"Ação imediata") -> 0 | M32: =COUNTIFS('BASE CONSOLIDADA'!$W$5:$W$129,1,'BASE CONSOLIDADA'!$G$5:$G$129,$J32,'BASE CONSOLIDADA'!$R$5:$R$129,"Validar cadastro") -> 0 | N32: =COUNTIFS('BASE CONSOLIDADA'!$W$5:$W$129,1,'BASE CONSOLIDADA'!$G$5:$G$129,$J32,'BASE CONSOLIDADA'!$R$5:$R$129,"Em tratamento") -> 0 | O32: =COUNTIFS('BASE CONSOLIDADA'!$W$5:$W$129,1,'BASE CONSOLIDADA'!$G$5:$G$129,$J32,'BASE CONSOLIDADA'!$R$5:$R$129,"Planejar revisão") -> 1 | P32: =COUNTIFS('BASE CONSOLIDADA'!$W$5:$W$129,1,'BASE CONSOLIDADA'!$G$5:$G$129,$J32,'BASE CONSOLIDADA'!$R$5:$R$129,"Regular") -> 10 | Q32: =COUNTIFS('BASE CONSOLIDADA'!$W$5:$W$129,1,'BASE CONSOLIDADA'!$G$5:$G$129,$J32,'BASE CONSOLIDADA'!$R$5:$R$129,"Inativo") -> 0 | S32: =IF('_AUX DASH'!$J$52="","",INDEX('_AUX DASH'!$K$50:$K$69,'_AUX DASH'!$J$52)) -> Isabel Pinto | V32: =IF('_AUX DASH'!$J$52="","",INDEX('_AUX DASH'!$B$50:$B$69,'_AUX DASH'!$J$52)) -> 2 | W32: =IF('_AUX DASH'!$J$52="","",INDEX('_AUX DASH'!$C$50:$C$69,'_AUX DASH'!$J$52)) -> 1 | X32: =IF('_AUX DASH'!$J$52="","",INDEX('_AUX DASH'!$D$50:$D$69,'_AUX DASH'!$J$52)) -> 0 | Y32: =IF('_AUX DASH'!$J$52="","",INDEX('_AUX DASH'!$E$50:$E$69,'_AUX DASH'!$J$52)) -> 0
J33: COMUM | L33: =COUNTIFS('BASE CONSOLIDADA'!$W$5:$W$129,1,'BASE CONSOLIDADA'!$G$5:$G$129,$J33,'BASE CONSOLIDADA'!$R$5:$R$129,"Ação imediata") -> 1 | M33: =COUNTIFS('BASE CONSOLIDADA'!$W$5:$W$129,1,'BASE CONSOLIDADA'!$G$5:$G$129,$J33,'BASE CONSOLIDADA'!$R$5:$R$129,"Validar cadastro") -> 0 | N33: =COUNTIFS('BASE CONSOLIDADA'!$W$5:$W$129,1,'BASE CONSOLIDADA'!$G$5:$G$129,$J33,'BASE CONSOLIDADA'!$R$5:$R$129,"Em tratamento") -> 0 | O33: =COUNTIFS('BASE CONSOLIDADA'!$W$5:$W$129,1,'BASE CONSOLIDADA'!$G$5:$G$129,$J33,'BASE CONSOLIDADA'!$R$5:$R$129,"Planejar revisão") -> 3 | P33: =COUNTIFS('BASE CONSOLIDADA'!$W$5:$W$129,1,'BASE CONSOLIDADA'!$G$5:$G$129,$J33,'BASE CONSOLIDADA'!$R$5:$R$129,"Regular") -> 7 | Q33: =COUNTIFS('BASE CONSOLIDADA'!$W$5:$W$129,1,'BASE CONSOLIDADA'!$G$5:$G$129,$J33,'BASE CONSOLIDADA'!$R$5:$R$129,"Inativo") -> 0 | S33: =IF('_AUX DASH'!$J$53="","",INDEX('_AUX DASH'!$K$50:$K$69,'_AUX DASH'!$J$53)) -> Bruna Goldschmidt | V33: =IF('_AUX DASH'!$J$53="","",INDEX('_AUX DASH'!$B$50:$B$69,'_AUX DASH'!$J$53)) -> 1 | W33: =IF('_AUX DASH'!$J$53="","",INDEX('_AUX DASH'!$C$50:$C$69,'_AUX DASH'!$J$53)) -> 1 | X33: =IF('_AUX DASH'!$J$53="","",INDEX('_AUX DASH'!$D$50:$D$69,'_AUX DASH'!$J$53)) -> 0 | Y33: =IF('_AUX DASH'!$J$53="","",INDEX('_AUX DASH'!$E$50:$E$69,'_AUX DASH'!$J$53)) -> 0
J34: PP | L34: =COUNTIFS('BASE CONSOLIDADA'!$W$5:$W$129,1,'BASE CONSOLIDADA'!$G$5:$G$129,$J34,'BASE CONSOLIDADA'!$R$5:$R$129,"Ação imediata") -> 0 | M34: =COUNTIFS('BASE CONSOLIDADA'!$W$5:$W$129,1,'BASE CONSOLIDADA'!$G$5:$G$129,$J34,'BASE CONSOLIDADA'!$R$5:$R$129,"Validar cadastro") -> 0 | N34: =COUNTIFS('BASE CONSOLIDADA'!$W$5:$W$129,1,'BASE CONSOLIDADA'!$G$5:$G$129,$J34,'BASE CONSOLIDADA'!$R$5:$R$129,"Em tratamento") -> 1 | O34: =COUNTIFS('BASE CONSOLIDADA'!$W$5:$W$129,1,'BASE CONSOLIDADA'!$G$5:$G$129,$J34,'BASE CONSOLIDADA'!$R$5:$R$129,"Planejar revisão") -> 2 | P34: =COUNTIFS('BASE CONSOLIDADA'!$W$5:$W$129,1,'BASE CONSOLIDADA'!$G$5:$G$129,$J34,'BASE CONSOLIDADA'!$R$5:$R$129,"Regular") -> 6 | Q34: =COUNTIFS('BASE CONSOLIDADA'!$W$5:$W$129,1,'BASE CONSOLIDADA'!$G$5:$G$129,$J34,'BASE CONSOLIDADA'!$R$5:$R$129,"Inativo") -> 1 | S34: =IF('_AUX DASH'!$J$54="","",INDEX('_AUX DASH'!$K$50:$K$69,'_AUX DASH'!$J$54)) -> Ana Oliveira | V34: =IF('_AUX DASH'!$J$54="","",INDEX('_AUX DASH'!$B$50:$B$69,'_AUX DASH'!$J$54)) -> 26 | W34: =IF('_AUX DASH'!$J$54="","",INDEX('_AUX DASH'!$C$50:$C$69,'_AUX DASH'!$J$54)) -> 0 | X34: =IF('_AUX DASH'!$J$54="","",INDEX('_AUX DASH'!$D$50:$D$69,'_AUX DASH'!$J$54)) -> 0 | Y34: =IF('_AUX DASH'!$J$54="","",INDEX('_AUX DASH'!$E$50:$E$69,'_AUX DASH'!$J$54)) -> 3
J35: PE/PP | L35: =COUNTIFS('BASE CONSOLIDADA'!$W$5:$W$129,1,'BASE CONSOLIDADA'!$G$5:$G$129,$J35,'BASE CONSOLIDADA'!$R$5:$R$129,"Ação imediata") -> 0 | M35: =COUNTIFS('BASE CONSOLIDADA'!$W$5:$W$129,1,'BASE CONSOLIDADA'!$G$5:$G$129,$J35,'BASE CONSOLIDADA'!$R$5:$R$129,"Validar cadastro") -> 1 | N35: =COUNTIFS('BASE CONSOLIDADA'!$W$5:$W$129,1,'BASE CONSOLIDADA'!$G$5:$G$129,$J35,'BASE CONSOLIDADA'!$R$5:$R$129,"Em tratamento") -> 0 | O35: =COUNTIFS('BASE CONSOLIDADA'!$W$5:$W$129,1,'BASE CONSOLIDADA'!$G$5:$G$129,$J35,'BASE CONSOLIDADA'!$R$5:$R$129,"Planejar revisão") -> 1 | P35: =COUNTIFS('BASE CONSOLIDADA'!$W$5:$W$129,1,'BASE CONSOLIDADA'!$G$5:$G$129,$J35,'BASE CONSOLIDADA'!$R$5:$R$129,"Regular") -> 7 | Q35: =COUNTIFS('BASE CONSOLIDADA'!$W$5:$W$129,1,'BASE CONSOLIDADA'!$G$5:$G$129,$J35,'BASE CONSOLIDADA'!$R$5:$R$129,"Inativo") -> 0 | S35: =IF('_AUX DASH'!$J$55="","",INDEX('_AUX DASH'!$K$50:$K$69,'_AUX DASH'!$J$55)) -> Fatima Guterres | V35: =IF('_AUX DASH'!$J$55="","",INDEX('_AUX DASH'!$B$50:$B$69,'_AUX DASH'!$J$55)) -> 11 | W35: =IF('_AUX DASH'!$J$55="","",INDEX('_AUX DASH'!$C$50:$C$69,'_AUX DASH'!$J$55)) -> 0 | X35: =IF('_AUX DASH'!$J$55="","",INDEX('_AUX DASH'!$D$50:$D$69,'_AUX DASH'!$J$55)) -> 0 | Y35: =IF('_AUX DASH'!$J$55="","",INDEX('_AUX DASH'!$E$50:$E$69,'_AUX DASH'!$J$55)) -> 2
J36: Q4/AOL | L36: =COUNTIFS('BASE CONSOLIDADA'!$W$5:$W$129,1,'BASE CONSOLIDADA'!$G$5:$G$129,$J36,'BASE CONSOLIDADA'!$R$5:$R$129,"Ação imediata") -> 0 | M36: =COUNTIFS('BASE CONSOLIDADA'!$W$5:$W$129,1,'BASE CONSOLIDADA'!$G$5:$G$129,$J36,'BASE CONSOLIDADA'!$R$5:$R$129,"Validar cadastro") -> 0 | N36: =COUNTIFS('BASE CONSOLIDADA'!$W$5:$W$129,1,'BASE CONSOLIDADA'!$G$5:$G$129,$J36,'BASE CONSOLIDADA'!$R$5:$R$129,"Em tratamento") -> 0 | O36: =COUNTIFS('BASE CONSOLIDADA'!$W$5:$W$129,1,'BASE CONSOLIDADA'!$G$5:$G$129,$J36,'BASE CONSOLIDADA'!$R$5:$R$129,"Planejar revisão") -> 0 | P36: =COUNTIFS('BASE CONSOLIDADA'!$W$5:$W$129,1,'BASE CONSOLIDADA'!$G$5:$G$129,$J36,'BASE CONSOLIDADA'!$R$5:$R$129,"Regular") -> 3 | Q36: =COUNTIFS('BASE CONSOLIDADA'!$W$5:$W$129,1,'BASE CONSOLIDADA'!$G$5:$G$129,$J36,'BASE CONSOLIDADA'!$R$5:$R$129,"Inativo") -> 0 | S36: =IF('_AUX DASH'!$J$56="","",INDEX('_AUX DASH'!$K$50:$K$69,'_AUX DASH'!$J$56)) -> Elton Taborda | V36: =IF('_AUX DASH'!$J$56="","",INDEX('_AUX DASH'!$B$50:$B$69,'_AUX DASH'!$J$56)) -> 2 | W36: =IF('_AUX DASH'!$J$56="","",INDEX('_AUX DASH'!$C$50:$C$69,'_AUX DASH'!$J$56)) -> 0 | X36: =IF('_AUX DASH'!$J$56="","",INDEX('_AUX DASH'!$D$50:$D$69,'_AUX DASH'!$J$56)) -> 0 | Y36: =IF('_AUX DASH'!$J$56="","",INDEX('_AUX DASH'!$E$50:$E$69,'_AUX DASH'!$J$56)) -> 2
J37: Total | L37: =SUM(L30:L36) -> 1 | M37: =SUM(M30:M36) -> 2 | N37: =SUM(N30:N36) -> 3 | O37: =SUM(O30:O36) -> 12 | P37: =SUM(P30:P36) -> 104 | Q37: =SUM(Q30:Q36) -> 3 | S37: =IF('_AUX DASH'!$J$57="","",INDEX('_AUX DASH'!$K$50:$K$69,'_AUX DASH'!$J$57)) -> Lais Nascimento | V37: =IF('_AUX DASH'!$J$57="","",INDEX('_AUX DASH'!$B$50:$B$69,'_AUX DASH'!$J$57)) -> 2 | W37: =IF('_AUX DASH'!$J$57="","",INDEX('_AUX DASH'!$C$50:$C$69,'_AUX DASH'!$J$57)) -> 0 | X37: =IF('_AUX DASH'!$J$57="","",INDEX('_AUX DASH'!$D$50:$D$69,'_AUX DASH'!$J$57)) -> 0 | Y37: =IF('_AUX DASH'!$J$57="","",INDEX('_AUX DASH'!$E$50:$E$69,'_AUX DASH'!$J$57)) -> 1
S38: =COUNTIF('_AUX DASH'!$B$50:$B$69,">0")&" responsáveis com carteira · lista completa em _AUX DASH" -> 20 responsáveis com carteira · lista completa em _AUX DASH
B40: ▣ OUTROS CONTROLES DOCUMENTAIS · não somados aos KPIs de instruções
B41: NDocs FMG e ANX | E41: Documentos Transversais | I41: LPP | L41: AST AOL | P41: AST Geral | S41: RT's | W41: MO
B42: =COUNTA('NDocs FMG e ANX'!$B$3:$B$42) -> 38 | E42: =COUNTA('Documentos Transversais'!$B$3:$B$57) -> 51 | I42: =COUNTA(LPP!$A$3:$A$124) -> 122 | L42: =COUNTA('AST AOL'!$A$3:$A$43) -> 35 | P42: =COUNTA('AST Geral'!$A$3:$A$43) -> 23 | S42: =COUNTA('RT''s'!$B$3:$B$16) -> 9 | W42: =COUNTA(MO!$B$3:$B$20) -> 5
B43: =IF(SUMPRODUCT(--ISERROR('NDocs FMG e ANX'!$A$3:$N$42))>0,"⚠ "&SUMPRODUCT(--ISERROR('NDocs FMG e ANX'!$A$3:$N$42))&" erro(s) legado(s)","Abrir aba →") -> Abrir aba → | E43: =IF(SUMPRODUCT(--ISERROR('Documentos Transversais'!$A$3:$N$57))>0,"⚠ "&SUMPRODUCT(--ISERROR('Documentos Transversais'!$A$3:$N$57))&" erro(s) legado(s)","Abrir aba →") -> Abrir aba → | I43: =IF(SUMPRODUCT(--ISERROR(LPP!$A$3:$N$124))>0,"⚠ "&SUMPRODUCT(--ISERROR(LPP!$A$3:$N$124))&" erro(s) legado(s)","Abrir aba →") -> ⚠ 25 erro(s) legado(s) | L43: =IF(SUMPRODUCT(--ISERROR('AST AOL'!$A$3:$N$43))>0,"⚠ "&SUMPRODUCT(--ISERROR('AST AOL'!$A$3:$N$43))&" erro(s) legado(s)","Abrir aba →") -> Abrir aba → | P43: =IF(SUMPRODUCT(--ISERROR('AST Geral'!$A$3:$N$43))>0,"⚠ "&SUMPRODUCT(--ISERROR('AST Geral'!$A$3:$N$43))&" erro(s) legado(s)","Abrir aba →") -> ⚠ 1 erro(s) legado(s) | S43: =IF(SUMPRODUCT(--ISERROR('RT''s'!$A$3:$N$16))>0,"⚠ "&SUMPRODUCT(--ISERROR('RT''s'!$A$3:$N$16))&" erro(s) legado(s)","Abrir aba →") -> Abrir aba → | W43: =IF(SUMPRODUCT(--ISERROR(MO!$A$3:$N$20))>0,"⚠ "&SUMPRODUCT(--ISERROR(MO!$A$3:$N$20))&" erro(s) legado(s)","Abrir aba →") -> Abrir aba →
B45: Saúde documental = (Regular + Planejar revisão) ÷ instruções ativas. Ativas = todas, exceto Canceladas e Fora de Uso. Mede "quantas instruções em uso estão aprovadas e dentro da validade".
B46: Situação Gerencial é camada analítica: o Status oficial do NDocs é preservado na Base Consolidada (coluna E). Regras completas em QUALIDADE BASE › Regras.
B47: Contagem por Código NDocs único (125 códigos de 131 linhas de instrução). Documento compartilhado entre áreas conta uma vez; o filtro de Área inclui os compartilhados (ex.: Q4 inclui Q4/AOL).

Sheet PESQUISA
B2: ⌕ PESQUISA DE DOCUMENTO
B3: Localize por Código NDocs, número antigo (IT …) ou parte do título — sem diferenciar maiúsculas
B4: ⌂ Início | D4: ▦ Dashboard | F4: ⌕ Pesquisa | H4: ☰ Base | J4: ✓ Qualidade | K4: ▤ Outros
B5: DIGITE NA CAIXA ABAIXO E TECLE ENTER
B6: 🔍 | C6: Termo: | D6: OXIGÊNIO | F6: =IF(qBusca="","Digite um termo para pesquisar",COUNT('BASE CONSOLIDADA'!$Z$5:$Z$129)&" resultado(s) · exibindo até 15") -> 7 resultado(s) · exibindo até 15
B8: # | C8: Código NDocs | D8: Antigo nº | E8: Título | F8: Versão | G8: Status NDocs | H8: Validade | I8: Área | J8: Responsável | K8: Situação Gerencial
B9: =IF(COUNT('BASE CONSOLIDADA'!$Z$5:$Z$129)<1,"",1) -> 1 | C9: =IF($B9="","",INDEX('BASE CONSOLIDADA'!$A$1:$A$129,SMALL('BASE CONSOLIDADA'!$Z$5:$Z$129,$B9))) -> BRK-INS-01-016238-PT | D9: =IF($B9="","",INDEX('BASE CONSOLIDADA'!$C$1:$C$129,SMALL('BASE CONSOLIDADA'!$Z$5:$Z$129,$B9))) -> IT 5020-00175 | E9: =IF($B9="","",INDEX('BASE CONSOLIDADA'!$D$1:$D$129,SMALL('BASE CONSOLIDADA'!$Z$5:$Z$129,$B9))) -> DETERMINAÇÃO DE OXIGÊNIO EM GASES POR TELEDYNE | F9: =IF($B9="","",INDEX('BASE CONSOLIDADA'!$B$1:$B$129,SMALL('BASE CONSOLIDADA'!$Z$5:$Z$129,$B9))) -> 7.0 | G9: =IF($B9="","",INDEX('BASE CONSOLIDADA'!$E$1:$E$129,SMALL('BASE CONSOLIDADA'!$Z$5:$Z$129,$B9))) -> Aprovado | H9: =IF($B9="","",INDEX('BASE CONSOLIDADA'!$O$1:$O$129,SMALL('BASE CONSOLIDADA'!$Z$5:$Z$129,$B9))) -> 48104 | I9: =IF($B9="","",INDEX('BASE CONSOLIDADA'!$G$1:$G$129,SMALL('BASE CONSOLIDADA'!$Z$5:$Z$129,$B9))) -> Q4/AOL | J9: =IF($B9="","",INDEX('BASE CONSOLIDADA'!$P$1:$P$129,SMALL('BASE CONSOLIDADA'!$Z$5:$Z$129,$B9))) -> Ana Claudia Sergio De Oliveira | K9: =IF($B9="","",INDEX('BASE CONSOLIDADA'!$R$1:$R$129,SMALL('BASE CONSOLIDADA'!$Z$5:$Z$129,$B9))) -> Regular
B10: =IF(COUNT('BASE CONSOLIDADA'!$Z$5:$Z$129)<2,"",2) -> 2 | C10: =IF($B10="","",INDEX('BASE CONSOLIDADA'!$A$1:$A$129,SMALL('BASE CONSOLIDADA'!$Z$5:$Z$129,$B10))) -> BRK-INS-01-016427-PT | D10: =IF($B10="","",INDEX('BASE CONSOLIDADA'!$C$1:$C$129,SMALL('BASE CONSOLIDADA'!$Z$5:$Z$129,$B10))) -> IT 5020-00216 | E10: =IF($B10="","",INDEX('BASE CONSOLIDADA'!$D$1:$D$129,SMALL('BASE CONSOLIDADA'!$Z$5:$Z$129,$B10))) -> DETERMINAÇÃO DA DEMANDA QUÍMICA DE OXIGÊNIO EM ÁGUAS E EFLUENTES | F10: =IF($B10="","",INDEX('BASE CONSOLIDADA'!$B$1:$B$129,SMALL('BASE CONSOLIDADA'!$Z$5:$Z$129,$B10))) -> 9.0 | G10: =IF($B10="","",INDEX('BASE CONSOLIDADA'!$E$1:$E$129,SMALL('BASE CONSOLIDADA'!$Z$5:$Z$129,$B10))) -> Aprovado | H10: =IF($B10="","",INDEX('BASE CONSOLIDADA'!$O$1:$O$129,SMALL('BASE CONSOLIDADA'!$Z$5:$Z$129,$B10))) -> 46846 | I10: =IF($B10="","",INDEX('BASE CONSOLIDADA'!$G$1:$G$129,SMALL('BASE CONSOLIDADA'!$Z$5:$Z$129,$B10))) -> Q4 | J10: =IF($B10="","",INDEX('BASE CONSOLIDADA'!$P$1:$P$129,SMALL('BASE CONSOLIDADA'!$Z$5:$Z$129,$B10))) -> Ana Carla Da Cruz Araujo | K10: =IF($B10="","",INDEX('BASE CONSOLIDADA'!$R$1:$R$129,SMALL('BASE CONSOLIDADA'!$Z$5:$Z$129,$B10))) -> Regular
B11: =IF(COUNT('BASE CONSOLIDADA'!$Z$5:$Z$129)<3,"",3) -> 3 | C11: =IF($B11="","",INDEX('BASE CONSOLIDADA'!$A$1:$A$129,SMALL('BASE CONSOLIDADA'!$Z$5:$Z$129,$B11))) -> BRK-INS-01-016793-PT | D11: =IF($B11="","",INDEX('BASE CONSOLIDADA'!$C$1:$C$129,SMALL('BASE CONSOLIDADA'!$Z$5:$Z$129,$B11))) -> IT 6010-00078 | E11: =IF($B11="","",INDEX('BASE CONSOLIDADA'!$D$1:$D$129,SMALL('BASE CONSOLIDADA'!$Z$5:$Z$129,$B11))) -> DETERMINAÇÃO DE OXIGÊNIO EM GASES POR TELEDYNE MOD 3010 | F11: =IF($B11="","",INDEX('BASE CONSOLIDADA'!$B$1:$B$129,SMALL('BASE CONSOLIDADA'!$Z$5:$Z$129,$B11))) -> 5.0 | G11: =IF($B11="","",INDEX('BASE CONSOLIDADA'!$E$1:$E$129,SMALL('BASE CONSOLIDADA'!$Z$5:$Z$129,$B11))) -> Aprovado | H11: =IF($B11="","",INDEX('BASE CONSOLIDADA'!$O$1:$O$129,SMALL('BASE CONSOLIDADA'!$Z$5:$Z$129,$B11))) -> 46689 | I11: =IF($B11="","",INDEX('BASE CONSOLIDADA'!$G$1:$G$129,SMALL('BASE CONSOLIDADA'!$Z$5:$Z$129,$B11))) -> Q4/AOL | J11: =IF($B11="","",INDEX('BASE CONSOLIDADA'!$P$1:$P$129,SMALL('BASE CONSOLIDADA'!$Z$5:$Z$129,$B11))) -> Ana Claudia Sergio De Oliveira | K11: =IF($B11="","",INDEX('BASE CONSOLIDADA'!$R$1:$R$129,SMALL('BASE CONSOLIDADA'!$Z$5:$Z$129,$B11))) -> Regular
B12: =IF(COUNT('BASE CONSOLIDADA'!$Z$5:$Z$129)<4,"",4) -> 4 | C12: =IF($B12="","",INDEX('BASE CONSOLIDADA'!$A$1:$A$129,SMALL('BASE CONSOLIDADA'!$Z$5:$Z$129,$B12))) -> BRK-INS-01-011812-PT | D12: =IF($B12="","",INDEX('BASE CONSOLIDADA'!$C$1:$C$129,SMALL('BASE CONSOLIDADA'!$Z$5:$Z$129,$B12))) -> IT 5020-01340 | E12: =IF($B12="","",INDEX('BASE CONSOLIDADA'!$D$1:$D$129,SMALL('BASE CONSOLIDADA'!$Z$5:$Z$129,$B12))) -> DETERMINAÇÃO DE OXIGÊNIO PPM MOL EM GASES | F12: =IF($B12="","",INDEX('BASE CONSOLIDADA'!$B$1:$B$129,SMALL('BASE CONSOLIDADA'!$Z$5:$Z$129,$B12))) -> 6.0 | G12: =IF($B12="","",INDEX('BASE CONSOLIDADA'!$E$1:$E$129,SMALL('BASE CONSOLIDADA'!$Z$5:$Z$129,$B12))) -> Aprovado | H12: =IF($B12="","",INDEX('BASE CONSOLIDADA'!$O$1:$O$129,SMALL('BASE CONSOLIDADA'!$Z$5:$Z$129,$B12))) -> 47688 | I12: =IF($B12="","",INDEX('BASE CONSOLIDADA'!$G$1:$G$129,SMALL('BASE CONSOLIDADA'!$Z$5:$Z$129,$B12))) -> Q4 | J12: =IF($B12="","",INDEX('BASE CONSOLIDADA'!$P$1:$P$129,SMALL('BASE CONSOLIDADA'!$Z$5:$Z$129,$B12))) -> Camila Moraes De Oliveira | K12: =IF($B12="","",INDEX('BASE CONSOLIDADA'!$R$1:$R$129,SMALL('BASE CONSOLIDADA'!$Z$5:$Z$129,$B12))) -> Regular
B13: =IF(COUNT('BASE CONSOLIDADA'!$Z$5:$Z$129)<5,"",5) -> 5 | C13: =IF($B13="","",INDEX('BASE CONSOLIDADA'!$A$1:$A$129,SMALL('BASE CONSOLIDADA'!$Z$5:$Z$129,$B13))) -> BRK-INS-01-016681-PT | D13: =IF($B13="","",INDEX('BASE CONSOLIDADA'!$C$1:$C$129,SMALL('BASE CONSOLIDADA'!$Z$5:$Z$129,$B13))) -> IT 5030-02940-PT | E13: =IF($B13="","",INDEX('BASE CONSOLIDADA'!$D$1:$D$129,SMALL('BASE CONSOLIDADA'!$Z$5:$Z$129,$B13))) -> AJUSTECALIBRAÇÃO DOS ANALISADORES DE OXIGÊNIO DISSOLVIDO | F13: =IF($B13="","",INDEX('BASE CONSOLIDADA'!$B$1:$B$129,SMALL('BASE CONSOLIDADA'!$Z$5:$Z$129,$B13))) -> 3.0 | G13: =IF($B13="","",INDEX('BASE CONSOLIDADA'!$E$1:$E$129,SMALL('BASE CONSOLIDADA'!$Z$5:$Z$129,$B13))) -> Aprovado | H13: =IF($B13="","",INDEX('BASE CONSOLIDADA'!$O$1:$O$129,SMALL('BASE CONSOLIDADA'!$Z$5:$Z$129,$B13))) -> 48000 | I13: =IF($B13="","",INDEX('BASE CONSOLIDADA'!$G$1:$G$129,SMALL('BASE CONSOLIDADA'!$Z$5:$Z$129,$B13))) -> AOL | J13: =IF($B13="","",INDEX('BASE CONSOLIDADA'!$P$1:$P$129,SMALL('BASE CONSOLIDADA'!$Z$5:$Z$129,$B13))) -> Ana Claudia Sergio De Oliveira | K13: =IF($B13="","",INDEX('BASE CONSOLIDADA'!$R$1:$R$129,SMALL('BASE CONSOLIDADA'!$Z$5:$Z$129,$B13))) -> Regular
B14: =IF(COUNT('BASE CONSOLIDADA'!$Z$5:$Z$129)<6,"",6) -> 6 | C14: =IF($B14="","",INDEX('BASE CONSOLIDADA'!$A$1:$A$129,SMALL('BASE CONSOLIDADA'!$Z$5:$Z$129,$B14))) -> BRK-INS-01-016205-PT | D14: =IF($B14="","",INDEX('BASE CONSOLIDADA'!$C$1:$C$129,SMALL('BASE CONSOLIDADA'!$Z$5:$Z$129,$B14))) -> IT 5030-00248 | E14: =IF($B14="","",INDEX('BASE CONSOLIDADA'!$D$1:$D$129,SMALL('BASE CONSOLIDADA'!$Z$5:$Z$129,$B14))) -> AJUSTE E CALIBRAÇÃO DE ANALISADORES DE OXIGÊNIO DA SERVOMEX - DCX RJ | F14: =IF($B14="","",INDEX('BASE CONSOLIDADA'!$B$1:$B$129,SMALL('BASE CONSOLIDADA'!$Z$5:$Z$129,$B14))) -> 8.0 | G14: =IF($B14="","",INDEX('BASE CONSOLIDADA'!$E$1:$E$129,SMALL('BASE CONSOLIDADA'!$Z$5:$Z$129,$B14))) -> Aprovado | H14: =IF($B14="","",INDEX('BASE CONSOLIDADA'!$O$1:$O$129,SMALL('BASE CONSOLIDADA'!$Z$5:$Z$129,$B14))) -> 48104 | I14: =IF($B14="","",INDEX('BASE CONSOLIDADA'!$G$1:$G$129,SMALL('BASE CONSOLIDADA'!$Z$5:$Z$129,$B14))) -> AOL | J14: =IF($B14="","",INDEX('BASE CONSOLIDADA'!$P$1:$P$129,SMALL('BASE CONSOLIDADA'!$Z$5:$Z$129,$B14))) -> Ana Claudia Sergio De Oliveira | K14: =IF($B14="","",INDEX('BASE CONSOLIDADA'!$R$1:$R$129,SMALL('BASE CONSOLIDADA'!$Z$5:$Z$129,$B14))) -> Regular
B15: =IF(COUNT('BASE CONSOLIDADA'!$Z$5:$Z$129)<7,"",7) -> 7 | C15: =IF($B15="","",INDEX('BASE CONSOLIDADA'!$A$1:$A$129,SMALL('BASE CONSOLIDADA'!$Z$5:$Z$129,$B15))) -> BRK-INS-01-016748-PT | D15: =IF($B15="","",INDEX('BASE CONSOLIDADA'!$C$1:$C$129,SMALL('BASE CONSOLIDADA'!$Z$5:$Z$129,$B15))) -> IT 5030-02962-PT | E15: =IF($B15="","",INDEX('BASE CONSOLIDADA'!$D$1:$D$129,SMALL('BASE CONSOLIDADA'!$Z$5:$Z$129,$B15))) -> AJUSTE E CALIBRAÇÃO DOS ANALISADORES PORTÁTEIS DE OXIGÊNIO DISSOLVIDO | F15: =IF($B15="","",INDEX('BASE CONSOLIDADA'!$B$1:$B$129,SMALL('BASE CONSOLIDADA'!$Z$5:$Z$129,$B15))) -> 3.0 | G15: =IF($B15="","",INDEX('BASE CONSOLIDADA'!$E$1:$E$129,SMALL('BASE CONSOLIDADA'!$Z$5:$Z$129,$B15))) -> Aprovado | H15: =IF($B15="","",INDEX('BASE CONSOLIDADA'!$O$1:$O$129,SMALL('BASE CONSOLIDADA'!$Z$5:$Z$129,$B15))) -> 48008 | I15: =IF($B15="","",INDEX('BASE CONSOLIDADA'!$G$1:$G$129,SMALL('BASE CONSOLIDADA'!$Z$5:$Z$129,$B15))) -> AOL | J15: =IF($B15="","",INDEX('BASE CONSOLIDADA'!$P$1:$P$129,SMALL('BASE CONSOLIDADA'!$Z$5:$Z$129,$B15))) -> Ana Claudia Sergio De Oliveira | K15: =IF($B15="","",INDEX('BASE CONSOLIDADA'!$R$1:$R$129,SMALL('BASE CONSOLIDADA'!$Z$5:$Z$129,$B15))) -> Regular
B16: =IF(COUNT('BASE CONSOLIDADA'!$Z$5:$Z$129)<8,"",8) | C16: =IF($B16="","",INDEX('BASE CONSOLIDADA'!$A$1:$A$129,SMALL('BASE CONSOLIDADA'!$Z$5:$Z$129,$B16))) | D16: =IF($B16="","",INDEX('BASE CONSOLIDADA'!$C$1:$C$129,SMALL('BASE CONSOLIDADA'!$Z$5:$Z$129,$B16))) | E16: =IF($B16="","",INDEX('BASE CONSOLIDADA'!$D$1:$D$129,SMALL('BASE CONSOLIDADA'!$Z$5:$Z$129,$B16))) | F16: =IF($B16="","",INDEX('BASE CONSOLIDADA'!$B$1:$B$129,SMALL('BASE CONSOLIDADA'!$Z$5:$Z$129,$B16))) | G16: =IF($B16="","",INDEX('BASE CONSOLIDADA'!$E$1:$E$129,SMALL('BASE CONSOLIDADA'!$Z$5:$Z$129,$B16))) | H16: =IF($B16="","",INDEX('BASE CONSOLIDADA'!$O$1:$O$129,SMALL('BASE CONSOLIDADA'!$Z$5:$Z$129,$B16))) | I16: =IF($B16="","",INDEX('BASE CONSOLIDADA'!$G$1:$G$129,SMALL('BASE CONSOLIDADA'!$Z$5:$Z$129,$B16))) | J16: =IF($B16="","",INDEX('BASE CONSOLIDADA'!$P$1:$P$129,SMALL('BASE CONSOLIDADA'!$Z$5:$Z$129,$B16))) | K16: =IF($B16="","",INDEX('BASE CONSOLIDADA'!$R$1:$R$129,SMALL('BASE CONSOLIDADA'!$Z$5:$Z$129,$B16)))
B17: =IF(COUNT('BASE CONSOLIDADA'!$Z$5:$Z$129)<9,"",9) | C17: =IF($B17="","",INDEX('BASE CONSOLIDADA'!$A$1:$A$129,SMALL('BASE CONSOLIDADA'!$Z$5:$Z$129,$B17))) | D17: =IF($B17="","",INDEX('BASE CONSOLIDADA'!$C$1:$C$129,SMALL('BASE CONSOLIDADA'!$Z$5:$Z$129,$B17))) | E17: =IF($B17="","",INDEX('BASE CONSOLIDADA'!$D$1:$D$129,SMALL('BASE CONSOLIDADA'!$Z$5:$Z$129,$B17))) | F17: =IF($B17="","",INDEX('BASE CONSOLIDADA'!$B$1:$B$129,SMALL('BASE CONSOLIDADA'!$Z$5:$Z$129,$B17))) | G17: =IF($B17="","",INDEX('BASE CONSOLIDADA'!$E$1:$E$129,SMALL('BASE CONSOLIDADA'!$Z$5:$Z$129,$B17))) | H17: =IF($B17="","",INDEX('BASE CONSOLIDADA'!$O$1:$O$129,SMALL('BASE CONSOLIDADA'!$Z$5:$Z$129,$B17))) | I17: =IF($B17="","",INDEX('BASE CONSOLIDADA'!$G$1:$G$129,SMALL('BASE CONSOLIDADA'!$Z$5:$Z$129,$B17))) | J17: =IF($B17="","",INDEX('BASE CONSOLIDADA'!$P$1:$P$129,SMALL('BASE CONSOLIDADA'!$Z$5:$Z$129,$B17))) | K17: =IF($B17="","",INDEX('BASE CONSOLIDADA'!$R$1:$R$129,SMALL('BASE CONSOLIDADA'!$Z$5:$Z$129,$B17)))
B18: =IF(COUNT('BASE CONSOLIDADA'!$Z$5:$Z$129)<10,"",10) | C18: =IF($B18="","",INDEX('BASE CONSOLIDADA'!$A$1:$A$129,SMALL('BASE CONSOLIDADA'!$Z$5:$Z$129,$B18))) | D18: =IF($B18="","",INDEX('BASE CONSOLIDADA'!$C$1:$C$129,SMALL('BASE CONSOLIDADA'!$Z$5:$Z$129,$B18))) | E18: =IF($B18="","",INDEX('BASE CONSOLIDADA'!$D$1:$D$129,SMALL('BASE CONSOLIDADA'!$Z$5:$Z$129,$B18))) | F18: =IF($B18="","",INDEX('BASE CONSOLIDADA'!$B$1:$B$129,SMALL('BASE CONSOLIDADA'!$Z$5:$Z$129,$B18))) | G18: =IF($B18="","",INDEX('BASE CONSOLIDADA'!$E$1:$E$129,SMALL('BASE CONSOLIDADA'!$Z$5:$Z$129,$B18))) | H18: =IF($B18="","",INDEX('BASE CONSOLIDADA'!$O$1:$O$129,SMALL('BASE CONSOLIDADA'!$Z$5:$Z$129,$B18))) | I18: =IF($B18="","",INDEX('BASE CONSOLIDADA'!$G$1:$G$129,SMALL('BASE CONSOLIDADA'!$Z$5:$Z$129,$B18))) | J18: =IF($B18="","",INDEX('BASE CONSOLIDADA'!$P$1:$P$129,SMALL('BASE CONSOLIDADA'!$Z$5:$Z$129,$B18))) | K18: =IF($B18="","",INDEX('BASE CONSOLIDADA'!$R$1:$R$129,SMALL('BASE CONSOLIDADA'!$Z$5:$Z$129,$B18)))
B19: =IF(COUNT('BASE CONSOLIDADA'!$Z$5:$Z$129)<11,"",11) | C19: =IF($B19="","",INDEX('BASE CONSOLIDADA'!$A$1:$A$129,SMALL('BASE CONSOLIDADA'!$Z$5:$Z$129,$B19))) | D19: =IF($B19="","",INDEX('BASE CONSOLIDADA'!$C$1:$C$129,SMALL('BASE CONSOLIDADA'!$Z$5:$Z$129,$B19))) | E19: =IF($B19="","",INDEX('BASE CONSOLIDADA'!$D$1:$D$129,SMALL('BASE CONSOLIDADA'!$Z$5:$Z$129,$B19))) | F19: =IF($B19="","",INDEX('BASE CONSOLIDADA'!$B$1:$B$129,SMALL('BASE CONSOLIDADA'!$Z$5:$Z$129,$B19))) | G19: =IF($B19="","",INDEX('BASE CONSOLIDADA'!$E$1:$E$129,SMALL('BASE CONSOLIDADA'!$Z$5:$Z$129,$B19))) | H19: =IF($B19="","",INDEX('BASE CONSOLIDADA'!$O$1:$O$129,SMALL('BASE CONSOLIDADA'!$Z$5:$Z$129,$B19))) | I19: =IF($B19="","",INDEX('BASE CONSOLIDADA'!$G$1:$G$129,SMALL('BASE CONSOLIDADA'!$Z$5:$Z$129,$B19))) | J19: =IF($B19="","",INDEX('BASE CONSOLIDADA'!$P$1:$P$129,SMALL('BASE CONSOLIDADA'!$Z$5:$Z$129,$B19))) | K19: =IF($B19="","",INDEX('BASE CONSOLIDADA'!$R$1:$R$129,SMALL('BASE CONSOLIDADA'!$Z$5:$Z$129,$B19)))
B20: =IF(COUNT('BASE CONSOLIDADA'!$Z$5:$Z$129)<12,"",12) | C20: =IF($B20="","",INDEX('BASE CONSOLIDADA'!$A$1:$A$129,SMALL('BASE CONSOLIDADA'!$Z$5:$Z$129,$B20))) | D20: =IF($B20="","",INDEX('BASE CONSOLIDADA'!$C$1:$C$129,SMALL('BASE CONSOLIDADA'!$Z$5:$Z$129,$B20))) | E20: =IF($B20="","",INDEX('BASE CONSOLIDADA'!$D$1:$D$129,SMALL('BASE CONSOLIDADA'!$Z$5:$Z$129,$B20))) | F20: =IF($B20="","",INDEX('BASE CONSOLIDADA'!$B$1:$B$129,SMALL('BASE CONSOLIDADA'!$Z$5:$Z$129,$B20))) | G20: =IF($B20="","",INDEX('BASE CONSOLIDADA'!$E$1:$E$129,SMALL('BASE CONSOLIDADA'!$Z$5:$Z$129,$B20))) | H20: =IF($B20="","",INDEX('BASE CONSOLIDADA'!$O$1:$O$129,SMALL('BASE CONSOLIDADA'!$Z$5:$Z$129,$B20))) | I20: =IF($B20="","",INDEX('BASE CONSOLIDADA'!$G$1:$G$129,SMALL('BASE CONSOLIDADA'!$Z$5:$Z$129,$B20))) | J20: =IF($B20="","",INDEX('BASE CONSOLIDADA'!$P$1:$P$129,SMALL('BASE CONSOLIDADA'!$Z$5:$Z$129,$B20))) | K20: =IF($B20="","",INDEX('BASE CONSOLIDADA'!$R$1:$R$129,SMALL('BASE CONSOLIDADA'!$Z$5:$Z$129,$B20)))
B21: =IF(COUNT('BASE CONSOLIDADA'!$Z$5:$Z$129)<13,"",13) | C21: =IF($B21="","",INDEX('BASE CONSOLIDADA'!$A$1:$A$129,SMALL('BASE CONSOLIDADA'!$Z$5:$Z$129,$B21))) | D21: =IF($B21="","",INDEX('BASE CONSOLIDADA'!$C$1:$C$129,SMALL('BASE CONSOLIDADA'!$Z$5:$Z$129,$B21))) | E21: =IF($B21="","",INDEX('BASE CONSOLIDADA'!$D$1:$D$129,SMALL('BASE CONSOLIDADA'!$Z$5:$Z$129,$B21))) | F21: =IF($B21="","",INDEX('BASE CONSOLIDADA'!$B$1:$B$129,SMALL('BASE CONSOLIDADA'!$Z$5:$Z$129,$B21))) | G21: =IF($B21="","",INDEX('BASE CONSOLIDADA'!$E$1:$E$129,SMALL('BASE CONSOLIDADA'!$Z$5:$Z$129,$B21))) | H21: =IF($B21="","",INDEX('BASE CONSOLIDADA'!$O$1:$O$129,SMALL('BASE CONSOLIDADA'!$Z$5:$Z$129,$B21))) | I21: =IF($B21="","",INDEX('BASE CONSOLIDADA'!$G$1:$G$129,SMALL('BASE CONSOLIDADA'!$Z$5:$Z$129,$B21))) | J21: =IF($B21="","",INDEX('BASE CONSOLIDADA'!$P$1:$P$129,SMALL('BASE CONSOLIDADA'!$Z$5:$Z$129,$B21))) | K21: =IF($B21="","",INDEX('BASE CONSOLIDADA'!$R$1:$R$129,SMALL('BASE CONSOLIDADA'!$Z$5:$Z$129,$B21)))
B22: =IF(COUNT('BASE CONSOLIDADA'!$Z$5:$Z$129)<14,"",14) | C22: =IF($B22="","",INDEX('BASE CONSOLIDADA'!$A$1:$A$129,SMALL('BASE CONSOLIDADA'!$Z$5:$Z$129,$B22))) | D22: =IF($B22="","",INDEX('BASE CONSOLIDADA'!$C$1:$C$129,SMALL('BASE CONSOLIDADA'!$Z$5:$Z$129,$B22))) | E22: =IF($B22="","",INDEX('BASE CONSOLIDADA'!$D$1:$D$129,SMALL('BASE CONSOLIDADA'!$Z$5:$Z$129,$B22))) | F22: =IF($B22="","",INDEX('BASE CONSOLIDADA'!$B$1:$B$129,SMALL('BASE CONSOLIDADA'!$Z$5:$Z$129,$B22))) | G22: =IF($B22="","",INDEX('BASE CONSOLIDADA'!$E$1:$E$129,SMALL('BASE CONSOLIDADA'!$Z$5:$Z$129,$B22))) | H22: =IF($B22="","",INDEX('BASE CONSOLIDADA'!$O$1:$O$129,SMALL('BASE CONSOLIDADA'!$Z$5:$Z$129,$B22))) | I22: =IF($B22="","",INDEX('BASE CONSOLIDADA'!$G$1:$G$129,SMALL('BASE CONSOLIDADA'!$Z$5:$Z$129,$B22))) | J22: =IF($B22="","",INDEX('BASE CONSOLIDADA'!$P$1:$P$129,SMALL('BASE CONSOLIDADA'!$Z$5:$Z$129,$B22))) | K22: =IF($B22="","",INDEX('BASE CONSOLIDADA'!$R$1:$R$129,SMALL('BASE CONSOLIDADA'!$Z$5:$Z$129,$B22)))
B23: =IF(COUNT('BASE CONSOLIDADA'!$Z$5:$Z$129)<15,"",15) | C23: =IF($B23="","",INDEX('BASE CONSOLIDADA'!$A$1:$A$129,SMALL('BASE CONSOLIDADA'!$Z$5:$Z$129,$B23))) | D23: =IF($B23="","",INDEX('BASE CONSOLIDADA'!$C$1:$C$129,SMALL('BASE CONSOLIDADA'!$Z$5:$Z$129,$B23))) | E23: =IF($B23="","",INDEX('BASE CONSOLIDADA'!$D$1:$D$129,SMALL('BASE CONSOLIDADA'!$Z$5:$Z$129,$B23))) | F23: =IF($B23="","",INDEX('BASE CONSOLIDADA'!$B$1:$B$129,SMALL('BASE CONSOLIDADA'!$Z$5:$Z$129,$B23))) | G23: =IF($B23="","",INDEX('BASE CONSOLIDADA'!$E$1:$E$129,SMALL('BASE CONSOLIDADA'!$Z$5:$Z$129,$B23))) | H23: =IF($B23="","",INDEX('BASE CONSOLIDADA'!$O$1:$O$129,SMALL('BASE CONSOLIDADA'!$Z$5:$Z$129,$B23))) | I23: =IF($B23="","",INDEX('BASE CONSOLIDADA'!$G$1:$G$129,SMALL('BASE CONSOLIDADA'!$Z$5:$Z$129,$B23))) | J23: =IF($B23="","",INDEX('BASE CONSOLIDADA'!$P$1:$P$129,SMALL('BASE CONSOLIDADA'!$Z$5:$Z$129,$B23))) | K23: =IF($B23="","",INDEX('BASE CONSOLIDADA'!$R$1:$R$129,SMALL('BASE CONSOLIDADA'!$Z$5:$Z$129,$B23)))
B25: Dica: digite só o número (ex.: 016238 ou 5020-00217) ou uma palavra do título. Apague o termo para limpar. Detalhes completos na Base Consolidada.

Sheet BASE CONSOLIDADA
A1: BASE CONSOLIDADA DE INSTRUÇÕES | E1: ⌂ Início | F1: ▦ Dashboard | H1: ⌕ Pesquisa | I1: ✓ Qualidade
A2: ="LCQ RJ · "&COUNTA('BASE CONSOLIDADA'!$A$5:$A$129)&" códigos únicos consolidados de NDocs Q4, PE_PP, AOL e COMUNS" -> LCQ RJ · 125 códigos únicos consolidados de NDocs Q4, PE_PP, AOL e COMUNS
A3: ▌ DADO ORIGINAL NDocs — copiado da aba indicada em "Origem", sem edição | N3: ▌ CAMADA ANALÍTICA — fórmulas, não editar
A4: Código NDocs | B4: Versão | C4: Antigo Número | D4: Título | E4: Status NDocs | F4: Validade | G4: Área consolidada | H4: Abrangência | I4: Responsável | J4: Norma | K4: Comentários | L4: Origem (aba!linha) | M4: Qtd. registros origem | N4: Status padronizado | O4: Validade (analítica) | P4: Responsável padronizado | Q4: Dias p/ vencer | R4: Situação Gerencial | S4: Horizonte de validade | T4: Mês de vencimento | U4: Prioridade | V4: Ação recomendada | W4: Filtro dashboard | X4: Score ação | Y4: Chave de busca | Z4: Busca (linha)
A5: BRK-INS-01-010015-PT | B5: 7.0 | C5: IT 5020-00217 | D5: DETERMINAÇÃO DA CONCENTRAÇÃO DE SULFETO | E5: Aprovado | F5: 46689 | G5: Q4 | I5: Ana CARLA DA CRUZ ARAUJO | J5: UOP 163 - HYDROGEN SULFIDE AND MERCAPTAN SULFUR IN LIQUID HYDROCARBONS BY POTENTIOMETRIC TITRATION | L5: NDocs Q4!3 | M5: 1 | N5: =IF(TRIM(SUBSTITUTE(E5,CHAR(160)," "))="Avaiação de uso","Avaliação de uso",IF(TRIM(SUBSTITUTE(E5,CHAR(160)," "))="Cancelada","Cancelado",TRIM(SUBSTITUTE(E5,CHAR(160)," ")))) -> Aprovado | O5: =IF(ISNUMBER(F5),F5,IFERROR(DATE(RIGHT(RIGHT(TRIM(F5),10),4),MID(RIGHT(TRIM(F5),10),4,2),LEFT(RIGHT(TRIM(F5),10),2)),"")) -> 46689 | P5: =PROPER(TRIM(SUBSTITUTE(I5,CHAR(160)," "))) -> Ana Carla Da Cruz Araujo | Q5: =IF(O5="","",O5-DataRef) -> 388 | R5: =IF(OR(N5="Cancelado",N5="Fora de Uso"),"Inativo",IF(OR(N5="Revisão",N5="Em Elaboração"),"Em tratamento",IF(OR(N5<>"Aprovado",O5=""),"Validar cadastro",IF(O5<DataRef,"Ação imediata",IF(O5<=EDATE(DataRef,12),"Planejar revisão","Regular"))))) -> Regular | S5: =IF(R5="Inativo","Inativo",IF(O5="","Sem validade",IF(O5<DataRef,"Vencida",IF(O5<=DataRef+90,"Até 90 dias",IF(O5<=EDATE(DataRef,12),"91 dias a 12 meses","Após 12 meses"))))) -> Após 12 meses | T5: =IF(O5="","",DATE(YEAR(O5),MONTH(O5),1)) -> 46661 | U5: =IF(R5="Ação imediata",1,IF(N5="Não encontrado",2,IF(N5="Revisão",3,IF(N5="Em Elaboração",4,IF(S5="Até 90 dias",5,IF(R5="Validar cadastro",6,0)))))) -> 0 | V5: =CHOOSE(U5+1,IF(R5="Planejar revisão","Incluir no plano anual de revisão",IF(R5="Inativo","Sem ação","Monitorar")),"Revisar ou prorrogar validade","Confirmar status no NDocs","Acompanhar revisão","Concluir elaboração","Iniciar revisão (≤ 90 dias)","Validar aplicabilidade") -> Monitorar | W5: =(OR(fArea="Todas",ISNUMBER(SEARCH(fArea,G5))))*(OR(fStatus="Todos",N5=fStatus))*(OR(fSit="Todas",R5=fSit))*(OR(fResp="Todos",P5=fResp))*(OR(fHor="Todos",S5=fHor)) -> 1 | X5: =IF(AND(W5=1,U5>0),(7-U5)*100000+50000-IF(ISNUMBER(Q5),Q5,0)+ROW()/1000,0) -> 0 | Y5: =UPPER(A5&" "&TRIM(SUBSTITUTE(C5,CHAR(160)," "))&" "&TRIM(SUBSTITUTE(D5,CHAR(160)," "))) -> BRK-INS-01-010015-PT IT 5020-00217 DETERMINAÇÃO DA CONCENTRAÇÃO DE SULFETO | Z5: =IF(qBusca="","",IF(ISNUMBER(SEARCH(TRIM(qBusca),Y5)),ROW(),""))
A6: BRK-INS-01-010021-PT | B6: 7.0 | C6: IT 5020-00219 | D6: DETERMINAÇÃO DA TURBIDEZ | E6: Aprovado | F6: 48008 | G6: Q4 | I6: LARISSA VICENTE CARDOSO GUEDES | L6: NDocs Q4!4 | M6: 1 | N6: =IF(TRIM(SUBSTITUTE(E6,CHAR(160)," "))="Avaiação de uso","Avaliação de uso",IF(TRIM(SUBSTITUTE(E6,CHAR(160)," "))="Cancelada","Cancelado",TRIM(SUBSTITUTE(E6,CHAR(160)," ")))) -> Aprovado | O6: =IF(ISNUMBER(F6),F6,IFERROR(DATE(RIGHT(RIGHT(TRIM(F6),10),4),MID(RIGHT(TRIM(F6),10),4,2),LEFT(RIGHT(TRIM(F6),10),2)),"")) -> 48008 | P6: =PROPER(TRIM(SUBSTITUTE(I6,CHAR(160)," "))) -> Larissa Vicente Cardoso Guedes | Q6: =IF(O6="","",O6-DataRef) -> 1707 | R6: =IF(OR(N6="Cancelado",N6="Fora de Uso"),"Inativo",IF(OR(N6="Revisão",N6="Em Elaboração"),"Em tratamento",IF(OR(N6<>"Aprovado",O6=""),"Validar cadastro",IF(O6<DataRef,"Ação imediata",IF(O6<=EDATE(DataRef,12),"Planejar revisão","Regular"))))) -> Regular | S6: =IF(R6="Inativo","Inativo",IF(O6="","Sem validade",IF(O6<DataRef,"Vencida",IF(O6<=DataRef+90,"Até 90 dias",IF(O6<=EDATE(DataRef,12),"91 dias a 12 meses","Após 12 meses"))))) -> Após 12 meses | T6: =IF(O6="","",DATE(YEAR(O6),MONTH(O6),1)) -> 48000 | U6: =IF(R6="Ação imediata",1,IF(N6="Não encontrado",2,IF(N6="Revisão",3,IF(N6="Em Elaboração",4,IF(S6="Até 90 dias",5,IF(R6="Validar cadastro",6,0)))))) -> 0 | V6: =CHOOSE(U6+1,IF(R6="Planejar revisão","Incluir no plano anual de revisão",IF(R6="Inativo","Sem ação","Monitorar")),"Revisar ou prorrogar validade","Confirmar status no NDocs","Acompanhar revisão","Concluir elaboração","Iniciar revisão (≤ 90 dias)","Validar aplicabilidade") -> Monitorar | W6: =(OR(fArea="Todas",ISNUMBER(SEARCH(fArea,G6))))*(OR(fStatus="Todos",N6=fStatus))*(OR(fSit="Todas",R6=fSit))*(OR(fResp="Todos",P6=fResp))*(OR(fHor="Todos",S6=fHor)) -> 1 | X6: =IF(AND(W6=1,U6>0),(7-U6)*100000+50000-IF(ISNUMBER(Q6),Q6,0)+ROW()/1000,0) -> 0 | Y6: =UPPER(A6&" "&TRIM(SUBSTITUTE(C6,CHAR(160)," "))&" "&TRIM(SUBSTITUTE(D6,CHAR(160)," "))) -> BRK-INS-01-010021-PT IT 5020-00219 DETERMINAÇÃO DA TURBIDEZ | Z6: =IF(qBusca="","",IF(ISNUMBER(SEARCH(TRIM(qBusca),Y6)),ROW(),""))
A7: BRK-INS-01-010028-PT | B7: 7.0 | C7: IT 5020-00220 | D7: DETERMINAÇÃO DA CONCENTRAÇÃO DE CLORO RESIDUAL LIVRE | E7: Aprovado | F7: 46846 | G7: Q4 | I7: Ana CARLA DA CRUZ ARAUJO | L7: NDocs Q4!5 | M7: 1 | N7: =IF(TRIM(SUBSTITUTE(E7,CHAR(160)," "))="Avaiação de uso","Avaliação de uso",IF(TRIM(SUBSTITUTE(E7,CHAR(160)," "))="Cancelada","Cancelado",TRIM(SUBSTITUTE(E7,CHAR(160)," ")))) -> Aprovado | O7: =IF(ISNUMBER(F7),F7,IFERROR(DATE(RIGHT(RIGHT(TRIM(F7),10),4),MID(RIGHT(TRIM(F7),10),4,2),LEFT(RIGHT(TRIM(F7),10),2)),"")) -> 46846 | P7: =PROPER(TRIM(SUBSTITUTE(I7,CHAR(160)," "))) -> Ana Carla Da Cruz Araujo | Q7: =IF(O7="","",O7-DataRef) -> 545 | R7: =IF(OR(N7="Cancelado",N7="Fora de Uso"),"Inativo",IF(OR(N7="Revisão",N7="Em Elaboração"),"Em tratamento",IF(OR(N7<>"Aprovado",O7=""),"Validar cadastro",IF(O7<DataRef,"Ação imediata",IF(O7<=EDATE(DataRef,12),"Planejar revisão","Regular"))))) -> Regular | S7: =IF(R7="Inativo","Inativo",IF(O7="","Sem validade",IF(O7<DataRef,"Vencida",IF(O7<=DataRef+90,"Até 90 dias",IF(O7<=EDATE(DataRef,12),"91 dias a 12 meses","Após 12 meses"))))) -> Após 12 meses | T7: =IF(O7="","",DATE(YEAR(O7),MONTH(O7),1)) -> 46844 | U7: =IF(R7="Ação imediata",1,IF(N7="Não encontrado",2,IF(N7="Revisão",3,IF(N7="Em Elaboração",4,IF(S7="Até 90 dias",5,IF(R7="Validar cadastro",6,0)))))) -> 0 | V7: =CHOOSE(U7+1,IF(R7="Planejar revisão","Incluir no plano anual de revisão",IF(R7="Inativo","Sem ação","Monitorar")),"Revisar ou prorrogar validade","Confirmar status no NDocs","Acompanhar revisão","Concluir elaboração","Iniciar revisão (≤ 90 dias)","Validar aplicabilidade") -> Monitorar | W7: =(OR(fArea="Todas",ISNUMBER(SEARCH(fArea,G7))))*(OR(fStatus="Todos",N7=fStatus))*(OR(fSit="Todas",R7=fSit))*(OR(fResp="Todos",P7=fResp))*(OR(fHor="Todos",S7=fHor)) -> 1 | X7: =IF(AND(W7=1,U7>0),(7-U7)*100000+50000-IF(ISNUMBER(Q7),Q7,0)+ROW()/1000,0) -> 0 | Y7: =UPPER(A7&" "&TRIM(SUBSTITUTE(C7,CHAR(160)," "))&" "&TRIM(SUBSTITUTE(D7,CHAR(160)," "))) -> BRK-INS-01-010028-PT IT 5020-00220 DETERMINAÇÃO DA CONCENTRAÇÃO DE CLORO RESIDUAL LIVRE | Z7: =IF(qBusca="","",IF(ISNUMBER(SEARCH(TRIM(qBusca),Y7)),ROW(),""))
A8: BRK-INS-01-010035-PT | B8: 6.0 | C8: IT 5020-00221 | D8: DETERMINAÇÃO DA CONCENTRAÇÃO DE NAOH E NA2CO3 | E8: Aprovado | F8: 46846 | G8: Q4 | I8: Ana CARLA DA CRUZ ARAUJO | J8: ASTM D5580; ABNT NBR 8140 - SODA CÁUSTICA LÍQUIDA - DETERMINAÇÃO DA ALCALINIDADE TOTAL - MÉTODO POTENCIOMÉTRICO/VOLUMÉTRICO | L8: NDocs Q4!6 | M8: 1 | N8: =IF(TRIM(SUBSTITUTE(E8,CHAR(160)," "))="Avaiação de uso","Avaliação de uso",IF(TRIM(SUBSTITUTE(E8,CHAR(160)," "))="Cancelada","Cancelado",TRIM(SUBSTITUTE(E8,CHAR(160)," ")))) -> Aprovado | O8: =IF(ISNUMBER(F8),F8,IFERROR(DATE(RIGHT(RIGHT(TRIM(F8),10),4),MID(RIGHT(TRIM(F8),10),4,2),LEFT(RIGHT(TRIM(F8),10),2)),"")) -> 46846 | P8: =PROPER(TRIM(SUBSTITUTE(I8,CHAR(160)," "))) -> Ana Carla Da Cruz Araujo | Q8: =IF(O8="","",O8-DataRef) -> 545 | R8: =IF(OR(N8="Cancelado",N8="Fora de Uso"),"Inativo",IF(OR(N8="Revisão",N8="Em Elaboração"),"Em tratamento",IF(OR(N8<>"Aprovado",O8=""),"Validar cadastro",IF(O8<DataRef,"Ação imediata",IF(O8<=EDATE(DataRef,12),"Planejar revisão","Regular"))))) -> Regular | S8: =IF(R8="Inativo","Inativo",IF(O8="","Sem validade",IF(O8<DataRef,"Vencida",IF(O8<=DataRef+90,"Até 90 dias",IF(O8<=EDATE(DataRef,12),"91 dias a 12 meses","Após 12 meses"))))) -> Após 12 meses | T8: =IF(O8="","",DATE(YEAR(O8),MONTH(O8),1)) -> 46844 | U8: =IF(R8="Ação imediata",1,IF(N8="Não encontrado",2,IF(N8="Revisão",3,IF(N8="Em Elaboração",4,IF(S8="Até 90 dias",5,IF(R8="Validar cadastro",6,0)))))) -> 0 | V8: =CHOOSE(U8+1,IF(R8="Planejar revisão","Incluir no plano anual de revisão",IF(R8="Inativo","Sem ação","Monitorar")),"Revisar ou prorrogar validade","Confirmar status no NDocs","Acompanhar revisão","Concluir elaboração","Iniciar revisão (≤ 90 dias)","Validar aplicabilidade") -> Monitorar | W8: =(OR(fArea="Todas",ISNUMBER(SEARCH(fArea,G8))))*(OR(fStatus="Todos",N8=fStatus))*(OR(fSit="Todas",R8=fSit))*(OR(fResp="Todos",P8=fResp))*(OR(fHor="Todos",S8=fHor)) -> 1 | X8: =IF(AND(W8=1,U8>0),(7-U8)*100000+50000-IF(ISNUMBER(Q8),Q8,0)+ROW()/1000,0) -> 0 | Y8: =UPPER(A8&" "&TRIM(SUBSTITUTE(C8,CHAR(160)," "))&" "&TRIM(SUBSTITUTE(D8,CHAR(160)," "))) -> BRK-INS-01-010035-PT IT 5020-00221 DETERMINAÇÃO DA CONCENTRAÇÃO DE NAOH E NA2CO3 | Z8: =IF(qBusca="","",IF(ISNUMBER(SEARCH(TRIM(qBusca),Y8)),ROW(),""))
A9: BRK-INS-01-010039-PT | B9: 6.0 | C9: IT 5020-00222 | D9: DETERMINAÇÃO DA TEMPERATURA | E9: Aprovado | F9: 46730 | G9: Q4 | I9: Ana CARLA DA CRUZ ARAUJO | L9: NDocs Q4!7 | M9: 1 | N9: =IF(TRIM(SUBSTITUTE(E9,CHAR(160)," "))="Avaiação de uso","Avaliação de uso",IF(TRIM(SUBSTITUTE(E9,CHAR(160)," "))="Cancelada","Cancelado",TRIM(SUBSTITUTE(E9,CHAR(160)," ")))) -> Aprovado | O9: =IF(ISNUMBER(F9),F9,IFERROR(DATE(RIGHT(RIGHT(TRIM(F9),10),4),MID(RIGHT(TRIM(F9),10),4,2),LEFT(RIGHT(TRIM(F9),10),2)),"")) -> 46730 | P9: =PROPER(TRIM(SUBSTITUTE(I9,CHAR(160)," "))) -> Ana Carla Da Cruz Araujo | Q9: =IF(O9="","",O9-DataRef) -> 429 | R9: =IF(OR(N9="Cancelado",N9="Fora de Uso"),"Inativo",IF(OR(N9="Revisão",N9="Em Elaboração"),"Em tratamento",IF(OR(N9<>"Aprovado",O9=""),"Validar cadastro",IF(O9<DataRef,"Ação imediata",IF(O9<=EDATE(DataRef,12),"Planejar revisão","Regular"))))) -> Regular | S9: =IF(R9="Inativo","Inativo",IF(O9="","Sem validade",IF(O9<DataRef,"Vencida",IF(O9<=DataRef+90,"Até 90 dias",IF(O9<=EDATE(DataRef,12),"91 dias a 12 meses","Após 12 meses"))))) -> Após 12 meses | T9: =IF(O9="","",DATE(YEAR(O9),MONTH(O9),1)) -> 46722 | U9: =IF(R9="Ação imediata",1,IF(N9="Não encontrado",2,IF(N9="Revisão",3,IF(N9="Em Elaboração",4,IF(S9="Até 90 dias",5,IF(R9="Validar cadastro",6,0)))))) -> 0 | V9: =CHOOSE(U9+1,IF(R9="Planejar revisão","Incluir no plano anual de revisão",IF(R9="Inativo","Sem ação","Monitorar")),"Revisar ou prorrogar validade","Confirmar status no NDocs","Acompanhar revisão","Concluir elaboração","Iniciar revisão (≤ 90 dias)","Validar aplicabilidade") -> Monitorar | W9: =(OR(fArea="Todas",ISNUMBER(SEARCH(fArea,G9))))*(OR(fStatus="Todos",N9=fStatus))*(OR(fSit="Todas",R9=fSit))*(OR(fResp="Todos",P9=fResp))*(OR(fHor="Todos",S9=fHor)) -> 1 | X9: =IF(AND(W9=1,U9>0),(7-U9)*100000+50000-IF(ISNUMBER(Q9),Q9,0)+ROW()/1000,0) -> 0 | Y9: =UPPER(A9&" "&TRIM(SUBSTITUTE(C9,CHAR(160)," "))&" "&TRIM(SUBSTITUTE(D9,CHAR(160)," "))) -> BRK-INS-01-010039-PT IT 5020-00222 DETERMINAÇÃO DA TEMPERATURA | Z9: =IF(qBusca="","",IF(ISNUMBER(SEARCH(TRIM(qBusca),Y9)),ROW(),""))
A10: BRK-INS-01-010051-PT | B10: 6.0 | C10: IT 5020-00225 | D10: DETERMINAÇÃO DO PH | E10: Aprovado | F10: 46689 | G10: Q4 | I10: Ana CARLA DA CRUZ ARAUJO | J10: ASTM D1293 | L10: NDocs Q4!8 | M10: 1 | N10: =IF(TRIM(SUBSTITUTE(E10,CHAR(160)," "))="Avaiação de uso","Avaliação de uso",IF(TRIM(SUBSTITUTE(E10,CHAR(160)," "))="Cancelada","Cancelado",TRIM(SUBSTITUTE(E10,CHAR(160)," ")))) -> Aprovado | O10: =IF(ISNUMBER(F10),F10,IFERROR(DATE(RIGHT(RIGHT(TRIM(F10),10),4),MID(RIGHT(TRIM(F10),10),4,2),LEFT(RIGHT(TRIM(F10),10),2)),"")) -> 46689 | P10: =PROPER(TRIM(SUBSTITUTE(I10,CHAR(160)," "))) -> Ana Carla Da Cruz Araujo | Q10: =IF(O10="","",O10-DataRef) -> 388 | R10: =IF(OR(N10="Cancelado",N10="Fora de Uso"),"Inativo",IF(OR(N10="Revisão",N10="Em Elaboração"),"Em tratamento",IF(OR(N10<>"Aprovado",O10=""),"Validar cadastro",IF(O10<DataRef,"Ação imediata",IF(O10<=EDATE(DataRef,12),"Planejar revisão","Regular"))))) -> Regular | S10: =IF(R10="Inativo","Inativo",IF(O10="","Sem validade",IF(O10<DataRef,"Vencida",IF(O10<=DataRef+90,"Até 90 dias",IF(O10<=EDATE(DataRef,12),"91 dias a 12 meses","Após 12 meses"))))) -> Após 12 meses | T10: =IF(O10="","",DATE(YEAR(O10),MONTH(O10),1)) -> 46661 | U10: =IF(R10="Ação imediata",1,IF(N10="Não encontrado",2,IF(N10="Revisão",3,IF(N10="Em Elaboração",4,IF(S10="Até 90 dias",5,IF(R10="Validar cadastro",6,0)))))) -> 0 | V10: =CHOOSE(U10+1,IF(R10="Planejar revisão","Incluir no plano anual de revisão",IF(R10="Inativo","Sem ação","Monitorar")),"Revisar ou prorrogar validade","Confirmar status no NDocs","Acompanhar revisão","Concluir elaboração","Iniciar revisão (≤ 90 dias)","Validar aplicabilidade") -> Monitorar | W10: =(OR(fArea="Todas",ISNUMBER(SEARCH(fArea,G10))))*(OR(fStatus="Todos",N10=fStatus))*(OR(fSit="Todas",R10=fSit))*(OR(fResp="Todos",P10=fResp))*(OR(fHor="Todos",S10=fHor)) -> 1 | X10: =IF(AND(W10=1,U10>0),(7-U10)*100000+50000-IF(ISNUMBER(Q10),Q10,0)+ROW()/1000,0) -> 0 | Y10: =UPPER(A10&" "&TRIM(SUBSTITUTE(C10,CHAR(160)," "))&" "&TRIM(SUBSTITUTE(D10,CHAR(160)," "))) -> BRK-INS-01-010051-PT IT 5020-00225 DETERMINAÇÃO DO PH | Z10: =IF(qBusca="","",IF(ISNUMBER(SEARCH(TRIM(qBusca),Y10)),ROW(),""))
A11: BRK-INS-01-010064-PT | B11: 8.0 | C11: IT 5020-00228 | D11: PREPARO DE PADRÕES E SOLUÇÕES DO LCQ DCX - Q4, PE9 E PP5. | E11: Aprovado | F11: 46846 | G11: Q4 | I11: Ana CARLA DA CRUZ ARAUJO | L11: NDocs Q4!9 | M11: 1 | N11: =IF(TRIM(SUBSTITUTE(E11,CHAR(160)," "))="Avaiação de uso","Avaliação de uso",IF(TRIM(SUBSTITUTE(E11,CHAR(160)," "))="Cancelada","Cancelado",TRIM(SUBSTITUTE(E11,CHAR(160)," ")))) -> Aprovado | O11: =IF(ISNUMBER(F11),F11,IFERROR(DATE(RIGHT(RIGHT(TRIM(F11),10),4),MID(RIGHT(TRIM(F11),10),4,2),LEFT(RIGHT(TRIM(F11),10),2)),"")) -> 46846 | P11: =PROPER(TRIM(SUBSTITUTE(I11,CHAR(160)," "))) -> Ana Carla Da Cruz Araujo | Q11: =IF(O11="","",O11-DataRef) -> 545 | R11: =IF(OR(N11="Cancelado",N11="Fora de Uso"),"Inativo",IF(OR(N11="Revisão",N11="Em Elaboração"),"Em tratamento",IF(OR(N11<>"Aprovado",O11=""),"Validar cadastro",IF(O11<DataRef,"Ação imediata",IF(O11<=EDATE(DataRef,12),"Planejar revisão","Regular"))))) -> Regular | S11: =IF(R11="Inativo","Inativo",IF(O11="","Sem validade",IF(O11<DataRef,"Vencida",IF(O11<=DataRef+90,"Até 90 dias",IF(O11<=EDATE(DataRef,12),"91 dias a 12 meses","Após 12 meses"))))) -> Após 12 meses | T11: =IF(O11="","",DATE(YEAR(O11),MONTH(O11),1)) -> 46844 | U11: =IF(R11="Ação imediata",1,IF(N11="Não encontrado",2,IF(N11="Revisão",3,IF(N11="Em Elaboração",4,IF(S11="Até 90 dias",5,IF(R11="Validar cadastro",6,0)))))) -> 0 | V11: =CHOOSE(U11+1,IF(R11="Planejar revisão","Incluir no plano anual de revisão",IF(R11="Inativo","Sem ação","Monitorar")),"Revisar ou prorrogar validade","Confirmar status no NDocs","Acompanhar revisão","Concluir elaboração","Iniciar revisão (≤ 90 dias)","Validar aplicabilidade") -> Monitorar | W11: =(OR(fArea="Todas",ISNUMBER(SEARCH(fArea,G11))))*(OR(fStatus="Todos",N11=fStatus))*(OR(fSit="Todas",R11=fSit))*(OR(fResp="Todos",P11=fResp))*(OR(fHor="Todos",S11=fHor)) -> 1 | X11: =IF(AND(W11=1,U11>0),(7-U11)*100000+50000-IF(ISNUMBER(Q11),Q11,0)+ROW()/1000,0) -> 0 | Y11: =UPPER(A11&" "&TRIM(SUBSTITUTE(C11,CHAR(160)," "))&" "&TRIM(SUBSTITUTE(D11,CHAR(160)," "))) -> BRK-INS-01-010064-PT IT 5020-00228 PREPARO DE PADRÕES E SOLUÇÕES DO LCQ DCX - Q4, PE9 E PP5. | Z11: =IF(qBusca="","",IF(ISNUMBER(SEARCH(TRIM(qBusca),Y11)),ROW(),""))
A12: BRK-INS-01-010069-PT | B12: 6.0 | C12: IT 5020-00229 | D12: DETERMINAÇÃO DA CONCENTRAÇÃO DE SÍLICA EM ÁGUAS | E12: Aprovado | F12: 46731 | G12: Q4 | I12: Ana CARLA DA CRUZ ARAUJO | L12: NDocs Q4!10 | M12: 1 | N12: =IF(TRIM(SUBSTITUTE(E12,CHAR(160)," "))="Avaiação de uso","Avaliação de uso",IF(TRIM(SUBSTITUTE(E12,CHAR(160)," "))="Cancelada","Cancelado",TRIM(SUBSTITUTE(E12,CHAR(160)," ")))) -> Aprovado | O12: =IF(ISNUMBER(F12),F12,IFERROR(DATE(RIGHT(RIGHT(TRIM(F12),10),4),MID(RIGHT(TRIM(F12),10),4,2),LEFT(RIGHT(TRIM(F12),10),2)),"")) -> 46731 | P12: =PROPER(TRIM(SUBSTITUTE(I12,CHAR(160)," "))) -> Ana Carla Da Cruz Araujo | Q12: =IF(O12="","",O12-DataRef) -> 430 | R12: =IF(OR(N12="Cancelado",N12="Fora de Uso"),"Inativo",IF(OR(N12="Revisão",N12="Em Elaboração"),"Em tratamento",IF(OR(N12<>"Aprovado",O12=""),"Validar cadastro",IF(O12<DataRef,"Ação imediata",IF(O12<=EDATE(DataRef,12),"Planejar revisão","Regular"))))) -> Regular | S12: =IF(R12="Inativo","Inativo",IF(O12="","Sem validade",IF(O12<DataRef,"Vencida",IF(O12<=DataRef+90,"Até 90 dias",IF(O12<=EDATE(DataRef,12),"91 dias a 12 meses","Após 12 meses"))))) -> Após 12 meses | T12: =IF(O12="","",DATE(YEAR(O12),MONTH(O12),1)) -> 46722 | U12: =IF(R12="Ação imediata",1,IF(N12="Não encontrado",2,IF(N12="Revisão",3,IF(N12="Em Elaboração",4,IF(S12="Até 90 dias",5,IF(R12="Validar cadastro",6,0)))))) -> 0 | V12: =CHOOSE(U12+1,IF(R12="Planejar revisão","Incluir no plano anual de revisão",IF(R12="Inativo","Sem ação","Monitorar")),"Revisar ou prorrogar validade","Confirmar status no NDocs","Acompanhar revisão","Concluir elaboração","Iniciar revisão (≤ 90 dias)","Validar aplicabilidade") -> Monitorar | W12: =(OR(fArea="Todas",ISNUMBER(SEARCH(fArea,G12))))*(OR(fStatus="Todos",N12=fStatus))*(OR(fSit="Todas",R12=fSit))*(OR(fResp="Todos",P12=fResp))*(OR(fHor="Todos",S12=fHor)) -> 1 | X12: =IF(AND(W12=1,U12>0),(7-U12)*100000+50000-IF(ISNUMBER(Q12),Q12,0)+ROW()/1000,0) -> 0 | Y12: =UPPER(A12&" "&TRIM(SUBSTITUTE(C12,CHAR(160)," "))&" "&TRIM(SUBSTITUTE(D12,CHAR(160)," "))) -> BRK-INS-01-010069-PT IT 5020-00229 DETERMINAÇÃO DA CONCENTRAÇÃO DE SÍLICA EM ÁGUAS | Z12: =IF(qBusca="","",IF(ISNUMBER(SEARCH(TRIM(qBusca),Y12)),ROW(),""))
A13: BRK-INS-01-010073-PT | B13: 6.0 | C13: IT 5020-00231 | D13: DETERMINAÇÃO DA CONCENTRAÇÃO DE FÓSFORO TOTAL | E13: Aprovado | F13: 46731 | G13: Q4 | I13: Ana CARLA DA CRUZ ARAUJO | L13: NDocs Q4!11 | M13: 1 | N13: =IF(TRIM(SUBSTITUTE(E13,CHAR(160)," "))="Avaiação de uso","Avaliação de uso",IF(TRIM(SUBSTITUTE(E13,CHAR(160)," "))="Cancelada","Cancelado",TRIM(SUBSTITUTE(E13,CHAR(160)," ")))) -> Aprovado | O13: =IF(ISNUMBER(F13),F13,IFERROR(DATE(RIGHT(RIGHT(TRIM(F13),10),4),MID(RIGHT(TRIM(F13),10),4,2),LEFT(RIGHT(TRIM(F13),10),2)),"")) -> 46731 | P13: =PROPER(TRIM(SUBSTITUTE(I13,CHAR(160)," "))) -> Ana Carla Da Cruz Araujo | Q13: =IF(O13="","",O13-DataRef) -> 430 | R13: =IF(OR(N13="Cancelado",N13="Fora de Uso"),"Inativo",IF(OR(N13="Revisão",N13="Em Elaboração"),"Em tratamento",IF(OR(N13<>"Aprovado",O13=""),"Validar cadastro",IF(O13<DataRef,"Ação imediata",IF(O13<=EDATE(DataRef,12),"Planejar revisão","Regular"))))) -> Regular | S13: =IF(R13="Inativo","Inativo",IF(O13="","Sem validade",IF(O13<DataRef,"Vencida",IF(O13<=DataRef+90,"Até 90 dias",IF(O13<=EDATE(DataRef,12),"91 dias a 12 meses","Após 12 meses"))))) -> Após 12 meses | T13: =IF(O13="","",DATE(YEAR(O13),MONTH(O13),1)) -> 46722 | U13: =IF(R13="Ação imediata",1,IF(N13="Não encontrado",2,IF(N13="Revisão",3,IF(N13="Em Elaboração",4,IF(S13="Até 90 dias",5,IF(R13="Validar cadastro",6,0)))))) -> 0 | V13: =CHOOSE(U13+1,IF(R13="Planejar revisão","Incluir no plano anual de revisão",IF(R13="Inativo","Sem ação","Monitorar")),"Revisar ou prorrogar validade","Confirmar status no NDocs","Acompanhar revisão","Concluir elaboração","Iniciar revisão (≤ 90 dias)","Validar aplicabilidade") -> Monitorar | W13: =(OR(fArea="Todas",ISNUMBER(SEARCH(fArea,G13))))*(OR(fStatus="Todos",N13=fStatus))*(OR(fSit="Todas",R13=fSit))*(OR(fResp="Todos",P13=fResp))*(OR(fHor="Todos",S13=fHor)) -> 1 | X13: =IF(AND(W13=1,U13>0),(7-U13)*100000+50000-IF(ISNUMBER(Q13),Q13,0)+ROW()/1000,0) -> 0 | Y13: =UPPER(A13&" "&TRIM(SUBSTITUTE(C13,CHAR(160)," "))&" "&TRIM(SUBSTITUTE(D13,CHAR(160)," "))) -> BRK-INS-01-010073-PT IT 5020-00231 DETERMINAÇÃO DA CONCENTRAÇÃO DE FÓSFORO TOTAL | Z13: =IF(qBusca="","",IF(ISNUMBER(SEARCH(TRIM(qBusca),Y13)),ROW(),""))
A14: BRK-INS-01-010078-PT | B14: 6.0 | C14: IT 5020-00232 | D14: DETERMINAÇÃO DA CONDUTIVIDADE EM ÁGUAS E EFLUENTES | E14: Aprovado | F14: 46846 | G14: Q4 | I14: Ana CARLA DA CRUZ ARAUJO | J14: ASTM D1125 | L14: NDocs Q4!12 | M14: 1 | N14: =IF(TRIM(SUBSTITUTE(E14,CHAR(160)," "))="Avaiação de uso","Avaliação de uso",IF(TRIM(SUBSTITUTE(E14,CHAR(160)," "))="Cancelada","Cancelado",TRIM(SUBSTITUTE(E14,CHAR(160)," ")))) -> Aprovado | O14: =IF(ISNUMBER(F14),F14,IFERROR(DATE(RIGHT(RIGHT(TRIM(F14),10),4),MID(RIGHT(TRIM(F14),10),4,2),LEFT(RIGHT(TRIM(F14),10),2)),"")) -> 46846 | P14: =PROPER(TRIM(SUBSTITUTE(I14,CHAR(160)," "))) -> Ana Carla Da Cruz Araujo | Q14: =IF(O14="","",O14-DataRef) -> 545 | R14: =IF(OR(N14="Cancelado",N14="Fora de Uso"),"Inativo",IF(OR(N14="Revisão",N14="Em Elaboração"),"Em tratamento",IF(OR(N14<>"Aprovado",O14=""),"Validar cadastro",IF(O14<DataRef,"Ação imediata",IF(O14<=EDATE(DataRef,12),"Planejar revisão","Regular"))))) -> Regular | S14: =IF(R14="Inativo","Inativo",IF(O14="","Sem validade",IF(O14<DataRef,"Vencida",IF(O14<=DataRef+90,"Até 90 dias",IF(O14<=EDATE(DataRef,12),"91 dias a 12 meses","Após 12 meses"))))) -> Após 12 meses | T14: =IF(O14="","",DATE(YEAR(O14),MONTH(O14),1)) -> 46844 | U14: =IF(R14="Ação imediata",1,IF(N14="Não encontrado",2,IF(N14="Revisão",3,IF(N14="Em Elaboração",4,IF(S14="Até 90 dias",5,IF(R14="Validar cadastro",6,0)))))) -> 0 | V14: =CHOOSE(U14+1,IF(R14="Planejar revisão","Incluir no plano anual de revisão",IF(R14="Inativo","Sem ação","Monitorar")),"Revisar ou prorrogar validade","Confirmar status no NDocs","Acompanhar revisão","Concluir elaboração","Iniciar revisão (≤ 90 dias)","Validar aplicabilidade") -> Monitorar | W14: =(OR(fArea="Todas",ISNUMBER(SEARCH(fArea,G14))))*(OR(fStatus="Todos",N14=fStatus))*(OR(fSit="Todas",R14=fSit))*(OR(fResp="Todos",P14=fResp))*(OR(fHor="Todos",S14=fHor)) -> 1 | X14: =IF(AND(W14=1,U14>0),(7-U14)*100000+50000-IF(ISNUMBER(Q14),Q14,0)+ROW()/1000,0) -> 0 | Y14: =UPPER(A14&" "&TRIM(SUBSTITUTE(C14,CHAR(160)," "))&" "&TRIM(SUBSTITUTE(D14,CHAR(160)," "))) -> BRK-INS-01-010078-PT IT 5020-00232 DETERMINAÇÃO DA CONDUTIVIDADE EM ÁGUAS E EFLUENTES | Z14: =IF(qBusca="","",IF(ISNUMBER(SEARCH(TRIM(qBusca),Y14)),ROW(),""))
A15: BRK-INS-01-010083-PT | B15: 6.0 | C15: IT 5020-00233 | D15: DENSIDADE DO GÁS LIQUEFEITO DE PETRÓLEO POR DENSÍMETRO SOB PRESSÃO | E15: Aprovado | F15: 46689 | G15: Q4 | I15: Ana CARLA DA CRUZ ARAUJO | J15: ASTM D1657 - STANDARD TEST METHOD FOR DENSITY OR RELATIVE DENSITY OF LIGHT HYDROCARBONS BY PRESSURE HYDROMETER; ASTM E100 - STANDARD SPECIFICATION FOR ASTM HYDROMETERS; ASTM D1250 | L15: NDocs Q4!13 | M15: 1 | N15: =IF(TRIM(SUBSTITUTE(E15,CHAR(160)," "))="Avaiação de uso","Avaliação de uso",IF(TRIM(SUBSTITUTE(E15,CHAR(160)," "))="Cancelada","Cancelado",TRIM(SUBSTITUTE(E15,CHAR(160)," ")))) -> Aprovado | O15: =IF(ISNUMBER(F15),F15,IFERROR(DATE(RIGHT(RIGHT(TRIM(F15),10),4),MID(RIGHT(TRIM(F15),10),4,2),LEFT(RIGHT(TRIM(F15),10),2)),"")) -> 46689 | P15: =PROPER(TRIM(SUBSTITUTE(I15,CHAR(160)," "))) -> Ana Carla Da Cruz Araujo | Q15: =IF(O15="","",O15-DataRef) -> 388 | R15: =IF(OR(N15="Cancelado",N15="Fora de Uso"),"Inativo",IF(OR(N15="Revisão",N15="Em Elaboração"),"Em tratamento",IF(OR(N15<>"Aprovado",O15=""),"Validar cadastro",IF(O15<DataRef,"Ação imediata",IF(O15<=EDATE(DataRef,12),"Planejar revisão","Regular"))))) -> Regular | S15: =IF(R15="Inativo","Inativo",IF(O15="","Sem validade",IF(O15<DataRef,"Vencida",IF(O15<=DataRef+90,"Até 90 dias",IF(O15<=EDATE(DataRef,12),"91 dias a 12 meses","Após 12 meses"))))) -> Após 12 meses | T15: =IF(O15="","",DATE(YEAR(O15),MONTH(O15),1)) -> 46661 | U15: =IF(R15="Ação imediata",1,IF(N15="Não encontrado",2,IF(N15="Revisão",3,IF(N15="Em Elaboração",4,IF(S15="Até 90 dias",5,IF(R15="Validar cadastro",6,0)))))) -> 0 | V15: =CHOOSE(U15+1,IF(R15="Planejar revisão","Incluir no plano anual de revisão",IF(R15="Inativo","Sem ação","Monitorar")),"Revisar ou prorrogar validade","Confirmar status no NDocs","Acompanhar revisão","Concluir elaboração","Iniciar revisão (≤ 90 dias)","Validar aplicabilidade") -> Monitorar | W15: =(OR(fArea="Todas",ISNUMBER(SEARCH(fArea,G15))))*(OR(fStatus="Todos",N15=fStatus))*(OR(fSit="Todas",R15=fSit))*(OR(fResp="Todos",P15=fResp))*(OR(fHor="Todos",S15=fHor)) -> 1 | X15: =IF(AND(W15=1,U15>0),(7-U15)*100000+50000-IF(ISNUMBER(Q15),Q15,0)+ROW()/1000,0) -> 0 | Y15: =UPPER(A15&" "&TRIM(SUBSTITUTE(C15,CHAR(160)," "))&" "&TRIM(SUBSTITUTE(D15,CHAR(160)," "))) -> BRK-INS-01-010083-PT IT 5020-00233 DENSIDADE DO GÁS LIQUEFEITO DE PETRÓLEO POR DENSÍMETRO SOB PRESSÃO | Z15: =IF(qBusca="","",IF(ISNUMBER(SEARCH(TRIM(qBusca),Y15)),ROW(),""))
A16: BRK-INS-01-015113-PT | B16: 7.0 | C16: IT 5020-02473 | D16: DETERMINAÇÃO DA CONCENTRAÇÃO DE NITROGÊNIO TOTAL | E16: Aprovado | F16: 47917 | G16: Q4 | I16: Ana CARLA DA CRUZ ARAUJO | L16: NDocs Q4!14 | M16: 1 | N16: =IF(TRIM(SUBSTITUTE(E16,CHAR(160)," "))="Avaiação de uso","Avaliação de uso",IF(TRIM(SUBSTITUTE(E16,CHAR(160)," "))="Cancelada","Cancelado",TRIM(SUBSTITUTE(E16,CHAR(160)," ")))) -> Aprovado | O16: =IF(ISNUMBER(F16),F16,IFERROR(DATE(RIGHT(RIGHT(TRIM(F16),10),4),MID(RIGHT(TRIM(F16),10),4,2),LEFT(RIGHT(TRIM(F16),10),2)),"")) -> 47917 | P16: =PROPER(TRIM(SUBSTITUTE(I16,CHAR(160)," "))) -> Ana Carla Da Cruz Araujo | Q16: =IF(O16="","",O16-DataRef) -> 1616 | R16: =IF(OR(N16="Cancelado",N16="Fora de Uso"),"Inativo",IF(OR(N16="Revisão",N16="Em Elaboração"),"Em tratamento",IF(OR(N16<>"Aprovado",O16=""),"Validar cadastro",IF(O16<DataRef,"Ação imediata",IF(O16<=EDATE(DataRef,12),"Planejar revisão","Regular"))))) -> Regular | S16: =IF(R16="Inativo","Inativo",IF(O16="","Sem validade",IF(O16<DataRef,"Vencida",IF(O16<=DataRef+90,"Até 90 dias",IF(O16<=EDATE(DataRef,12),"91 dias a 12 meses","Após 12 meses"))))) -> Após 12 meses | T16: =IF(O16="","",DATE(YEAR(O16),MONTH(O16),1)) -> 47908 | U16: =IF(R16="Ação imediata",1,IF(N16="Não encontrado",2,IF(N16="Revisão",3,IF(N16="Em Elaboração",4,IF(S16="Até 90 dias",5,IF(R16="Validar cadastro",6,0)))))) -> 0 | V16: =CHOOSE(U16+1,IF(R16="Planejar revisão","Incluir no plano anual de revisão",IF(R16="Inativo","Sem ação","Monitorar")),"Revisar ou prorrogar validade","Confirmar status no NDocs","Acompanhar revisão","Concluir elaboração","Iniciar revisão (≤ 90 dias)","Validar aplicabilidade") -> Monitorar | W16: =(OR(fArea="Todas",ISNUMBER(SEARCH(fArea,G16))))*(OR(fStatus="Todos",N16=fStatus))*(OR(fSit="Todas",R16=fSit))*(OR(fResp="Todos",P16=fResp))*(OR(fHor="Todos",S16=fHor)) -> 1 | X16: =IF(AND(W16=1,U16>0),(7-U16)*100000+50000-IF(ISNUMBER(Q16),Q16,0)+ROW()/1000,0) -> 0 | Y16: =UPPER(A16&" "&TRIM(SUBSTITUTE(C16,CHAR(160)," "))&" "&TRIM(SUBSTITUTE(D16,CHAR(160)," "))) -> BRK-INS-01-015113-PT IT 5020-02473 DETERMINAÇÃO DA CONCENTRAÇÃO DE NITROGÊNIO TOTAL | Z16: =IF(qBusca="","",IF(ISNUMBER(SEARCH(TRIM(qBusca),Y16)),ROW(),""))
A17: BRK-INS-01-015318-PT | B17: 8.0 | C17: IT 5020-02558 | D17: DETERMINAÇÃO DE GASES INORGÂNICOS E HIDROCARBONETOS LEVES POR CROMATOGRAFIA EM FASE GASOSA | E17: Aprovado | F17: 46907 | G17: Q4 | I17: Ana CARLA DA CRUZ ARAUJO | L17: NDocs Q4!15 | M17: 1 | N17: =IF(TRIM(SUBSTITUTE(E17,CHAR(160)," "))="Avaiação de uso","Avaliação de uso",IF(TRIM(SUBSTITUTE(E17,CHAR(160)," "))="Cancelada","Cancelado",TRIM(SUBSTITUTE(E17,CHAR(160)," ")))) -> Aprovado | O17: =IF(ISNUMBER(F17),F17,IFERROR(DATE(RIGHT(RIGHT(TRIM(F17),10),4),MID(RIGHT(TRIM(F17),10),4,2),LEFT(RIGHT(TRIM(F17),10),2)),"")) -> 46907 | P17: =PROPER(TRIM(SUBSTITUTE(I17,CHAR(160)," "))) -> Ana Carla Da Cruz Araujo | Q17: =IF(O17="","",O17-DataRef) -> 606 | R17: =IF(OR(N17="Cancelado",N17="Fora de Uso"),"Inativo",IF(OR(N17="Revisão",N17="Em Elaboração"),"Em tratamento",IF(OR(N17<>"Aprovado",O17=""),"Validar cadastro",IF(O17<DataRef,"Ação imediata",IF(O17<=EDATE(DataRef,12),"Planejar revisão","Regular"))))) -> Regular | S17: =IF(R17="Inativo","Inativo",IF(O17="","Sem validade",IF(O17<DataRef,"Vencida",IF(O17<=DataRef+90,"Até 90 dias",IF(O17<=EDATE(DataRef,12),"91 dias a 12 meses","Após 12 meses"))))) -> Após 12 meses | T17: =IF(O17="","",DATE(YEAR(O17),MONTH(O17),1)) -> 46905 | U17: =IF(R17="Ação imediata",1,IF(N17="Não encontrado",2,IF(N17="Revisão",3,IF(N17="Em Elaboração",4,IF(S17="Até 90 dias",5,IF(R17="Validar cadastro",6,0)))))) -> 0 | V17: =CHOOSE(U17+1,IF(R17="Planejar revisão","Incluir no plano anual de revisão",IF(R17="Inativo","Sem ação","Monitorar")),"Revisar ou prorrogar validade","Confirmar status no NDocs","Acompanhar revisão","Concluir elaboração","Iniciar revisão (≤ 90 dias)","Validar aplicabilidade") -> Monitorar | W17: =(OR(fArea="Todas",ISNUMBER(SEARCH(fArea,G17))))*(OR(fStatus="Todos",N17=fStatus))*(OR(fSit="Todas",R17=fSit))*(OR(fResp="Todos",P17=fResp))*(OR(fHor="Todos",S17=fHor)) -> 1 | X17: =IF(AND(W17=1,U17>0),(7-U17)*100000+50000-IF(ISNUMBER(Q17),Q17,0)+ROW()/1000,0) -> 0 | Y17: =UPPER(A17&" "&TRIM(SUBSTITUTE(C17,CHAR(160)," "))&" "&TRIM(SUBSTITUTE(D17,CHAR(160)," "))) -> BRK-INS-01-015318-PT IT 5020-02558 DETERMINAÇÃO DE GASES INORGÂNICOS E HIDROCARBONETOS LEVES POR CROMATOGRAFIA EM FASE GASOSA | Z17: =IF(qBusca="","",IF(ISNUMBER(SEARCH(TRIM(qBusca),Y17)),ROW(),""))
A18: BRK-INS-01-015837-PT | B18: 0.5 | C18: IT 5020-02742 | D18: DETERMINAÇÃO DE INORGÂNICOS POR CROMATOGRAFIA GASOSA | E18: Em Elaboração | G18: Q4 | I18: ISABEL TEIXEIRA MALVAR PINTO | J18: ASTM D2504 | L18: NDocs Q4!16 | M18: 1 | N18: =IF(TRIM(SUBSTITUTE(E18,CHAR(160)," "))="Avaiação de uso","Avaliação de uso",IF(TRIM(SUBSTITUTE(E18,CHAR(160)," "))="Cancelada","Cancelado",TRIM(SUBSTITUTE(E18,CHAR(160)," ")))) -> Em Elaboração | O18: =IF(ISNUMBER(F18),F18,IFERROR(DATE(RIGHT(RIGHT(TRIM(F18),10),4),MID(RIGHT(TRIM(F18),10),4,2),LEFT(RIGHT(TRIM(F18),10),2)),"")) | P18: =PROPER(TRIM(SUBSTITUTE(I18,CHAR(160)," "))) -> Isabel Teixeira Malvar Pinto | Q18: =IF(O18="","",O18-DataRef) | R18: =IF(OR(N18="Cancelado",N18="Fora de Uso"),"Inativo",IF(OR(N18="Revisão",N18="Em Elaboração"),"Em tratamento",IF(OR(N18<>"Aprovado",O18=""),"Validar cadastro",IF(O18<DataRef,"Ação imediata",IF(O18<=EDATE(DataRef,12),"Planejar revisão","Regular"))))) -> Em tratamento | S18: =IF(R18="Inativo","Inativo",IF(O18="","Sem validade",IF(O18<DataRef,"Vencida",IF(O18<=DataRef+90,"Até 90 dias",IF(O18<=EDATE(DataRef,12),"91 dias a 12 meses","Após 12 meses"))))) -> Sem validade | T18: =IF(O18="","",DATE(YEAR(O18),MONTH(O18),1)) | U18: =IF(R18="Ação imediata",1,IF(N18="Não encontrado",2,IF(N18="Revisão",3,IF(N18="Em Elaboração",4,IF(S18="Até 90 dias",5,IF(R18="Validar cadastro",6,0)))))) -> 4 | V18: =CHOOSE(U18+1,IF(R18="Planejar revisão","Incluir no plano anual de revisão",IF(R18="Inativo","Sem ação","Monitorar")),"Revisar ou prorrogar validade","Confirmar status no NDocs","Acompanhar revisão","Concluir elaboração","Iniciar revisão (≤ 90 dias)","Validar aplicabilidade") -> Concluir elaboração | W18: =(OR(fArea="Todas",ISNUMBER(SEARCH(fArea,G18))))*(OR(fStatus="Todos",N18=fStatus))*(OR(fSit="Todas",R18=fSit))*(OR(fResp="Todos",P18=fResp))*(OR(fHor="Todos",S18=fHor)) -> 1 | X18: =IF(AND(W18=1,U18>0),(7-U18)*100000+50000-IF(ISNUMBER(Q18),Q18,0)+ROW()/1000,0) -> 350000.02 | Y18: =UPPER(A18&" "&TRIM(SUBSTITUTE(C18,CHAR(160)," "))&" "&TRIM(SUBSTITUTE(D18,CHAR(160)," "))) -> BRK-INS-01-015837-PT IT 5020-02742 DETERMINAÇÃO DE INORGÂNICOS POR CROMATOGRAFIA GASOSA | Z18: =IF(qBusca="","",IF(ISNUMBER(SEARCH(TRIM(qBusca),Y18)),ROW(),""))
A19: BRK-INS-01-016192-PT | B19: 6.0 | C19: IT 5020-00164 | D19: DETERMINAÇÃO DE GOMA POTENCIAL | E19: Aprovado | F19: 46689 | G19: Q4 | I19: Ana CARLA DA CRUZ ARAUJO | J19: ASTM D873 - STANDARD TEST METHOD FOR OXIDATION STABILITY OF AVIATION FUELS (POTENTIAL RESIDUE METHOD). | L19: NDocs Q4!17 | M19: 1 | N19: =IF(TRIM(SUBSTITUTE(E19,CHAR(160)," "))="Avaiação de uso","Avaliação de uso",IF(TRIM(SUBSTITUTE(E19,CHAR(160)," "))="Cancelada","Cancelado",TRIM(SUBSTITUTE(E19,CHAR(160)," ")))) -> Aprovado | O19: =IF(ISNUMBER(F19),F19,IFERROR(DATE(RIGHT(RIGHT(TRIM(F19),10),4),MID(RIGHT(TRIM(F19),10),4,2),LEFT(RIGHT(TRIM(F19),10),2)),"")) -> 46689 | P19: =PROPER(TRIM(SUBSTITUTE(I19,CHAR(160)," "))) -> Ana Carla Da Cruz Araujo | Q19: =IF(O19="","",O19-DataRef) -> 388 | R19: =IF(OR(N19="Cancelado",N19="Fora de Uso"),"Inativo",IF(OR(N19="Revisão",N19="Em Elaboração"),"Em tratamento",IF(OR(N19<>"Aprovado",O19=""),"Validar cadastro",IF(O19<DataRef,"Ação imediata",IF(O19<=EDATE(DataRef,12),"Planejar revisão","Regular"))))) -> Regular | S19: =IF(R19="Inativo","Inativo",IF(O19="","Sem validade",IF(O19<DataRef,"Vencida",IF(O19<=DataRef+90,"Até 90 dias",IF(O19<=EDATE(DataRef,12),"91 dias a 12 meses","Após 12 meses"))))) -> Após 12 meses | T19: =IF(O19="","",DATE(YEAR(O19),MONTH(O19),1)) -> 46661 | U19: =IF(R19="Ação imediata",1,IF(N19="Não encontrado",2,IF(N19="Revisão",3,IF(N19="Em Elaboração",4,IF(S19="Até 90 dias",5,IF(R19="Validar cadastro",6,0)))))) -> 0 | V19: =CHOOSE(U19+1,IF(R19="Planejar revisão","Incluir no plano anual de revisão",IF(R19="Inativo","Sem ação","Monitorar")),"Revisar ou prorrogar validade","Confirmar status no NDocs","Acompanhar revisão","Concluir elaboração","Iniciar revisão (≤ 90 dias)","Validar aplicabilidade") -> Monitorar | W19: =(OR(fArea="Todas",ISNUMBER(SEARCH(fArea,G19))))*(OR(fStatus="Todos",N19=fStatus))*(OR(fSit="Todas",R19=fSit))*(OR(fResp="Todos",P19=fResp))*(OR(fHor="Todos",S19=fHor)) -> 1 | X19: =IF(AND(W19=1,U19>0),(7-U19)*100000+50000-IF(ISNUMBER(Q19),Q19,0)+ROW()/1000,0) -> 0 | Y19: =UPPER(A19&" "&TRIM(SUBSTITUTE(C19,CHAR(160)," "))&" "&TRIM(SUBSTITUTE(D19,CHAR(160)," "))) -> BRK-INS-01-016192-PT IT 5020-00164 DETERMINAÇÃO DE GOMA POTENCIAL | Z19: =IF(qBusca="","",IF(ISNUMBER(SEARCH(TRIM(qBusca),Y19)),ROW(),""))
A20: BRK-INS-01-016201-PT | B20: 9.0 | C20: IT 5020-00166 | D20: DETERMINAÇÃO DO PERÍODO DE INDUÇÃO | E20: Aprovado | F20: 46846 | G20: Q4 | I20: Ana CARLA DA CRUZ ARAUJO | J20: ASTM D525 - STANDARD TEST METHOD FOR OXIDATION STABILITY OF GASOLINE (INDUCTION PERIOD METHOD). | L20: NDocs Q4!18 | M20: 1 | N20: =IF(TRIM(SUBSTITUTE(E20,CHAR(160)," "))="Avaiação de uso","Avaliação de uso",IF(TRIM(SUBSTITUTE(E20,CHAR(160)," "))="Cancelada","Cancelado",TRIM(SUBSTITUTE(E20,CHAR(160)," ")))) -> Aprovado | O20: =IF(ISNUMBER(F20),F20,IFERROR(DATE(RIGHT(RIGHT(TRIM(F20),10),4),MID(RIGHT(TRIM(F20),10),4,2),LEFT(RIGHT(TRIM(F20),10),2)),"")) -> 46846 | P20: =PROPER(TRIM(SUBSTITUTE(I20,CHAR(160)," "))) -> Ana Carla Da Cruz Araujo | Q20: =IF(O20="","",O20-DataRef) -> 545 | R20: =IF(OR(N20="Cancelado",N20="Fora de Uso"),"Inativo",IF(OR(N20="Revisão",N20="Em Elaboração"),"Em tratamento",IF(OR(N20<>"Aprovado",O20=""),"Validar cadastro",IF(O20<DataRef,"Ação imediata",IF(O20<=EDATE(DataRef,12),"Planejar revisão","Regular"))))) -> Regular | S20: =IF(R20="Inativo","Inativo",IF(O20="","Sem validade",IF(O20<DataRef,"Vencida",IF(O20<=DataRef+90,"Até 90 dias",IF(O20<=EDATE(DataRef,12),"91 dias a 12 meses","Após 12 meses"))))) -> Após 12 meses | T20: =IF(O20="","",DATE(YEAR(O20),MONTH(O20),1)) -> 46844 | U20: =IF(R20="Ação imediata",1,IF(N20="Não encontrado",2,IF(N20="Revisão",3,IF(N20="Em Elaboração",4,IF(S20="Até 90 dias",5,IF(R20="Validar cadastro",6,0)))))) -> 0 | V20: =CHOOSE(U20+1,IF(R20="Planejar revisão","Incluir no plano anual de revisão",IF(R20="Inativo","Sem ação","Monitorar")),"Revisar ou prorrogar validade","Confirmar status no NDocs","Acompanhar revisão","Concluir elaboração","Iniciar revisão (≤ 90 dias)","Validar aplicabilidade") -> Monitorar | W20: =(OR(fArea="Todas",ISNUMBER(SEARCH(fArea,G20))))*(OR(fStatus="Todos",N20=fStatus))*(OR(fSit="Todas",R20=fSit))*(OR(fResp="Todos",P20=fResp))*(OR(fHor="Todos",S20=fHor)) -> 1 | X20: =IF(AND(W20=1,U20>0),(7-U20)*100000+50000-IF(ISNUMBER(Q20),Q20,0)+ROW()/1000,0) -> 0 | Y20: =UPPER(A20&" "&TRIM(SUBSTITUTE(C20,CHAR(160)," "))&" "&TRIM(SUBSTITUTE(D20,CHAR(160)," "))) -> BRK-INS-01-016201-PT IT 5020-00166 DETERMINAÇÃO DO PERÍODO DE INDUÇÃO | Z20: =IF(qBusca="","",IF(ISNUMBER(SEARCH(TRIM(qBusca),Y20)),ROW(),""))
A21: BRK-INS-01-016208-PT | B21: 8.0 | C21: IT 5020-00168 | D21: DETERMINAÇÃO DE UMIDADE POR COULOMETRIA | E21: Aprovado | F21: 47974 | G21: Q4 | I21: Ana CARLA DA CRUZ ARAUJO | L21: NDocs Q4!19 | M21: 1 | N21: =IF(TRIM(SUBSTITUTE(E21,CHAR(160)," "))="Avaiação de uso","Avaliação de uso",IF(TRIM(SUBSTITUTE(E21,CHAR(160)," "))="Cancelada","Cancelado",TRIM(SUBSTITUTE(E21,CHAR(160)," ")))) -> Aprovado | O21: =IF(ISNUMBER(F21),F21,IFERROR(DATE(RIGHT(RIGHT(TRIM(F21),10),4),MID(RIGHT(TRIM(F21),10),4,2),LEFT(RIGHT(TRIM(F21),10),2)),"")) -> 47974 | P21: =PROPER(TRIM(SUBSTITUTE(I21,CHAR(160)," "))) -> Ana Carla Da Cruz Araujo | Q21: =IF(O21="","",O21-DataRef) -> 1673 | R21: =IF(OR(N21="Cancelado",N21="Fora de Uso"),"Inativo",IF(OR(N21="Revisão",N21="Em Elaboração"),"Em tratamento",IF(OR(N21<>"Aprovado",O21=""),"Validar cadastro",IF(O21<DataRef,"Ação imediata",IF(O21<=EDATE(DataRef,12),"Planejar revisão","Regular"))))) -> Regular | S21: =IF(R21="Inativo","Inativo",IF(O21="","Sem validade",IF(O21<DataRef,"Vencida",IF(O21<=DataRef+90,"Até 90 dias",IF(O21<=EDATE(DataRef,12),"91 dias a 12 meses","Após 12 meses"))))) -> Após 12 meses | T21: =IF(O21="","",DATE(YEAR(O21),MONTH(O21),1)) -> 47969 | U21: =IF(R21="Ação imediata",1,IF(N21="Não encontrado",2,IF(N21="Revisão",3,IF(N21="Em Elaboração",4,IF(S21="Até 90 dias",5,IF(R21="Validar cadastro",6,0)))))) -> 0 | V21: =CHOOSE(U21+1,IF(R21="Planejar revisão","Incluir no plano anual de revisão",IF(R21="Inativo","Sem ação","Monitorar")),"Revisar ou prorrogar validade","Confirmar status no NDocs","Acompanhar revisão","Concluir elaboração","Iniciar revisão (≤ 90 dias)","Validar aplicabilidade") -> Monitorar | W21: =(OR(fArea="Todas",ISNUMBER(SEARCH(fArea,G21))))*(OR(fStatus="Todos",N21=fStatus))*(OR(fSit="Todas",R21=fSit))*(OR(fResp="Todos",P21=fResp))*(OR(fHor="Todos",S21=fHor)) -> 1 | X21: =IF(AND(W21=1,U21>0),(7-U21)*100000+50000-IF(ISNUMBER(Q21),Q21,0)+ROW()/1000,0) -> 0 | Y21: =UPPER(A21&" "&TRIM(SUBSTITUTE(C21,CHAR(160)," "))&" "&TRIM(SUBSTITUTE(D21,CHAR(160)," "))) -> BRK-INS-01-016208-PT IT 5020-00168 DETERMINAÇÃO DE UMIDADE POR COULOMETRIA | Z21: =IF(qBusca="","",IF(ISNUMBER(SEARCH(TRIM(qBusca),Y21)),ROW(),""))
A22: BRK-INS-01-016220-PT | B22: 6.0 | C22: IT 5020-00170 | D22: DETERMINAÇÃO DA DENSIDADE ABSOLUTA E RELATIVA PELO DENSIMETRO DIGITAL | E22: Aprovado | F22: 48008 | G22: Q4 | I22: LARISSA VICENTE CARDOSO GUEDES | J22: ASTM D4052 - STANDARD TEST METHOD FOR DENSITY, RELATIVE DENSITY, AND API GRAVITY OF LIQUIDS BY DIGITAL DENSITY METER. | L22: NDocs Q4!20 | M22: 1 | N22: =IF(TRIM(SUBSTITUTE(E22,CHAR(160)," "))="Avaiação de uso","Avaliação de uso",IF(TRIM(SUBSTITUTE(E22,CHAR(160)," "))="Cancelada","Cancelado",TRIM(SUBSTITUTE(E22,CHAR(160)," ")))) -> Aprovado | O22: =IF(ISNUMBER(F22),F22,IFERROR(DATE(RIGHT(RIGHT(TRIM(F22),10),4),MID(RIGHT(TRIM(F22),10),4,2),LEFT(RIGHT(TRIM(F22),10),2)),"")) -> 48008 | P22: =PROPER(TRIM(SUBSTITUTE(I22,CHAR(160)," "))) -> Larissa Vicente Cardoso Guedes | Q22: =IF(O22="","",O22-DataRef) -> 1707 | R22: =IF(OR(N22="Cancelado",N22="Fora de Uso"),"Inativo",IF(OR(N22="Revisão",N22="Em Elaboração"),"Em tratamento",IF(OR(N22<>"Aprovado",O22=""),"Validar cadastro",IF(O22<DataRef,"Ação imediata",IF(O22<=EDATE(DataRef,12),"Planejar revisão","Regular"))))) -> Regular | S22: =IF(R22="Inativo","Inativo",IF(O22="","Sem validade",IF(O22<DataRef,"Vencida",IF(O22<=DataRef+90,"Até 90 dias",IF(O22<=EDATE(DataRef,12),"91 dias a 12 meses","Após 12 meses"))))) -> Após 12 meses | T22: =IF(O22="","",DATE(YEAR(O22),MONTH(O22),1)) -> 48000 | U22: =IF(R22="Ação imediata",1,IF(N22="Não encontrado",2,IF(N22="Revisão",3,IF(N22="Em Elaboração",4,IF(S22="Até 90 dias",5,IF(R22="Validar cadastro",6,0)))))) -> 0 | V22: =CHOOSE(U22+1,IF(R22="Planejar revisão","Incluir no plano anual de revisão",IF(R22="Inativo","Sem ação","Monitorar")),"Revisar ou prorrogar validade","Confirmar status no NDocs","Acompanhar revisão","Concluir elaboração","Iniciar revisão (≤ 90 dias)","Validar aplicabilidade") -> Monitorar | W22: =(OR(fArea="Todas",ISNUMBER(SEARCH(fArea,G22))))*(OR(fStatus="Todos",N22=fStatus))*(OR(fSit="Todas",R22=fSit))*(OR(fResp="Todos",P22=fResp))*(OR(fHor="Todos",S22=fHor)) -> 1 | X22: =IF(AND(W22=1,U22>0),(7-U22)*100000+50000-IF(ISNUMBER(Q22),Q22,0)+ROW()/1000,0) -> 0 | Y22: =UPPER(A22&" "&TRIM(SUBSTITUTE(C22,CHAR(160)," "))&" "&TRIM(SUBSTITUTE(D22,CHAR(160)," "))) -> BRK-INS-01-016220-PT IT 5020-00170 DETERMINAÇÃO DA DENSIDADE ABSOLUTA E RELATIVA PELO DENSIMETRO DIGITAL | Z22: =IF(qBusca="","",IF(ISNUMBER(SEARCH(TRIM(qBusca),Y22)),ROW(),""))
A23: BRK-INS-01-016228-PT | B23: 5.0 | C23: IT 5020-00172 | D23: DETERMINAÇÃO DE CARBONO ORGÂNICO TOTAL (TOC) | E23: Não encontrado | F23: 45706 | G23: Q4 | I23: Ana CARLA DA CRUZ ARAUJO | L23: NDocs Q4!21 | M23: 1 | N23: =IF(TRIM(SUBSTITUTE(E23,CHAR(160)," "))="Avaiação de uso","Avaliação de uso",IF(TRIM(SUBSTITUTE(E23,CHAR(160)," "))="Cancelada","Cancelado",TRIM(SUBSTITUTE(E23,CHAR(160)," ")))) -> Não encontrado | O23: =IF(ISNUMBER(F23),F23,IFERROR(DATE(RIGHT(RIGHT(TRIM(F23),10),4),MID(RIGHT(TRIM(F23),10),4,2),LEFT(RIGHT(TRIM(F23),10),2)),"")) -> 45706 | P23: =PROPER(TRIM(SUBSTITUTE(I23,CHAR(160)," "))) -> Ana Carla Da Cruz Araujo | Q23: =IF(O23="","",O23-DataRef) -> -595 | R23: =IF(OR(N23="Cancelado",N23="Fora de Uso"),"Inativo",IF(OR(N23="Revisão",N23="Em Elaboração"),"Em tratamento",IF(OR(N23<>"Aprovado",O23=""),"Validar cadastro",IF(O23<DataRef,"Ação imediata",IF(O23<=EDATE(DataRef,12),"Planejar revisão","Regular"))))) -> Validar cadastro | S23: =IF(R23="Inativo","Inativo",IF(O23="","Sem validade",IF(O23<DataRef,"Vencida",IF(O23<=DataRef+90,"Até 90 dias",IF(O23<=EDATE(DataRef,12),"91 dias a 12 meses","Após 12 meses"))))) -> Vencida | T23: =IF(O23="","",DATE(YEAR(O23),MONTH(O23),1)) -> 45689 | U23: =IF(R23="Ação imediata",1,IF(N23="Não encontrado",2,IF(N23="Revisão",3,IF(N23="Em Elaboração",4,IF(S23="Até 90 dias",5,IF(R23="Validar cadastro",6,0)))))) -> 2 | V23: =CHOOSE(U23+1,IF(R23="Planejar revisão","Incluir no plano anual de revisão",IF(R23="Inativo","Sem ação","Monitorar")),"Revisar ou prorrogar validade","Confirmar status no NDocs","Acompanhar revisão","Concluir elaboração","Iniciar revisão (≤ 90 dias)","Validar aplicabilidade") -> Confirmar status no NDocs | W23: =(OR(fArea="Todas",ISNUMBER(SEARCH(fArea,G23))))*(OR(fStatus="Todos",N23=fStatus))*(OR(fSit="Todas",R23=fSit))*(OR(fResp="Todos",P23=fResp))*(OR(fHor="Todos",S23=fHor)) -> 1 | X23: =IF(AND(W23=1,U23>0),(7-U23)*100000+50000-IF(ISNUMBER(Q23),Q23,0)+ROW()/1000,0) -> 550595.02 | Y23: =UPPER(A23&" "&TRIM(SUBSTITUTE(C23,CHAR(160)," "))&" "&TRIM(SUBSTITUTE(D23,CHAR(160)," "))) -> BRK-INS-01-016228-PT IT 5020-00172 DETERMINAÇÃO DE CARBONO ORGÂNICO TOTAL (TOC) | Z23: =IF(qBusca="","",IF(ISNUMBER(SEARCH(TRIM(qBusca),Y23)),ROW(),""))
A24: BRK-INS-01-016238-PT | B24: 7.0 | C24: IT 5020-00175 | D24: DETERMINAÇÃO DE OXIGÊNIO EM GASES POR TELEDYNE | E24: Aprovado | F24: 48104 | G24: Q4/AOL | I24: Ana Claudia Sergio De Oliveira | L24: NDocs Q4!22; NDocs AOL!23 | M24: 2 | N24: =IF(TRIM(SUBSTITUTE(E24,CHAR(160)," "))="Avaiação de uso","Avaliação de uso",IF(TRIM(SUBSTITUTE(E24,CHAR(160)," "))="Cancelada","Cancelado",TRIM(SUBSTITUTE(E24,CHAR(160)," ")))) -> Aprovado | O24: =IF(ISNUMBER(F24),F24,IFERROR(DATE(RIGHT(RIGHT(TRIM(F24),10),4),MID(RIGHT(TRIM(F24),10),4,2),LEFT(RIGHT(TRIM(F24),10),2)),"")) -> 48104 | P24: =PROPER(TRIM(SUBSTITUTE(I24,CHAR(160)," "))) -> Ana Claudia Sergio De Oliveira | Q24: =IF(O24="","",O24-DataRef) -> 1803 | R24: =IF(OR(N24="Cancelado",N24="Fora de Uso"),"Inativo",IF(OR(N24="Revisão",N24="Em Elaboração"),"Em tratamento",IF(OR(N24<>"Aprovado",O24=""),"Validar cadastro",IF(O24<DataRef,"Ação imediata",IF(O24<=EDATE(DataRef,12),"Planejar revisão","Regular"))))) -> Regular | S24: =IF(R24="Inativo","Inativo",IF(O24="","Sem validade",IF(O24<DataRef,"Vencida",IF(O24<=DataRef+90,"Até 90 dias",IF(O24<=EDATE(DataRef,12),"91 dias a 12 meses","Após 12 meses"))))) -> Após 12 meses | T24: =IF(O24="","",DATE(YEAR(O24),MONTH(O24),1)) -> 48092 | U24: =IF(R24="Ação imediata",1,IF(N24="Não encontrado",2,IF(N24="Revisão",3,IF(N24="Em Elaboração",4,IF(S24="Até 90 dias",5,IF(R24="Validar cadastro",6,0)))))) -> 0 | V24: =CHOOSE(U24+1,IF(R24="Planejar revisão","Incluir no plano anual de revisão",IF(R24="Inativo","Sem ação","Monitorar")),"Revisar ou prorrogar validade","Confirmar status no NDocs","Acompanhar revisão","Concluir elaboração","Iniciar revisão (≤ 90 dias)","Validar aplicabilidade") -> Monitorar | W24: =(OR(fArea="Todas",ISNUMBER(SEARCH(fArea,G24))))*(OR(fStatus="Todos",N24=fStatus))*(OR(fSit="Todas",R24=fSit))*(OR(fResp="Todos",P24=fResp))*(OR(fHor="Todos",S24=fHor)) -> 1 | X24: =IF(AND(W24=1,U24>0),(7-U24)*100000+50000-IF(ISNUMBER(Q24),Q24,0)+ROW()/1000,0) -> 0 | Y24: =UPPER(A24&" "&TRIM(SUBSTITUTE(C24,CHAR(160)," "))&" "&TRIM(SUBSTITUTE(D24,CHAR(160)," "))) -> BRK-INS-01-016238-PT IT 5020-00175 DETERMINAÇÃO DE OXIGÊNIO EM GASES POR TELEDYNE | Z24: =IF(qBusca="","",IF(ISNUMBER(SEARCH(TRIM(qBusca),Y24)),ROW(),"")) -> 24
A25: BRK-INS-01-016250-PT | B25: 6.0 | C25: IT 5020-00178 | D25: DETERMINAÇÃO DA COMPOSIÇÃO DA GASOLINA DE PIRÓLISE POR CROMATOGRAFIA EM FASE GASOSA | E25: Aprovado | F25: 46731 | G25: Q4 | I25: Ana CARLA DA CRUZ ARAUJO | L25: NDocs Q4!23 | M25: 1 | N25: =IF(TRIM(SUBSTITUTE(E25,CHAR(160)," "))="Avaiação de uso","Avaliação de uso",IF(TRIM(SUBSTITUTE(E25,CHAR(160)," "))="Cancelada","Cancelado",TRIM(SUBSTITUTE(E25,CHAR(160)," ")))) -> Aprovado | O25: =IF(ISNUMBER(F25),F25,IFERROR(DATE(RIGHT(RIGHT(TRIM(F25),10),4),MID(RIGHT(TRIM(F25),10),4,2),LEFT(RIGHT(TRIM(F25),10),2)),"")) -> 46731 | P25: =PROPER(TRIM(SUBSTITUTE(I25,CHAR(160)," "))) -> Ana Carla Da Cruz Araujo | Q25: =IF(O25="","",O25-DataRef) -> 430 | R25: =IF(OR(N25="Cancelado",N25="Fora de Uso"),"Inativo",IF(OR(N25="Revisão",N25="Em Elaboração"),"Em tratamento",IF(OR(N25<>"Aprovado",O25=""),"Validar cadastro",IF(O25<DataRef,"Ação imediata",IF(O25<=EDATE(DataRef,12),"Planejar revisão","Regular"))))) -> Regular | S25: =IF(R25="Inativo","Inativo",IF(O25="","Sem validade",IF(O25<DataRef,"Vencida",IF(O25<=DataRef+90,"Até 90 dias",IF(O25<=EDATE(DataRef,12),"91 dias a 12 meses","Após 12 meses"))))) -> Após 12 meses | T25: =IF(O25="","",DATE(YEAR(O25),MONTH(O25),1)) -> 46722 | U25: =IF(R25="Ação imediata",1,IF(N25="Não encontrado",2,IF(N25="Revisão",3,IF(N25="Em Elaboração",4,IF(S25="Até 90 dias",5,IF(R25="Validar cadastro",6,0)))))) -> 0 | V25: =CHOOSE(U25+1,IF(R25="Planejar revisão","Incluir no plano anual de revisão",IF(R25="Inativo","Sem ação","Monitorar")),"Revisar ou prorrogar validade","Confirmar status no NDocs","Acompanhar revisão","Concluir elaboração","Iniciar revisão (≤ 90 dias)","Validar aplicabilidade") -> Monitorar | W25: =(OR(fArea="Todas",ISNUMBER(SEARCH(fArea,G25))))*(OR(fStatus="Todos",N25=fStatus))*(OR(fSit="Todas",R25=fSit))*(OR(fResp="Todos",P25=fResp))*(OR(fHor="Todos",S25=fHor)) -> 1 | X25: =IF(AND(W25=1,U25>0),(7-U25)*100000+50000-IF(ISNUMBER(Q25),Q25,0)+ROW()/1000,0) -> 0 | Y25: =UPPER(A25&" "&TRIM(SUBSTITUTE(C25,CHAR(160)," "))&" "&TRIM(SUBSTITUTE(D25,CHAR(160)," "))) -> BRK-INS-01-016250-PT IT 5020-00178 DETERMINAÇÃO DA COMPOSIÇÃO DA GASOLINA DE PIRÓLISE POR CROMATOGRAFIA EM FASE GASOSA | Z25: =IF(qBusca="","",IF(ISNUMBER(SEARCH(TRIM(qBusca),Y25)),ROW(),""))
A26: BRK-INS-01-016256-PT | B26: 8.0 | C26: IT 5020-00179 | D26: DETERMINAÇÃO DA COMPOSIÇÃO DE C4 PRODUTO POR CROMATOGRAFIA EM FASE GASOSA | E26: Aprovado | F26: 48014 | G26: Q4 | I26: LARISSA VICENTE CARDOSO GUEDES | L26: NDocs Q4!24 | M26: 1 | N26: =IF(TRIM(SUBSTITUTE(E26,CHAR(160)," "))="Avaiação de uso","Avaliação de uso",IF(TRIM(SUBSTITUTE(E26,CHAR(160)," "))="Cancelada","Cancelado",TRIM(SUBSTITUTE(E26,CHAR(160)," ")))) -> Aprovado | O26: =IF(ISNUMBER(F26),F26,IFERROR(DATE(RIGHT(RIGHT(TRIM(F26),10),4),MID(RIGHT(TRIM(F26),10),4,2),LEFT(RIGHT(TRIM(F26),10),2)),"")) -> 48014 | P26: =PROPER(TRIM(SUBSTITUTE(I26,CHAR(160)," "))) -> Larissa Vicente Cardoso Guedes | Q26: =IF(O26="","",O26-DataRef) -> 1713 | R26: =IF(OR(N26="Cancelado",N26="Fora de Uso"),"Inativo",IF(OR(N26="Revisão",N26="Em Elaboração"),"Em tratamento",IF(OR(N26<>"Aprovado",O26=""),"Validar cadastro",IF(O26<DataRef,"Ação imediata",IF(O26<=EDATE(DataRef,12),"Planejar revisão","Regular"))))) -> Regular | S26: =IF(R26="Inativo","Inativo",IF(O26="","Sem validade",IF(O26<DataRef,"Vencida",IF(O26<=DataRef+90,"Até 90 dias",IF(O26<=EDATE(DataRef,12),"91 dias a 12 meses","Após 12 meses"))))) -> Após 12 meses | T26: =IF(O26="","",DATE(YEAR(O26),MONTH(O26),1)) -> 48000 | U26: =IF(R26="Ação imediata",1,IF(N26="Não encontrado",2,IF(N26="Revisão",3,IF(N26="Em Elaboração",4,IF(S26="Até 90 dias",5,IF(R26="Validar cadastro",6,0)))))) -> 0 | V26: =CHOOSE(U26+1,IF(R26="Planejar revisão","Incluir no plano anual de revisão",IF(R26="Inativo","Sem ação","Monitorar")),"Revisar ou prorrogar validade","Confirmar status no NDocs","Acompanhar revisão","Concluir elaboração","Iniciar revisão (≤ 90 dias)","Validar aplicabilidade") -> Monitorar | W26: =(OR(fArea="Todas",ISNUMBER(SEARCH(fArea,G26))))*(OR(fStatus="Todos",N26=fStatus))*(OR(fSit="Todas",R26=fSit))*(OR(fResp="Todos",P26=fResp))*(OR(fHor="Todos",S26=fHor)) -> 1 | X26: =IF(AND(W26=1,U26>0),(7-U26)*100000+50000-IF(ISNUMBER(Q26),Q26,0)+ROW()/1000,0) -> 0 | Y26: =UPPER(A26&" "&TRIM(SUBSTITUTE(C26,CHAR(160)," "))&" "&TRIM(SUBSTITUTE(D26,CHAR(160)," "))) -> BRK-INS-01-016256-PT IT 5020-00179 DETERMINAÇÃO DA COMPOSIÇÃO DE C4 PRODUTO POR CROMATOGRAFIA EM FASE GASOSA | Z26: =IF(qBusca="","",IF(ISNUMBER(SEARCH(TRIM(qBusca),Y26)),ROW(),""))
A27: BRK-INS-01-016263-PT | B27: 6.0 | C27: IT 5020-00180 | D27: DETERMINAÇÃO DA COMPOSIÇÃO DE C9 AROMÁTICO POR CROMATOGRAFIA EM FASE GASOSA | E27: Aprovado | F27: 46731 | G27: Q4 | I27: Ana CARLA DA CRUZ ARAUJO | L27: NDocs Q4!25 | M27: 1 | N27: =IF(TRIM(SUBSTITUTE(E27,CHAR(160)," "))="Avaiação de uso","Avaliação de uso",IF(TRIM(SUBSTITUTE(E27,CHAR(160)," "))="Cancelada","Cancelado",TRIM(SUBSTITUTE(E27,CHAR(160)," ")))) -> Aprovado | O27: =IF(ISNUMBER(F27),F27,IFERROR(DATE(RIGHT(RIGHT(TRIM(F27),10),4),MID(RIGHT(TRIM(F27),10),4,2),LEFT(RIGHT(TRIM(F27),10),2)),"")) -> 46731 | P27: =PROPER(TRIM(SUBSTITUTE(I27,CHAR(160)," "))) -> Ana Carla Da Cruz Araujo | Q27: =IF(O27="","",O27-DataRef) -> 430 | R27: =IF(OR(N27="Cancelado",N27="Fora de Uso"),"Inativo",IF(OR(N27="Revisão",N27="Em Elaboração"),"Em tratamento",IF(OR(N27<>"Aprovado",O27=""),"Validar cadastro",IF(O27<DataRef,"Ação imediata",IF(O27<=EDATE(DataRef,12),"Planejar revisão","Regular"))))) -> Regular | S27: =IF(R27="Inativo","Inativo",IF(O27="","Sem validade",IF(O27<DataRef,"Vencida",IF(O27<=DataRef+90,"Até 90 dias",IF(O27<=EDATE(DataRef,12),"91 dias a 12 meses","Após 12 meses"))))) -> Após 12 meses | T27: =IF(O27="","",DATE(YEAR(O27),MONTH(O27),1)) -> 46722 | U27: =IF(R27="Ação imediata",1,IF(N27="Não encontrado",2,IF(N27="Revisão",3,IF(N27="Em Elaboração",4,IF(S27="Até 90 dias",5,IF(R27="Validar cadastro",6,0)))))) -> 0 | V27: =CHOOSE(U27+1,IF(R27="Planejar revisão","Incluir no plano anual de revisão",IF(R27="Inativo","Sem ação","Monitorar")),"Revisar ou prorrogar validade","Confirmar status no NDocs","Acompanhar revisão","Concluir elaboração","Iniciar revisão (≤ 90 dias)","Validar aplicabilidade") -> Monitorar | W27: =(OR(fArea="Todas",ISNUMBER(SEARCH(fArea,G27))))*(OR(fStatus="Todos",N27=fStatus))*(OR(fSit="Todas",R27=fSit))*(OR(fResp="Todos",P27=fResp))*(OR(fHor="Todos",S27=fHor)) -> 1 | X27: =IF(AND(W27=1,U27>0),(7-U27)*100000+50000-IF(ISNUMBER(Q27),Q27,0)+ROW()/1000,0) -> 0 | Y27: =UPPER(A27&" "&TRIM(SUBSTITUTE(C27,CHAR(160)," "))&" "&TRIM(SUBSTITUTE(D27,CHAR(160)," "))) -> BRK-INS-01-016263-PT IT 5020-00180 DETERMINAÇÃO DA COMPOSIÇÃO DE C9 AROMÁTICO POR CROMATOGRAFIA EM FASE GASOSA | Z27: =IF(qBusca="","",IF(ISNUMBER(SEARCH(TRIM(qBusca),Y27)),ROW(),""))
A28: BRK-INS-01-016278-PT | B28: 6.0 | C28: IT 5020-00186 | D28: DETERMINAÇÃO DE HIDROCARBONETOS CONTAMINANTES EM PROPANO FRESCO POR CROMATOGRAFIA EM FASE GASOSA | E28: Aprovado | F28: 48106 | G28: Q4 | I28: LARISSA VICENTE CARDOSO GUEDES | L28: NDocs Q4!26 | M28: 1 | N28: =IF(TRIM(SUBSTITUTE(E28,CHAR(160)," "))="Avaiação de uso","Avaliação de uso",IF(TRIM(SUBSTITUTE(E28,CHAR(160)," "))="Cancelada","Cancelado",TRIM(SUBSTITUTE(E28,CHAR(160)," ")))) -> Aprovado | O28: =IF(ISNUMBER(F28),F28,IFERROR(DATE(RIGHT(RIGHT(TRIM(F28),10),4),MID(RIGHT(TRIM(F28),10),4,2),LEFT(RIGHT(TRIM(F28),10),2)),"")) -> 48106 | P28: =PROPER(TRIM(SUBSTITUTE(I28,CHAR(160)," "))) -> Larissa Vicente Cardoso Guedes | Q28: =IF(O28="","",O28-DataRef) -> 1805 | R28: =IF(OR(N28="Cancelado",N28="Fora de Uso"),"Inativo",IF(OR(N28="Revisão",N28="Em Elaboração"),"Em tratamento",IF(OR(N28<>"Aprovado",O28=""),"Validar cadastro",IF(O28<DataRef,"Ação imediata",IF(O28<=EDATE(DataRef,12),"Planejar revisão","Regular"))))) -> Regular | S28: =IF(R28="Inativo","Inativo",IF(O28="","Sem validade",IF(O28<DataRef,"Vencida",IF(O28<=DataRef+90,"Até 90 dias",IF(O28<=EDATE(DataRef,12),"91 dias a 12 meses","Após 12 meses"))))) -> Após 12 meses | T28: =IF(O28="","",DATE(YEAR(O28),MONTH(O28),1)) -> 48092 | U28: =IF(R28="Ação imediata",1,IF(N28="Não encontrado",2,IF(N28="Revisão",3,IF(N28="Em Elaboração",4,IF(S28="Até 90 dias",5,IF(R28="Validar cadastro",6,0)))))) -> 0 | V28: =CHOOSE(U28+1,IF(R28="Planejar revisão","Incluir no plano anual de revisão",IF(R28="Inativo","Sem ação","Monitorar")),"Revisar ou prorrogar validade","Confirmar status no NDocs","Acompanhar revisão","Concluir elaboração","Iniciar revisão (≤ 90 dias)","Validar aplicabilidade") -> Monitorar | W28: =(OR(fArea="Todas",ISNUMBER(SEARCH(fArea,G28))))*(OR(fStatus="Todos",N28=fStatus))*(OR(fSit="Todas",R28=fSit))*(OR(fResp="Todos",P28=fResp))*(OR(fHor="Todos",S28=fHor)) -> 1 | X28: =IF(AND(W28=1,U28>0),(7-U28)*100000+50000-IF(ISNUMBER(Q28),Q28,0)+ROW()/1000,0) -> 0 | Y28: =UPPER(A28&" "&TRIM(SUBSTITUTE(C28,CHAR(160)," "))&" "&TRIM(SUBSTITUTE(D28,CHAR(160)," "))) -> BRK-INS-01-016278-PT IT 5020-00186 DETERMINAÇÃO DE HIDROCARBONETOS CONTAMINANTES EM PROPANO FRESCO POR CROMATOGRAFIA EM FASE GASOSA | Z28: =IF(qBusca="","",IF(ISNUMBER(SEARCH(TRIM(qBusca),Y28)),ROW(),""))
A29: BRK-INS-01-016287-PT | B29: 7.0 | C29: IT 5020-00189 | D29: DETERMINAÇÃO DE HIDROCARBONETOS RESIDUAIS E VOLÁTEIS EM RESINA DE POLIETILENO POR CROMATOGRAFIA EM FASE GASOSA | E29: Aprovado | F29: 46907 | G29: Q4 | I29: Ana CARLA DA CRUZ ARAUJO | J29: ASTM D4526 | L29: NDocs Q4!27 | M29: 1 | N29: =IF(TRIM(SUBSTITUTE(E29,CHAR(160)," "))="Avaiação de uso","Avaliação de uso",IF(TRIM(SUBSTITUTE(E29,CHAR(160)," "))="Cancelada","Cancelado",TRIM(SUBSTITUTE(E29,CHAR(160)," ")))) -> Aprovado | O29: =IF(ISNUMBER(F29),F29,IFERROR(DATE(RIGHT(RIGHT(TRIM(F29),10),4),MID(RIGHT(TRIM(F29),10),4,2),LEFT(RIGHT(TRIM(F29),10),2)),"")) -> 46907 | P29: =PROPER(TRIM(SUBSTITUTE(I29,CHAR(160)," "))) -> Ana Carla Da Cruz Araujo | Q29: =IF(O29="","",O29-DataRef) -> 606 | R29: =IF(OR(N29="Cancelado",N29="Fora de Uso"),"Inativo",IF(OR(N29="Revisão",N29="Em Elaboração"),"Em tratamento",IF(OR(N29<>"Aprovado",O29=""),"Validar cadastro",IF(O29<DataRef,"Ação imediata",IF(O29<=EDATE(DataRef,12),"Planejar revisão","Regular"))))) -> Regular | S29: =IF(R29="Inativo","Inativo",IF(O29="","Sem validade",IF(O29<DataRef,"Vencida",IF(O29<=DataRef+90,"Até 90 dias",IF(O29<=EDATE(DataRef,12),"91 dias a 12 meses","Após 12 meses"))))) -> Após 12 meses | T29: =IF(O29="","",DATE(YEAR(O29),MONTH(O29),1)) -> 46905 | U29: =IF(R29="Ação imediata",1,IF(N29="Não encontrado",2,IF(N29="Revisão",3,IF(N29="Em Elaboração",4,IF(S29="Até 90 dias",5,IF(R29="Validar cadastro",6,0)))))) -> 0 | V29: =CHOOSE(U29+1,IF(R29="Planejar revisão","Incluir no plano anual de revisão",IF(R29="Inativo","Sem ação","Monitorar")),"Revisar ou prorrogar validade","Confirmar status no NDocs","Acompanhar revisão","Concluir elaboração","Iniciar revisão (≤ 90 dias)","Validar aplicabilidade") -> Monitorar | W29: =(OR(fArea="Todas",ISNUMBER(SEARCH(fArea,G29))))*(OR(fStatus="Todos",N29=fStatus))*(OR(fSit="Todas",R29=fSit))*(OR(fResp="Todos",P29=fResp))*(OR(fHor="Todos",S29=fHor)) -> 1 | X29: =IF(AND(W29=1,U29>0),(7-U29)*100000+50000-IF(ISNUMBER(Q29),Q29,0)+ROW()/1000,0) -> 0 | Y29: =UPPER(A29&" "&TRIM(SUBSTITUTE(C29,CHAR(160)," "))&" "&TRIM(SUBSTITUTE(D29,CHAR(160)," "))) -> BRK-INS-01-016287-PT IT 5020-00189 DETERMINAÇÃO DE HIDROCARBONETOS RESIDUAIS E VOLÁTEIS EM RESINA DE POLIETILENO POR CROMATOGRAFIA EM FASE GASOSA | Z29: =IF(qBusca="","",IF(ISNUMBER(SEARCH(TRIM(qBusca),Y29)),ROW(),""))
A30: BRK-INS-01-016288-PT | B30: 6.0 | C30: IT 5030-00260 | D30: CALIBRAÇÃO DE ANALISADOR DE UMIDADE PORTÁTIL PANAMETRICS | E30: Aprovado | F30: 48008 | G30: Q4/AOL | I30: Ana Claudia Sergio de Oliveira | L30: NDocs Q4!28; NDocs AOL!24 | M30: 2 | N30: =IF(TRIM(SUBSTITUTE(E30,CHAR(160)," "))="Avaiação de uso","Avaliação de uso",IF(TRIM(SUBSTITUTE(E30,CHAR(160)," "))="Cancelada","Cancelado",TRIM(SUBSTITUTE(E30,CHAR(160)," ")))) -> Aprovado | O30: =IF(ISNUMBER(F30),F30,IFERROR(DATE(RIGHT(RIGHT(TRIM(F30),10),4),MID(RIGHT(TRIM(F30),10),4,2),LEFT(RIGHT(TRIM(F30),10),2)),"")) -> 48008 | P30: =PROPER(TRIM(SUBSTITUTE(I30,CHAR(160)," "))) -> Ana Claudia Sergio De Oliveira | Q30: =IF(O30="","",O30-DataRef) -> 1707 | R30: =IF(OR(N30="Cancelado",N30="Fora de Uso"),"Inativo",IF(OR(N30="Revisão",N30="Em Elaboração"),"Em tratamento",IF(OR(N30<>"Aprovado",O30=""),"Validar cadastro",IF(O30<DataRef,"Ação imediata",IF(O30<=EDATE(DataRef,12),"Planejar revisão","Regular"))))) -> Regular | S30: =IF(R30="Inativo","Inativo",IF(O30="","Sem validade",IF(O30<DataRef,"Vencida",IF(O30<=DataRef+90,"Até 90 dias",IF(O30<=EDATE(DataRef,12),"91 dias a 12 meses","Após 12 meses"))))) -> Após 12 meses | T30: =IF(O30="","",DATE(YEAR(O30),MONTH(O30),1)) -> 48000 | U30: =IF(R30="Ação imediata",1,IF(N30="Não encontrado",2,IF(N30="Revisão",3,IF(N30="Em Elaboração",4,IF(S30="Até 90 dias",5,IF(R30="Validar cadastro",6,0)))))) -> 0 | V30: =CHOOSE(U30+1,IF(R30="Planejar revisão","Incluir no plano anual de revisão",IF(R30="Inativo","Sem ação","Monitorar")),"Revisar ou prorrogar validade","Confirmar status no NDocs","Acompanhar revisão","Concluir elaboração","Iniciar revisão (≤ 90 dias)","Validar aplicabilidade") -> Monitorar | W30: =(OR(fArea="Todas",ISNUMBER(SEARCH(fArea,G30))))*(OR(fStatus="Todos",N30=fStatus))*(OR(fSit="Todas",R30=fSit))*(OR(fResp="Todos",P30=fResp))*(OR(fHor="Todos",S30=fHor)) -> 1 | X30: =IF(AND(W30=1,U30>0),(7-U30)*100000+50000-IF(ISNUMBER(Q30),Q30,0)+ROW()/1000,0) -> 0 | Y30: =UPPER(A30&" "&TRIM(SUBSTITUTE(C30,CHAR(160)," "))&" "&TRIM(SUBSTITUTE(D30,CHAR(160)," "))) -> BRK-INS-01-016288-PT IT 5030-00260 CALIBRAÇÃO DE ANALISADOR DE UMIDADE PORTÁTIL PANAMETRICS | Z30: =IF(qBusca="","",IF(ISNUMBER(SEARCH(TRIM(qBusca),Y30)),ROW(),""))
A31: BRK-INS-01-016295-PT | B31: 5.0 | C31: IT 5020-00190 | D31: DETERMINAÇÃO DE COMPOSTOS SULFURADOS EM AMOSTRAS LÍQUIDAS (ANTEK 9000NS) | E31: Cancelada | F31: 45709 | G31: Q4 | I31: Ana CARLA DA CRUZ ARAUJO | J31: ASTM D5453 | K31: Cancelamento solicitado em 21/04/25. Substituída pela IT unidacado - BRK-INS-01-016214 | L31: NDocs Q4!29 | M31: 1 | N31: =IF(TRIM(SUBSTITUTE(E31,CHAR(160)," "))="Avaiação de uso","Avaliação de uso",IF(TRIM(SUBSTITUTE(E31,CHAR(160)," "))="Cancelada","Cancelado",TRIM(SUBSTITUTE(E31,CHAR(160)," ")))) -> Cancelado | O31: =IF(ISNUMBER(F31),F31,IFERROR(DATE(RIGHT(RIGHT(TRIM(F31),10),4),MID(RIGHT(TRIM(F31),10),4,2),LEFT(RIGHT(TRIM(F31),10),2)),"")) -> 45709 | P31: =PROPER(TRIM(SUBSTITUTE(I31,CHAR(160)," "))) -> Ana Carla Da Cruz Araujo | Q31: =IF(O31="","",O31-DataRef) -> -592 | R31: =IF(OR(N31="Cancelado",N31="Fora de Uso"),"Inativo",IF(OR(N31="Revisão",N31="Em Elaboração"),"Em tratamento",IF(OR(N31<>"Aprovado",O31=""),"Validar cadastro",IF(O31<DataRef,"Ação imediata",IF(O31<=EDATE(DataRef,12),"Planejar revisão","Regular"))))) -> Inativo | S31: =IF(R31="Inativo","Inativo",IF(O31="","Sem validade",IF(O31<DataRef,"Vencida",IF(O31<=DataRef+90,"Até 90 dias",IF(O31<=EDATE(DataRef,12),"91 dias a 12 meses","Após 12 meses"))))) -> Inativo | T31: =IF(O31="","",DATE(YEAR(O31),MONTH(O31),1)) -> 45689 | U31: =IF(R31="Ação imediata",1,IF(N31="Não encontrado",2,IF(N31="Revisão",3,IF(N31="Em Elaboração",4,IF(S31="Até 90 dias",5,IF(R31="Validar cadastro",6,0)))))) -> 0 | V31: =CHOOSE(U31+1,IF(R31="Planejar revisão","Incluir no plano anual de revisão",IF(R31="Inativo","Sem ação","Monitorar")),"Revisar ou prorrogar validade","Confirmar status no NDocs","Acompanhar revisão","Concluir elaboração","Iniciar revisão (≤ 90 dias)","Validar aplicabilidade") -> Sem ação | W31: =(OR(fArea="Todas",ISNUMBER(SEARCH(fArea,G31))))*(OR(fStatus="Todos",N31=fStatus))*(OR(fSit="Todas",R31=fSit))*(OR(fResp="Todos",P31=fResp))*(OR(fHor="Todos",S31=fHor)) -> 1 | X31: =IF(AND(W31=1,U31>0),(7-U31)*100000+50000-IF(ISNUMBER(Q31),Q31,0)+ROW()/1000,0) -> 0 | Y31: =UPPER(A31&" "&TRIM(SUBSTITUTE(C31,CHAR(160)," "))&" "&TRIM(SUBSTITUTE(D31,CHAR(160)," "))) -> BRK-INS-01-016295-PT IT 5020-00190 DETERMINAÇÃO DE COMPOSTOS SULFURADOS EM AMOSTRAS LÍQUIDAS (ANTEK 9000NS) | Z31: =IF(qBusca="","",IF(ISNUMBER(SEARCH(TRIM(qBusca),Y31)),ROW(),""))
A32: BRK-INS-01-016303-PT | B32: 6.0 | C32: IT 5020-00194 | D32: DETERMINAÇÃO DA COMPOSIÇÃO DO GÁS DE RECICLO DOS REATORES DAS LINHAS 1 E 2 POR CROMATOGRAFIA EM FASE GASOSA | E32: Aprovado | F32: 48008 | G32: Q4 | I32: LARISSA VICENTE CARDOSO GUEDES | L32: NDocs Q4!30 | M32: 1 | N32: =IF(TRIM(SUBSTITUTE(E32,CHAR(160)," "))="Avaiação de uso","Avaliação de uso",IF(TRIM(SUBSTITUTE(E32,CHAR(160)," "))="Cancelada","Cancelado",TRIM(SUBSTITUTE(E32,CHAR(160)," ")))) -> Aprovado | O32: =IF(ISNUMBER(F32),F32,IFERROR(DATE(RIGHT(RIGHT(TRIM(F32),10),4),MID(RIGHT(TRIM(F32),10),4,2),LEFT(RIGHT(TRIM(F32),10),2)),"")) -> 48008 | P32: =PROPER(TRIM(SUBSTITUTE(I32,CHAR(160)," "))) -> Larissa Vicente Cardoso Guedes | Q32: =IF(O32="","",O32-DataRef) -> 1707 | R32: =IF(OR(N32="Cancelado",N32="Fora de Uso"),"Inativo",IF(OR(N32="Revisão",N32="Em Elaboração"),"Em tratamento",IF(OR(N32<>"Aprovado",O32=""),"Validar cadastro",IF(O32<DataRef,"Ação imediata",IF(O32<=EDATE(DataRef,12),"Planejar revisão","Regular"))))) -> Regular | S32: =IF(R32="Inativo","Inativo",IF(O32="","Sem validade",IF(O32<DataRef,"Vencida",IF(O32<=DataRef+90,"Até 90 dias",IF(O32<=EDATE(DataRef,12),"91 dias a 12 meses","Após 12 meses"))))) -> Após 12 meses | T32: =IF(O32="","",DATE(YEAR(O32),MONTH(O32),1)) -> 48000 | U32: =IF(R32="Ação imediata",1,IF(N32="Não encontrado",2,IF(N32="Revisão",3,IF(N32="Em Elaboração",4,IF(S32="Até 90 dias",5,IF(R32="Validar cadastro",6,0)))))) -> 0 | V32: =CHOOSE(U32+1,IF(R32="Planejar revisão","Incluir no plano anual de revisão",IF(R32="Inativo","Sem ação","Monitorar")),"Revisar ou prorrogar validade","Confirmar status no NDocs","Acompanhar revisão","Concluir elaboração","Iniciar revisão (≤ 90 dias)","Validar aplicabilidade") -> Monitorar | W32: =(OR(fArea="Todas",ISNUMBER(SEARCH(fArea,G32))))*(OR(fStatus="Todos",N32=fStatus))*(OR(fSit="Todas",R32=fSit))*(OR(fResp="Todos",P32=fResp))*(OR(fHor="Todos",S32=fHor)) -> 1 | X32: =IF(AND(W32=1,U32>0),(7-U32)*100000+50000-IF(ISNUMBER(Q32),Q32,0)+ROW()/1000,0) -> 0 | Y32: =UPPER(A32&" "&TRIM(SUBSTITUTE(C32,CHAR(160)," "))&" "&TRIM(SUBSTITUTE(D32,CHAR(160)," "))) -> BRK-INS-01-016303-PT IT 5020-00194 DETERMINAÇÃO DA COMPOSIÇÃO DO GÁS DE RECICLO DOS REATORES DAS LINHAS 1 E 2 POR CROMATOGRAFIA EM FASE GASOSA | Z32: =IF(qBusca="","",IF(ISNUMBER(SEARCH(TRIM(qBusca),Y32)),ROW(),""))
A33: BRK-INS-01-016309-PT | B33: 5.0 | C33: IT 5020-00197 | D33: DETERMINAÇÃO DE HIDROCARBONETOS CONTAMINANTES EM ETANO FRESCO POR CROMATOGRAFIA EM FASE GASOSA | E33: Aprovado | F33: 48106 | G33: Q4 | I33: LARISSA VICENTE CARDOSO GUEDES | L33: NDocs Q4!31 | M33: 1 | N33: =IF(TRIM(SUBSTITUTE(E33,CHAR(160)," "))="Avaiação de uso","Avaliação de uso",IF(TRIM(SUBSTITUTE(E33,CHAR(160)," "))="Cancelada","Cancelado",TRIM(SUBSTITUTE(E33,CHAR(160)," ")))) -> Aprovado | O33: =IF(ISNUMBER(F33),F33,IFERROR(DATE(RIGHT(RIGHT(TRIM(F33),10),4),MID(RIGHT(TRIM(F33),10),4,2),LEFT(RIGHT(TRIM(F33),10),2)),"")) -> 48106 | P33: =PROPER(TRIM(SUBSTITUTE(I33,CHAR(160)," "))) -> Larissa Vicente Cardoso Guedes | Q33: =IF(O33="","",O33-DataRef) -> 1805 | R33: =IF(OR(N33="Cancelado",N33="Fora de Uso"),"Inativo",IF(OR(N33="Revisão",N33="Em Elaboração"),"Em tratamento",IF(OR(N33<>"Aprovado",O33=""),"Validar cadastro",IF(O33<DataRef,"Ação imediata",IF(O33<=EDATE(DataRef,12),"Planejar revisão","Regular"))))) -> Regular | S33: =IF(R33="Inativo","Inativo",IF(O33="","Sem validade",IF(O33<DataRef,"Vencida",IF(O33<=DataRef+90,"Até 90 dias",IF(O33<=EDATE(DataRef,12),"91 dias a 12 meses","Após 12 meses"))))) -> Após 12 meses | T33: =IF(O33="","",DATE(YEAR(O33),MONTH(O33),1)) -> 48092 | U33: =IF(R33="Ação imediata",1,IF(N33="Não encontrado",2,IF(N33="Revisão",3,IF(N33="Em Elaboração",4,IF(S33="Até 90 dias",5,IF(R33="Validar cadastro",6,0)))))) -> 0 | V33: =CHOOSE(U33+1,IF(R33="Planejar revisão","Incluir no plano anual de revisão",IF(R33="Inativo","Sem ação","Monitorar")),"Revisar ou prorrogar validade","Confirmar status no NDocs","Acompanhar revisão","Concluir elaboração","Iniciar revisão (≤ 90 dias)","Validar aplicabilidade") -> Monitorar | W33: =(OR(fArea="Todas",ISNUMBER(SEARCH(fArea,G33))))*(OR(fStatus="Todos",N33=fStatus))*(OR(fSit="Todas",R33=fSit))*(OR(fResp="Todos",P33=fResp))*(OR(fHor="Todos",S33=fHor)) -> 1 | X33: =IF(AND(W33=1,U33>0),(7-U33)*100000+50000-IF(ISNUMBER(Q33),Q33,0)+ROW()/1000,0) -> 0 | Y33: =UPPER(A33&" "&TRIM(SUBSTITUTE(C33,CHAR(160)," "))&" "&TRIM(SUBSTITUTE(D33,CHAR(160)," "))) -> BRK-INS-01-016309-PT IT 5020-00197 DETERMINAÇÃO DE HIDROCARBONETOS CONTAMINANTES EM ETANO FRESCO POR CROMATOGRAFIA EM FASE GASOSA | Z33: =IF(qBusca="","",IF(ISNUMBER(SEARCH(TRIM(qBusca),Y33)),ROW(),""))
A34: BRK-INS-01-021119-PT | B34: 1.0 | C34: IT 5020-00198 | D34: DETERMINAÇÃO DE OXIGENADOS EM GASES POR CROMATOGRAFIA EM FASE GASOSA | E34: Aprovado | F34: 48008 | G34: Q4 | I34: Ana CARLA DA CRUZ ARAUJO | L34: NDocs Q4!32 | M34: 1 | N34: =IF(TRIM(SUBSTITUTE(E34,CHAR(160)," "))="Avaiação de uso","Avaliação de uso",IF(TRIM(SUBSTITUTE(E34,CHAR(160)," "))="Cancelada","Cancelado",TRIM(SUBSTITUTE(E34,CHAR(160)," ")))) -> Aprovado | O34: =IF(ISNUMBER(F34),F34,IFERROR(DATE(RIGHT(RIGHT(TRIM(F34),10),4),MID(RIGHT(TRIM(F34),10),4,2),LEFT(RIGHT(TRIM(F34),10),2)),"")) -> 48008 | P34: =PROPER(TRIM(SUBSTITUTE(I34,CHAR(160)," "))) -> Ana Carla Da Cruz Araujo | Q34: =IF(O34="","",O34-DataRef) -> 1707 | R34: =IF(OR(N34="Cancelado",N34="Fora de Uso"),"Inativo",IF(OR(N34="Revisão",N34="Em Elaboração"),"Em tratamento",IF(OR(N34<>"Aprovado",O34=""),"Validar cadastro",IF(O34<DataRef,"Ação imediata",IF(O34<=EDATE(DataRef,12),"Planejar revisão","Regular"))))) -> Regular | S34: =IF(R34="Inativo","Inativo",IF(O34="","Sem validade",IF(O34<DataRef,"Vencida",IF(O34<=DataRef+90,"Até 90 dias",IF(O34<=EDATE(DataRef,12),"91 dias a 12 meses","Após 12 meses"))))) -> Após 12 meses | T34: =IF(O34="","",DATE(YEAR(O34),MONTH(O34),1)) -> 48000 | U34: =IF(R34="Ação imediata",1,IF(N34="Não encontrado",2,IF(N34="Revisão",3,IF(N34="Em Elaboração",4,IF(S34="Até 90 dias",5,IF(R34="Validar cadastro",6,0)))))) -> 0 | V34: =CHOOSE(U34+1,IF(R34="Planejar revisão","Incluir no plano anual de revisão",IF(R34="Inativo","Sem ação","Monitorar")),"Revisar ou prorrogar validade","Confirmar status no NDocs","Acompanhar revisão","Concluir elaboração","Iniciar revisão (≤ 90 dias)","Validar aplicabilidade") -> Monitorar | W34: =(OR(fArea="Todas",ISNUMBER(SEARCH(fArea,G34))))*(OR(fStatus="Todos",N34=fStatus))*(OR(fSit="Todas",R34=fSit))*(OR(fResp="Todos",P34=fResp))*(OR(fHor="Todos",S34=fHor)) -> 1 | X34: =IF(AND(W34=1,U34>0),(7-U34)*100000+50000-IF(ISNUMBER(Q34),Q34,0)+ROW()/1000,0) -> 0 | Y34: =UPPER(A34&" "&TRIM(SUBSTITUTE(C34,CHAR(160)," "))&" "&TRIM(SUBSTITUTE(D34,CHAR(160)," "))) -> BRK-INS-01-021119-PT IT 5020-00198 DETERMINAÇÃO DE OXIGENADOS EM GASES POR CROMATOGRAFIA EM FASE GASOSA | Z34: =IF(qBusca="","",IF(ISNUMBER(SEARCH(TRIM(qBusca),Y34)),ROW(),""))
A35: BRK-INS-01-016326-PT | B35: 7.0 | C35: IT 5020-00200 | D35: DETERMINAÇÃO DE HIDROCARBONETOS CONTAMINANTES EM ETENO PRODUTO POR CROMATOGRAFIA EM FASE GASOSA | E35: Aprovado | F35: 48031 | G35: Q4 | H35: UNIFICADA | I35: FATIMA MOURA GUTERRES | L35: NDocs Q4!33 | M35: 1 | N35: =IF(TRIM(SUBSTITUTE(E35,CHAR(160)," "))="Avaiação de uso","Avaliação de uso",IF(TRIM(SUBSTITUTE(E35,CHAR(160)," "))="Cancelada","Cancelado",TRIM(SUBSTITUTE(E35,CHAR(160)," ")))) -> Aprovado | O35: =IF(ISNUMBER(F35),F35,IFERROR(DATE(RIGHT(RIGHT(TRIM(F35),10),4),MID(RIGHT(TRIM(F35),10),4,2),LEFT(RIGHT(TRIM(F35),10),2)),"")) -> 48031 | P35: =PROPER(TRIM(SUBSTITUTE(I35,CHAR(160)," "))) -> Fatima Moura Guterres | Q35: =IF(O35="","",O35-DataRef) -> 1730 | R35: =IF(OR(N35="Cancelado",N35="Fora de Uso"),"Inativo",IF(OR(N35="Revisão",N35="Em Elaboração"),"Em tratamento",IF(OR(N35<>"Aprovado",O35=""),"Validar cadastro",IF(O35<DataRef,"Ação imediata",IF(O35<=EDATE(DataRef,12),"Planejar revisão","Regular"))))) -> Regular | S35: =IF(R35="Inativo","Inativo",IF(O35="","Sem validade",IF(O35<DataRef,"Vencida",IF(O35<=DataRef+90,"Até 90 dias",IF(O35<=EDATE(DataRef,12),"91 dias a 12 meses","Após 12 meses"))))) -> Após 12 meses | T35: =IF(O35="","",DATE(YEAR(O35),MONTH(O35),1)) -> 48030 | U35: =IF(R35="Ação imediata",1,IF(N35="Não encontrado",2,IF(N35="Revisão",3,IF(N35="Em Elaboração",4,IF(S35="Até 90 dias",5,IF(R35="Validar cadastro",6,0)))))) -> 0 | V35: =CHOOSE(U35+1,IF(R35="Planejar revisão","Incluir no plano anual de revisão",IF(R35="Inativo","Sem ação","Monitorar")),"Revisar ou prorrogar validade","Confirmar status no NDocs","Acompanhar revisão","Concluir elaboração","Iniciar revisão (≤ 90 dias)","Validar aplicabilidade") -> Monitorar | W35: =(OR(fArea="Todas",ISNUMBER(SEARCH(fArea,G35))))*(OR(fStatus="Todos",N35=fStatus))*(OR(fSit="Todas",R35=fSit))*(OR(fResp="Todos",P35=fResp))*(OR(fHor="Todos",S35=fHor)) -> 1 | X35: =IF(AND(W35=1,U35>0),(7-U35)*100000+50000-IF(ISNUMBER(Q35),Q35,0)+ROW()/1000,0) -> 0 | Y35: =UPPER(A35&" "&TRIM(SUBSTITUTE(C35,CHAR(160)," "))&" "&TRIM(SUBSTITUTE(D35,CHAR(160)," "))) -> BRK-INS-01-016326-PT IT 5020-00200 DETERMINAÇÃO DE HIDROCARBONETOS CONTAMINANTES EM ETENO PRODUTO POR CROMATOGRAFIA EM FASE GASOSA | Z35: =IF(qBusca="","",IF(ISNUMBER(SEARCH(TRIM(qBusca),Y35)),ROW(),""))
A36: BRK-INS-01-016334-PT | B36: 6.0 | C36: IT 5020-00202 | D36: DETERMINAÇÃO DE HIDROCARBONETOS CONTAMINANTES EM HIDROGÊNIO PRODUTO POR CROMATOGRAFIA EM FASE GASOSA | E36: Aprovado | F36: 48008 | G36: Q4 | I36: Ana CARLA DA CRUZ ARAUJO | L36: NDocs Q4!34 | M36: 1 | N36: =IF(TRIM(SUBSTITUTE(E36,CHAR(160)," "))="Avaiação de uso","Avaliação de uso",IF(TRIM(SUBSTITUTE(E36,CHAR(160)," "))="Cancelada","Cancelado",TRIM(SUBSTITUTE(E36,CHAR(160)," ")))) -> Aprovado | O36: =IF(ISNUMBER(F36),F36,IFERROR(DATE(RIGHT(RIGHT(TRIM(F36),10),4),MID(RIGHT(TRIM(F36),10),4,2),LEFT(RIGHT(TRIM(F36),10),2)),"")) -> 48008 | P36: =PROPER(TRIM(SUBSTITUTE(I36,CHAR(160)," "))) -> Ana Carla Da Cruz Araujo | Q36: =IF(O36="","",O36-DataRef) -> 1707 | R36: =IF(OR(N36="Cancelado",N36="Fora de Uso"),"Inativo",IF(OR(N36="Revisão",N36="Em Elaboração"),"Em tratamento",IF(OR(N36<>"Aprovado",O36=""),"Validar cadastro",IF(O36<DataRef,"Ação imediata",IF(O36<=EDATE(DataRef,12),"Planejar revisão","Regular"))))) -> Regular | S36: =IF(R36="Inativo","Inativo",IF(O36="","Sem validade",IF(O36<DataRef,"Vencida",IF(O36<=DataRef+90,"Até 90 dias",IF(O36<=EDATE(DataRef,12),"91 dias a 12 meses","Após 12 meses"))))) -> Após 12 meses | T36: =IF(O36="","",DATE(YEAR(O36),MONTH(O36),1)) -> 48000 | U36: =IF(R36="Ação imediata",1,IF(N36="Não encontrado",2,IF(N36="Revisão",3,IF(N36="Em Elaboração",4,IF(S36="Até 90 dias",5,IF(R36="Validar cadastro",6,0)))))) -> 0 | V36: =CHOOSE(U36+1,IF(R36="Planejar revisão","Incluir no plano anual de revisão",IF(R36="Inativo","Sem ação","Monitorar")),"Revisar ou prorrogar validade","Confirmar status no NDocs","Acompanhar revisão","Concluir elaboração","Iniciar revisão (≤ 90 dias)","Validar aplicabilidade") -> Monitorar | W36: =(OR(fArea="Todas",ISNUMBER(SEARCH(fArea,G36))))*(OR(fStatus="Todos",N36=fStatus))*(OR(fSit="Todas",R36=fSit))*(OR(fResp="Todos",P36=fResp))*(OR(fHor="Todos",S36=fHor)) -> 1 | X36: =IF(AND(W36=1,U36>0),(7-U36)*100000+50000-IF(ISNUMBER(Q36),Q36,0)+ROW()/1000,0) -> 0 | Y36: =UPPER(A36&" "&TRIM(SUBSTITUTE(C36,CHAR(160)," "))&" "&TRIM(SUBSTITUTE(D36,CHAR(160)," "))) -> BRK-INS-01-016334-PT IT 5020-00202 DETERMINAÇÃO DE HIDROCARBONETOS CONTAMINANTES EM HIDROGÊNIO PRODUTO POR CROMATOGRAFIA EM FASE GASOSA | Z36: =IF(qBusca="","",IF(ISNUMBER(SEARCH(TRIM(qBusca),Y36)),ROW(),""))
A37: BRK-INS-01-016341-PT | B37: 6.0 | C37: IT 5020-00203 | D37: DETERMINAÇÃO DE HIDROCARBONETOS EM GASES POR CROMATOGRAFIA EM FASE GASOSA CALCULADOS POR NORMALIZAÇÃO | E37: Aprovado | F37: 48104 | G37: Q4 | I37: LARISSA VICENTE CARDOSO GUEDES | L37: NDocs Q4!35 | M37: 1 | N37: =IF(TRIM(SUBSTITUTE(E37,CHAR(160)," "))="Avaiação de uso","Avaliação de uso",IF(TRIM(SUBSTITUTE(E37,CHAR(160)," "))="Cancelada","Cancelado",TRIM(SUBSTITUTE(E37,CHAR(160)," ")))) -> Aprovado | O37: =IF(ISNUMBER(F37),F37,IFERROR(DATE(RIGHT(RIGHT(TRIM(F37),10),4),MID(RIGHT(TRIM(F37),10),4,2),LEFT(RIGHT(TRIM(F37),10),2)),"")) -> 48104 | P37: =PROPER(TRIM(SUBSTITUTE(I37,CHAR(160)," "))) -> Larissa Vicente Cardoso Guedes | Q37: =IF(O37="","",O37-DataRef) -> 1803 | R37: =IF(OR(N37="Cancelado",N37="Fora de Uso"),"Inativo",IF(OR(N37="Revisão",N37="Em Elaboração"),"Em tratamento",IF(OR(N37<>"Aprovado",O37=""),"Validar cadastro",IF(O37<DataRef,"Ação imediata",IF(O37<=EDATE(DataRef,12),"Planejar revisão","Regular"))))) -> Regular | S37: =IF(R37="Inativo","Inativo",IF(O37="","Sem validade",IF(O37<DataRef,"Vencida",IF(O37<=DataRef+90,"Até 90 dias",IF(O37<=EDATE(DataRef,12),"91 dias a 12 meses","Após 12 meses"))))) -> Após 12 meses | T37: =IF(O37="","",DATE(YEAR(O37),MONTH(O37),1)) -> 48092 | U37: =IF(R37="Ação imediata",1,IF(N37="Não encontrado",2,IF(N37="Revisão",3,IF(N37="Em Elaboração",4,IF(S37="Até 90 dias",5,IF(R37="Validar cadastro",6,0)))))) -> 0 | V37: =CHOOSE(U37+1,IF(R37="Planejar revisão","Incluir no plano anual de revisão",IF(R37="Inativo","Sem ação","Monitorar")),"Revisar ou prorrogar validade","Confirmar status no NDocs","Acompanhar revisão","Concluir elaboração","Iniciar revisão (≤ 90 dias)","Validar aplicabilidade") -> Monitorar | W37: =(OR(fArea="Todas",ISNUMBER(SEARCH(fArea,G37))))*(OR(fStatus="Todos",N37=fStatus))*(OR(fSit="Todas",R37=fSit))*(OR(fResp="Todos",P37=fResp))*(OR(fHor="Todos",S37=fHor)) -> 1 | X37: =IF(AND(W37=1,U37>0),(7-U37)*100000+50000-IF(ISNUMBER(Q37),Q37,0)+ROW()/1000,0) -> 0 | Y37: =UPPER(A37&" "&TRIM(SUBSTITUTE(C37,CHAR(160)," "))&" "&TRIM(SUBSTITUTE(D37,CHAR(160)," "))) -> BRK-INS-01-016341-PT IT 5020-00203 DETERMINAÇÃO DE HIDROCARBONETOS EM GASES POR CROMATOGRAFIA EM FASE GASOSA CALCULADOS POR NORMALIZAÇÃO | Z37: =IF(qBusca="","",IF(ISNUMBER(SEARCH(TRIM(qBusca),Y37)),ROW(),""))
A38: BRK-INS-01-016346-PT | B38: 6.0 | C38: IT 5020-00207 | D38: DETERMINAÇÃO DA CONCENTRAÇÃO DE SODA CÁUSTICA POR VOLUMETRIA | E38: Aprovado | F38: 46914 | G38: Q4 | I38: Ana CARLA DA CRUZ ARAUJO | J38: ABNT NBR 8140 - SODA CÁUSTICA LÍQUIDA - DETERMINAÇÃO DA ALCALINIDADE TOTAL - MÉTODO POTENCIOMÉTRICO/VOLUMÉTRICO | L38: NDocs Q4!36 | M38: 1 | N38: =IF(TRIM(SUBSTITUTE(E38,CHAR(160)," "))="Avaiação de uso","Avaliação de uso",IF(TRIM(SUBSTITUTE(E38,CHAR(160)," "))="Cancelada","Cancelado",TRIM(SUBSTITUTE(E38,CHAR(160)," ")))) -> Aprovado | O38: =IF(ISNUMBER(F38),F38,IFERROR(DATE(RIGHT(RIGHT(TRIM(F38),10),4),MID(RIGHT(TRIM(F38),10),4,2),LEFT(RIGHT(TRIM(F38),10),2)),"")) -> 46914 | P38: =PROPER(TRIM(SUBSTITUTE(I38,CHAR(160)," "))) -> Ana Carla Da Cruz Araujo | Q38: =IF(O38="","",O38-DataRef) -> 613 | R38: =IF(OR(N38="Cancelado",N38="Fora de Uso"),"Inativo",IF(OR(N38="Revisão",N38="Em Elaboração"),"Em tratamento",IF(OR(N38<>"Aprovado",O38=""),"Validar cadastro",IF(O38<DataRef,"Ação imediata",IF(O38<=EDATE(DataRef,12),"Planejar revisão","Regular"))))) -> Regular | S38: =IF(R38="Inativo","Inativo",IF(O38="","Sem validade",IF(O38<DataRef,"Vencida",IF(O38<=DataRef+90,"Até 90 dias",IF(O38<=EDATE(DataRef,12),"91 dias a 12 meses","Após 12 meses"))))) -> Após 12 meses | T38: =IF(O38="","",DATE(YEAR(O38),MONTH(O38),1)) -> 46905 | U38: =IF(R38="Ação imediata",1,IF(N38="Não encontrado",2,IF(N38="Revisão",3,IF(N38="Em Elaboração",4,IF(S38="Até 90 dias",5,IF(R38="Validar cadastro",6,0)))))) -> 0 | V38: =CHOOSE(U38+1,IF(R38="Planejar revisão","Incluir no plano anual de revisão",IF(R38="Inativo","Sem ação","Monitorar")),"Revisar ou prorrogar validade","Confirmar status no NDocs","Acompanhar revisão","Concluir elaboração","Iniciar revisão (≤ 90 dias)","Validar aplicabilidade") -> Monitorar | W38: =(OR(fArea="Todas",ISNUMBER(SEARCH(fArea,G38))))*(OR(fStatus="Todos",N38=fStatus))*(OR(fSit="Todas",R38=fSit))*(OR(fResp="Todos",P38=fResp))*(OR(fHor="Todos",S38=fHor)) -> 1 | X38: =IF(AND(W38=1,U38>0),(7-U38)*100000+50000-IF(ISNUMBER(Q38),Q38,0)+ROW()/1000,0) -> 0 | Y38: =UPPER(A38&" "&TRIM(SUBSTITUTE(C38,CHAR(160)," "))&" "&TRIM(SUBSTITUTE(D38,CHAR(160)," "))) -> BRK-INS-01-016346-PT IT 5020-00207 DETERMINAÇÃO DA CONCENTRAÇÃO DE SODA CÁUSTICA POR VOLUMETRIA | Z38: =IF(qBusca="","",IF(ISNUMBER(SEARCH(TRIM(qBusca),Y38)),ROW(),""))
A39: BRK-INS-01-016354-PT | B39: 6.0 | C39: IT 5020-00208 | D39: DETERMINAÇÃO DA CONCENTRAÇÃO DE SÓLIDOS OU RESÍDUOS NÃO FILTRÁVEIS TOTAIS (RNFT) | E39: Aprovado | F39: 46846 | G39: Q4 | I39: Ana CARLA DA CRUZ ARAUJO | L39: NDocs Q4!37 | M39: 1 | N39: =IF(TRIM(SUBSTITUTE(E39,CHAR(160)," "))="Avaiação de uso","Avaliação de uso",IF(TRIM(SUBSTITUTE(E39,CHAR(160)," "))="Cancelada","Cancelado",TRIM(SUBSTITUTE(E39,CHAR(160)," ")))) -> Aprovado | O39: =IF(ISNUMBER(F39),F39,IFERROR(DATE(RIGHT(RIGHT(TRIM(F39),10),4),MID(RIGHT(TRIM(F39),10),4,2),LEFT(RIGHT(TRIM(F39),10),2)),"")) -> 46846 | P39: =PROPER(TRIM(SUBSTITUTE(I39,CHAR(160)," "))) -> Ana Carla Da Cruz Araujo | Q39: =IF(O39="","",O39-DataRef) -> 545 | R39: =IF(OR(N39="Cancelado",N39="Fora de Uso"),"Inativo",IF(OR(N39="Revisão",N39="Em Elaboração"),"Em tratamento",IF(OR(N39<>"Aprovado",O39=""),"Validar cadastro",IF(O39<DataRef,"Ação imediata",IF(O39<=EDATE(DataRef,12),"Planejar revisão","Regular"))))) -> Regular | S39: =IF(R39="Inativo","Inativo",IF(O39="","Sem validade",IF(O39<DataRef,"Vencida",IF(O39<=DataRef+90,"Até 90 dias",IF(O39<=EDATE(DataRef,12),"91 dias a 12 meses","Após 12 meses"))))) -> Após 12 meses | T39: =IF(O39="","",DATE(YEAR(O39),MONTH(O39),1)) -> 46844 | U39: =IF(R39="Ação imediata",1,IF(N39="Não encontrado",2,IF(N39="Revisão",3,IF(N39="Em Elaboração",4,IF(S39="Até 90 dias",5,IF(R39="Validar cadastro",6,0)))))) -> 0 | V39: =CHOOSE(U39+1,IF(R39="Planejar revisão","Incluir no plano anual de revisão",IF(R39="Inativo","Sem ação","Monitorar")),"Revisar ou prorrogar validade","Confirmar status no NDocs","Acompanhar revisão","Concluir elaboração","Iniciar revisão (≤ 90 dias)","Validar aplicabilidade") -> Monitorar | W39: =(OR(fArea="Todas",ISNUMBER(SEARCH(fArea,G39))))*(OR(fStatus="Todos",N39=fStatus))*(OR(fSit="Todas",R39=fSit))*(OR(fResp="Todos",P39=fResp))*(OR(fHor="Todos",S39=fHor)) -> 1 | X39: =IF(AND(W39=1,U39>0),(7-U39)*100000+50000-IF(ISNUMBER(Q39),Q39,0)+ROW()/1000,0) -> 0 | Y39: =UPPER(A39&" "&TRIM(SUBSTITUTE(C39,CHAR(160)," "))&" "&TRIM(SUBSTITUTE(D39,CHAR(160)," "))) -> BRK-INS-01-016354-PT IT 5020-00208 DETERMINAÇÃO DA CONCENTRAÇÃO DE SÓLIDOS OU RESÍDUOS NÃO FILTRÁVEIS TOTAIS (RNFT) | Z39: =IF(qBusca="","",IF(ISNUMBER(SEARCH(TRIM(qBusca),Y39)),ROW(),""))
A40: BRK-INS-01-016362-PT | B40: 7.0 | C40: IT 5020-00209 | D40: DETERMINAÇÃO DA CONCENTRAÇÃO DE SÓLIDOS SEDIMENTÁVEIS | E40: Aprovado | F40: 46914 | G40: Q4 | I40: Ana CARLA DA CRUZ ARAUJO | L40: NDocs Q4!38 | M40: 1 | N40: =IF(TRIM(SUBSTITUTE(E40,CHAR(160)," "))="Avaiação de uso","Avaliação de uso",IF(TRIM(SUBSTITUTE(E40,CHAR(160)," "))="Cancelada","Cancelado",TRIM(SUBSTITUTE(E40,CHAR(160)," ")))) -> Aprovado | O40: =IF(ISNUMBER(F40),F40,IFERROR(DATE(RIGHT(RIGHT(TRIM(F40),10),4),MID(RIGHT(TRIM(F40),10),4,2),LEFT(RIGHT(TRIM(F40),10),2)),"")) -> 46914 | P40: =PROPER(TRIM(SUBSTITUTE(I40,CHAR(160)," "))) -> Ana Carla Da Cruz Araujo | Q40: =IF(O40="","",O40-DataRef) -> 613 | R40: =IF(OR(N40="Cancelado",N40="Fora de Uso"),"Inativo",IF(OR(N40="Revisão",N40="Em Elaboração"),"Em tratamento",IF(OR(N40<>"Aprovado",O40=""),"Validar cadastro",IF(O40<DataRef,"Ação imediata",IF(O40<=EDATE(DataRef,12),"Planejar revisão","Regular"))))) -> Regular | S40: =IF(R40="Inativo","Inativo",IF(O40="","Sem validade",IF(O40<DataRef,"Vencida",IF(O40<=DataRef+90,"Até 90 dias",IF(O40<=EDATE(DataRef,12),"91 dias a 12 meses","Após 12 meses"))))) -> Após 12 meses | T40: =IF(O40="","",DATE(YEAR(O40),MONTH(O40),1)) -> 46905 | U40: =IF(R40="Ação imediata",1,IF(N40="Não encontrado",2,IF(N40="Revisão",3,IF(N40="Em Elaboração",4,IF(S40="Até 90 dias",5,IF(R40="Validar cadastro",6,0)))))) -> 0 | V40: =CHOOSE(U40+1,IF(R40="Planejar revisão","Incluir no plano anual de revisão",IF(R40="Inativo","Sem ação","Monitorar")),"Revisar ou prorrogar validade","Confirmar status no NDocs","Acompanhar revisão","Concluir elaboração","Iniciar revisão (≤ 90 dias)","Validar aplicabilidade") -> Monitorar | W40: =(OR(fArea="Todas",ISNUMBER(SEARCH(fArea,G40))))*(OR(fStatus="Todos",N40=fStatus))*(OR(fSit="Todas",R40=fSit))*(OR(fResp="Todos",P40=fResp))*(OR(fHor="Todos",S40=fHor)) -> 1 | X40: =IF(AND(W40=1,U40>0),(7-U40)*100000+50000-IF(ISNUMBER(Q40),Q40,0)+ROW()/1000,0) -> 0 | Y40: =UPPER(A40&" "&TRIM(SUBSTITUTE(C40,CHAR(160)," "))&" "&TRIM(SUBSTITUTE(D40,CHAR(160)," "))) -> BRK-INS-01-016362-PT IT 5020-00209 DETERMINAÇÃO DA CONCENTRAÇÃO DE SÓLIDOS SEDIMENTÁVEIS | Z40: =IF(qBusca="","",IF(ISNUMBER(SEARCH(TRIM(qBusca),Y40)),ROW(),""))
A41: BRK-INS-01-016375-PT | B41: 7.0 | C41: IT 5020-00210 | D41: DETERMINAÇÃO DE ALCALINIDADE EM ÁGUAS | E41: Aprovado | F41: 48008 | G41: Q4 | I41: LARISSA VICENTE CARDOSO GUEDES | L41: NDocs Q4!39 | M41: 1 | N41: =IF(TRIM(SUBSTITUTE(E41,CHAR(160)," "))="Avaiação de uso","Avaliação de uso",IF(TRIM(SUBSTITUTE(E41,CHAR(160)," "))="Cancelada","Cancelado",TRIM(SUBSTITUTE(E41,CHAR(160)," ")))) -> Aprovado | O41: =IF(ISNUMBER(F41),F41,IFERROR(DATE(RIGHT(RIGHT(TRIM(F41),10),4),MID(RIGHT(TRIM(F41),10),4,2),LEFT(RIGHT(TRIM(F41),10),2)),"")) -> 48008 | P41: =PROPER(TRIM(SUBSTITUTE(I41,CHAR(160)," "))) -> Larissa Vicente Cardoso Guedes | Q41: =IF(O41="","",O41-DataRef) -> 1707 | R41: =IF(OR(N41="Cancelado",N41="Fora de Uso"),"Inativo",IF(OR(N41="Revisão",N41="Em Elaboração"),"Em tratamento",IF(OR(N41<>"Aprovado",O41=""),"Validar cadastro",IF(O41<DataRef,"Ação imediata",IF(O41<=EDATE(DataRef,12),"Planejar revisão","Regular"))))) -> Regular | S41: =IF(R41="Inativo","Inativo",IF(O41="","Sem validade",IF(O41<DataRef,"Vencida",IF(O41<=DataRef+90,"Até 90 dias",IF(O41<=EDATE(DataRef,12),"91 dias a 12 meses","Após 12 meses"))))) -> Após 12 meses | T41: =IF(O41="","",DATE(YEAR(O41),MONTH(O41),1)) -> 48000 | U41: =IF(R41="Ação imediata",1,IF(N41="Não encontrado",2,IF(N41="Revisão",3,IF(N41="Em Elaboração",4,IF(S41="Até 90 dias",5,IF(R41="Validar cadastro",6,0)))))) -> 0 | V41: =CHOOSE(U41+1,IF(R41="Planejar revisão","Incluir no plano anual de revisão",IF(R41="Inativo","Sem ação","Monitorar")),"Revisar ou prorrogar validade","Confirmar status no NDocs","Acompanhar revisão","Concluir elaboração","Iniciar revisão (≤ 90 dias)","Validar aplicabilidade") -> Monitorar | W41: =(OR(fArea="Todas",ISNUMBER(SEARCH(fArea,G41))))*(OR(fStatus="Todos",N41=fStatus))*(OR(fSit="Todas",R41=fSit))*(OR(fResp="Todos",P41=fResp))*(OR(fHor="Todos",S41=fHor)) -> 1 | X41: =IF(AND(W41=1,U41>0),(7-U41)*100000+50000-IF(ISNUMBER(Q41),Q41,0)+ROW()/1000,0) -> 0 | Y41: =UPPER(A41&" "&TRIM(SUBSTITUTE(C41,CHAR(160)," "))&" "&TRIM(SUBSTITUTE(D41,CHAR(160)," "))) -> BRK-INS-01-016375-PT IT 5020-00210 DETERMINAÇÃO DE ALCALINIDADE EM ÁGUAS | Z41: =IF(qBusca="","",IF(ISNUMBER(SEARCH(TRIM(qBusca),Y41)),ROW(),""))
A42: BRK-INS-01-016387-PT | B42: 8.0 | C42: IT 5020-00212 | D42: DETERMINAÇÃO DA CONCENTRAÇÃO DE FENÓIS | E42: Aprovado | F42: 47917 | G42: Q4 | I42: Ana CARLA DA CRUZ ARAUJO | L42: NDocs Q4!40 | M42: 1 | N42: =IF(TRIM(SUBSTITUTE(E42,CHAR(160)," "))="Avaiação de uso","Avaliação de uso",IF(TRIM(SUBSTITUTE(E42,CHAR(160)," "))="Cancelada","Cancelado",TRIM(SUBSTITUTE(E42,CHAR(160)," ")))) -> Aprovado | O42: =IF(ISNUMBER(F42),F42,IFERROR(DATE(RIGHT(RIGHT(TRIM(F42),10),4),MID(RIGHT(TRIM(F42),10),4,2),LEFT(RIGHT(TRIM(F42),10),2)),"")) -> 47917 | P42: =PROPER(TRIM(SUBSTITUTE(I42,CHAR(160)," "))) -> Ana Carla Da Cruz Araujo | Q42: =IF(O42="","",O42-DataRef) -> 1616 | R42: =IF(OR(N42="Cancelado",N42="Fora de Uso"),"Inativo",IF(OR(N42="Revisão",N42="Em Elaboração"),"Em tratamento",IF(OR(N42<>"Aprovado",O42=""),"Validar cadastro",IF(O42<DataRef,"Ação imediata",IF(O42<=EDATE(DataRef,12),"Planejar revisão","Regular"))))) -> Regular | S42: =IF(R42="Inativo","Inativo",IF(O42="","Sem validade",IF(O42<DataRef,"Vencida",IF(O42<=DataRef+90,"Até 90 dias",IF(O42<=EDATE(DataRef,12),"91 dias a 12 meses","Após 12 meses"))))) -> Após 12 meses | T42: =IF(O42="","",DATE(YEAR(O42),MONTH(O42),1)) -> 47908 | U42: =IF(R42="Ação imediata",1,IF(N42="Não encontrado",2,IF(N42="Revisão",3,IF(N42="Em Elaboração",4,IF(S42="Até 90 dias",5,IF(R42="Validar cadastro",6,0)))))) -> 0 | V42: =CHOOSE(U42+1,IF(R42="Planejar revisão","Incluir no plano anual de revisão",IF(R42="Inativo","Sem ação","Monitorar")),"Revisar ou prorrogar validade","Confirmar status no NDocs","Acompanhar revisão","Concluir elaboração","Iniciar revisão (≤ 90 dias)","Validar aplicabilidade") -> Monitorar | W42: =(OR(fArea="Todas",ISNUMBER(SEARCH(fArea,G42))))*(OR(fStatus="Todos",N42=fStatus))*(OR(fSit="Todas",R42=fSit))*(OR(fResp="Todos",P42=fResp))*(OR(fHor="Todos",S42=fHor)) -> 1 | X42: =IF(AND(W42=1,U42>0),(7-U42)*100000+50000-IF(ISNUMBER(Q42),Q42,0)+ROW()/1000,0) -> 0 | Y42: =UPPER(A42&" "&TRIM(SUBSTITUTE(C42,CHAR(160)," "))&" "&TRIM(SUBSTITUTE(D42,CHAR(160)," "))) -> BRK-INS-01-016387-PT IT 5020-00212 DETERMINAÇÃO DA CONCENTRAÇÃO DE FENÓIS | Z42: =IF(qBusca="","",IF(ISNUMBER(SEARCH(TRIM(qBusca),Y42)),ROW(),""))
A43: BRK-INS-01-016400-PT | B43: 6.0 | C43: IT 5020-00213 | D43: DETERMINAÇÃO DA COR | E43: Aprovado | F43: 48008 | G43: Q4 | I43: LARISSA VICENTE CARDOSO GUEDES | L43: NDocs Q4!41 | M43: 1 | N43: =IF(TRIM(SUBSTITUTE(E43,CHAR(160)," "))="Avaiação de uso","Avaliação de uso",IF(TRIM(SUBSTITUTE(E43,CHAR(160)," "))="Cancelada","Cancelado",TRIM(SUBSTITUTE(E43,CHAR(160)," ")))) -> Aprovado | O43: =IF(ISNUMBER(F43),F43,IFERROR(DATE(RIGHT(RIGHT(TRIM(F43),10),4),MID(RIGHT(TRIM(F43),10),4,2),LEFT(RIGHT(TRIM(F43),10),2)),"")) -> 48008 | P43: =PROPER(TRIM(SUBSTITUTE(I43,CHAR(160)," "))) -> Larissa Vicente Cardoso Guedes | Q43: =IF(O43="","",O43-DataRef) -> 1707 | R43: =IF(OR(N43="Cancelado",N43="Fora de Uso"),"Inativo",IF(OR(N43="Revisão",N43="Em Elaboração"),"Em tratamento",IF(OR(N43<>"Aprovado",O43=""),"Validar cadastro",IF(O43<DataRef,"Ação imediata",IF(O43<=EDATE(DataRef,12),"Planejar revisão","Regular"))))) -> Regular | S43: =IF(R43="Inativo","Inativo",IF(O43="","Sem validade",IF(O43<DataRef,"Vencida",IF(O43<=DataRef+90,"Até 90 dias",IF(O43<=EDATE(DataRef,12),"91 dias a 12 meses","Após 12 meses"))))) -> Após 12 meses | T43: =IF(O43="","",DATE(YEAR(O43),MONTH(O43),1)) -> 48000 | U43: =IF(R43="Ação imediata",1,IF(N43="Não encontrado",2,IF(N43="Revisão",3,IF(N43="Em Elaboração",4,IF(S43="Até 90 dias",5,IF(R43="Validar cadastro",6,0)))))) -> 0 | V43: =CHOOSE(U43+1,IF(R43="Planejar revisão","Incluir no plano anual de revisão",IF(R43="Inativo","Sem ação","Monitorar")),"Revisar ou prorrogar validade","Confirmar status no NDocs","Acompanhar revisão","Concluir elaboração","Iniciar revisão (≤ 90 dias)","Validar aplicabilidade") -> Monitorar | W43: =(OR(fArea="Todas",ISNUMBER(SEARCH(fArea,G43))))*(OR(fStatus="Todos",N43=fStatus))*(OR(fSit="Todas",R43=fSit))*(OR(fResp="Todos",P43=fResp))*(OR(fHor="Todos",S43=fHor)) -> 1 | X43: =IF(AND(W43=1,U43>0),(7-U43)*100000+50000-IF(ISNUMBER(Q43),Q43,0)+ROW()/1000,0) -> 0 | Y43: =UPPER(A43&" "&TRIM(SUBSTITUTE(C43,CHAR(160)," "))&" "&TRIM(SUBSTITUTE(D43,CHAR(160)," "))) -> BRK-INS-01-016400-PT IT 5020-00213 DETERMINAÇÃO DA COR | Z43: =IF(qBusca="","",IF(ISNUMBER(SEARCH(TRIM(qBusca),Y43)),ROW(),""))
A44: BRK-INS-01-016413-PT | B44: 9.0 | C44: IT 5020-00215 | D44: DETERMINAÇÃO DA CONCENTRAÇÃO DE ORTOFOSFATO | E44: Aprovado | F44: 48008 | G44: Q4 | I44: LARISSA VICENTE CARDOSO GUEDES | L44: NDocs Q4!42 | M44: 1 | N44: =IF(TRIM(SUBSTITUTE(E44,CHAR(160)," "))="Avaiação de uso","Avaliação de uso",IF(TRIM(SUBSTITUTE(E44,CHAR(160)," "))="Cancelada","Cancelado",TRIM(SUBSTITUTE(E44,CHAR(160)," ")))) -> Aprovado | O44: =IF(ISNUMBER(F44),F44,IFERROR(DATE(RIGHT(RIGHT(TRIM(F44),10),4),MID(RIGHT(TRIM(F44),10),4,2),LEFT(RIGHT(TRIM(F44),10),2)),"")) -> 48008 | P44: =PROPER(TRIM(SUBSTITUTE(I44,CHAR(160)," "))) -> Larissa Vicente Cardoso Guedes | Q44: =IF(O44="","",O44-DataRef) -> 1707 | R44: =IF(OR(N44="Cancelado",N44="Fora de Uso"),"Inativo",IF(OR(N44="Revisão",N44="Em Elaboração"),"Em tratamento",IF(OR(N44<>"Aprovado",O44=""),"Validar cadastro",IF(O44<DataRef,"Ação imediata",IF(O44<=EDATE(DataRef,12),"Planejar revisão","Regular"))))) -> Regular | S44: =IF(R44="Inativo","Inativo",IF(O44="","Sem validade",IF(O44<DataRef,"Vencida",IF(O44<=DataRef+90,"Até 90 dias",IF(O44<=EDATE(DataRef,12),"91 dias a 12 meses","Após 12 meses"))))) -> Após 12 meses | T44: =IF(O44="","",DATE(YEAR(O44),MONTH(O44),1)) -> 48000 | U44: =IF(R44="Ação imediata",1,IF(N44="Não encontrado",2,IF(N44="Revisão",3,IF(N44="Em Elaboração",4,IF(S44="Até 90 dias",5,IF(R44="Validar cadastro",6,0)))))) -> 0 | V44: =CHOOSE(U44+1,IF(R44="Planejar revisão","Incluir no plano anual de revisão",IF(R44="Inativo","Sem ação","Monitorar")),"Revisar ou prorrogar validade","Confirmar status no NDocs","Acompanhar revisão","Concluir elaboração","Iniciar revisão (≤ 90 dias)","Validar aplicabilidade") -> Monitorar | W44: =(OR(fArea="Todas",ISNUMBER(SEARCH(fArea,G44))))*(OR(fStatus="Todos",N44=fStatus))*(OR(fSit="Todas",R44=fSit))*(OR(fResp="Todos",P44=fResp))*(OR(fHor="Todos",S44=fHor)) -> 1 | X44: =IF(AND(W44=1,U44>0),(7-U44)*100000+50000-IF(ISNUMBER(Q44),Q44,0)+ROW()/1000,0) -> 0 | Y44: =UPPER(A44&" "&TRIM(SUBSTITUTE(C44,CHAR(160)," "))&" "&TRIM(SUBSTITUTE(D44,CHAR(160)," "))) -> BRK-INS-01-016413-PT IT 5020-00215 DETERMINAÇÃO DA CONCENTRAÇÃO DE ORTOFOSFATO | Z44: =IF(qBusca="","",IF(ISNUMBER(SEARCH(TRIM(qBusca),Y44)),ROW(),""))
A45: BRK-INS-01-016427-PT | B45: 9.0 | C45: IT 5020-00216 | D45: DETERMINAÇÃO DA DEMANDA QUÍMICA DE OXIGÊNIO EM ÁGUAS E EFLUENTES | E45: Aprovado | F45: 46846 | G45: Q4 | I45: Ana CARLA DA CRUZ ARAUJO | J45: SM 5220 D - STANDARD METHODS EXAMINATION OF WATER ＆ WASTEWATER: CHEMICAL OXYGEN DEMAND (COD) | L45: NDocs Q4!43 | M45: 1 | N45: =IF(TRIM(SUBSTITUTE(E45,CHAR(160)," "))="Avaiação de uso","Avaliação de uso",IF(TRIM(SUBSTITUTE(E45,CHAR(160)," "))="Cancelada","Cancelado",TRIM(SUBSTITUTE(E45,CHAR(160)," ")))) -> Aprovado | O45: =IF(ISNUMBER(F45),F45,IFERROR(DATE(RIGHT(RIGHT(TRIM(F45),10),4),MID(RIGHT(TRIM(F45),10),4,2),LEFT(RIGHT(TRIM(F45),10),2)),"")) -> 46846 | P45: =PROPER(TRIM(SUBSTITUTE(I45,CHAR(160)," "))) -> Ana Carla Da Cruz Araujo | Q45: =IF(O45="","",O45-DataRef) -> 545 | R45: =IF(OR(N45="Cancelado",N45="Fora de Uso"),"Inativo",IF(OR(N45="Revisão",N45="Em Elaboração"),"Em tratamento",IF(OR(N45<>"Aprovado",O45=""),"Validar cadastro",IF(O45<DataRef,"Ação imediata",IF(O45<=EDATE(DataRef,12),"Planejar revisão","Regular"))))) -> Regular | S45: =IF(R45="Inativo","Inativo",IF(O45="","Sem validade",IF(O45<DataRef,"Vencida",IF(O45<=DataRef+90,"Até 90 dias",IF(O45<=EDATE(DataRef,12),"91 dias a 12 meses","Após 12 meses"))))) -> Após 12 meses | T45: =IF(O45="","",DATE(YEAR(O45),MONTH(O45),1)) -> 46844 | U45: =IF(R45="Ação imediata",1,IF(N45="Não encontrado",2,IF(N45="Revisão",3,IF(N45="Em Elaboração",4,IF(S45="Até 90 dias",5,IF(R45="Validar cadastro",6,0)))))) -> 0 | V45: =CHOOSE(U45+1,IF(R45="Planejar revisão","Incluir no plano anual de revisão",IF(R45="Inativo","Sem ação","Monitorar")),"Revisar ou prorrogar validade","Confirmar status no NDocs","Acompanhar revisão","Concluir elaboração","Iniciar revisão (≤ 90 dias)","Validar aplicabilidade") -> Monitorar | W45: =(OR(fArea="Todas",ISNUMBER(SEARCH(fArea,G45))))*(OR(fStatus="Todos",N45=fStatus))*(OR(fSit="Todas",R45=fSit))*(OR(fResp="Todos",P45=fResp))*(OR(fHor="Todos",S45=fHor)) -> 1 | X45: =IF(AND(W45=1,U45>0),(7-U45)*100000+50000-IF(ISNUMBER(Q45),Q45,0)+ROW()/1000,0) -> 0 | Y45: =UPPER(A45&" "&TRIM(SUBSTITUTE(C45,CHAR(160)," "))&" "&TRIM(SUBSTITUTE(D45,CHAR(160)," "))) -> BRK-INS-01-016427-PT IT 5020-00216 DETERMINAÇÃO DA DEMANDA QUÍMICA DE OXIGÊNIO EM ÁGUAS E EFLUENTES | Z45: =IF(qBusca="","",IF(ISNUMBER(SEARCH(TRIM(qBusca),Y45)),ROW(),"")) -> 45
A46: BRK-INS-01-016793-PT | B46: 5.0 | C46: IT 6010-00078 | D46: DETERMINAÇÃO DE OXIGÊNIO EM GASES POR TELEDYNE MOD 3010 | E46: Aprovado | F46: 46689 | G46: Q4/AOL | I46: Ana Claudia Sergio De Oliveira | L46: NDocs Q4!44; NDocs AOL!15 | M46: 2 | N46: =IF(TRIM(SUBSTITUTE(E46,CHAR(160)," "))="Avaiação de uso","Avaliação de uso",IF(TRIM(SUBSTITUTE(E46,CHAR(160)," "))="Cancelada","Cancelado",TRIM(SUBSTITUTE(E46,CHAR(160)," ")))) -> Aprovado | O46: =IF(ISNUMBER(F46),F46,IFERROR(DATE(RIGHT(RIGHT(TRIM(F46),10),4),MID(RIGHT(TRIM(F46),10),4,2),LEFT(RIGHT(TRIM(F46),10),2)),"")) -> 46689 | P46: =PROPER(TRIM(SUBSTITUTE(I46,CHAR(160)," "))) -> Ana Claudia Sergio De Oliveira | Q46: =IF(O46="","",O46-DataRef) -> 388 | R46: =IF(OR(N46="Cancelado",N46="Fora de Uso"),"Inativo",IF(OR(N46="Revisão",N46="Em Elaboração"),"Em tratamento",IF(OR(N46<>"Aprovado",O46=""),"Validar cadastro",IF(O46<DataRef,"Ação imediata",IF(O46<=EDATE(DataRef,12),"Planejar revisão","Regular"))))) -> Regular | S46: =IF(R46="Inativo","Inativo",IF(O46="","Sem validade",IF(O46<DataRef,"Vencida",IF(O46<=DataRef+90,"Até 90 dias",IF(O46<=EDATE(DataRef,12),"91 dias a 12 meses","Após 12 meses"))))) -> Após 12 meses | T46: =IF(O46="","",DATE(YEAR(O46),MONTH(O46),1)) -> 46661 | U46: =IF(R46="Ação imediata",1,IF(N46="Não encontrado",2,IF(N46="Revisão",3,IF(N46="Em Elaboração",4,IF(S46="Até 90 dias",5,IF(R46="Validar cadastro",6,0)))))) -> 0 | V46: =CHOOSE(U46+1,IF(R46="Planejar revisão","Incluir no plano anual de revisão",IF(R46="Inativo","Sem ação","Monitorar")),"Revisar ou prorrogar validade","Confirmar status no NDocs","Acompanhar revisão","Concluir elaboração","Iniciar revisão (≤ 90 dias)","Validar aplicabilidade") -> Monitorar | W46: =(OR(fArea="Todas",ISNUMBER(SEARCH(fArea,G46))))*(OR(fStatus="Todos",N46=fStatus))*(OR(fSit="Todas",R46=fSit))*(OR(fResp="Todos",P46=fResp))*(OR(fHor="Todos",S46=fHor)) -> 1 | X46: =IF(AND(W46=1,U46>0),(7-U46)*100000+50000-IF(ISNUMBER(Q46),Q46,0)+ROW()/1000,0) -> 0 | Y46: =UPPER(A46&" "&TRIM(SUBSTITUTE(C46,CHAR(160)," "))&" "&TRIM(SUBSTITUTE(D46,CHAR(160)," "))) -> BRK-INS-01-016793-PT IT 6010-00078 DETERMINAÇÃO DE OXIGÊNIO EM GASES POR TELEDYNE MOD 3010 | Z46: =IF(qBusca="","",IF(ISNUMBER(SEARCH(TRIM(qBusca),Y46)),ROW(),"")) -> 46
A47: BRK-INS-01-018898-PT | B47: 9.0 | C47: IT 5020-00211 | D47: DETERMINAÇÃO DE ÓLEOS E GRAXAS | E47: Revisão | F47: 46506 | G47: Q4 | I47: Ana CARLA DA CRUZ ARAUJO | J47: NBR 14063 - ÓLEOS E GRAXAS - PROCESSOS DE TRATAMENTO EM EFLUENTES DE MINERAÇÃO. | L47: NDocs Q4!45 | M47: 1 | N47: =IF(TRIM(SUBSTITUTE(E47,CHAR(160)," "))="Avaiação de uso","Avaliação de uso",IF(TRIM(SUBSTITUTE(E47,CHAR(160)," "))="Cancelada","Cancelado",TRIM(SUBSTITUTE(E47,CHAR(160)," ")))) -> Revisão | O47: =IF(ISNUMBER(F47),F47,IFERROR(DATE(RIGHT(RIGHT(TRIM(F47),10),4),MID(RIGHT(TRIM(F47),10),4,2),LEFT(RIGHT(TRIM(F47),10),2)),"")) -> 46506 | P47: =PROPER(TRIM(SUBSTITUTE(I47,CHAR(160)," "))) -> Ana Carla Da Cruz Araujo | Q47: =IF(O47="","",O47-DataRef) -> 205 | R47: =IF(OR(N47="Cancelado",N47="Fora de Uso"),"Inativo",IF(OR(N47="Revisão",N47="Em Elaboração"),"Em tratamento",IF(OR(N47<>"Aprovado",O47=""),"Validar cadastro",IF(O47<DataRef,"Ação imediata",IF(O47<=EDATE(DataRef,12),"Planejar revisão","Regular"))))) -> Em tratamento | S47: =IF(R47="Inativo","Inativo",IF(O47="","Sem validade",IF(O47<DataRef,"Vencida",IF(O47<=DataRef+90,"Até 90 dias",IF(O47<=EDATE(DataRef,12),"91 dias a 12 meses","Após 12 meses"))))) -> 91 dias a 12 meses | T47: =IF(O47="","",DATE(YEAR(O47),MONTH(O47),1)) -> 46478 | U47: =IF(R47="Ação imediata",1,IF(N47="Não encontrado",2,IF(N47="Revisão",3,IF(N47="Em Elaboração",4,IF(S47="Até 90 dias",5,IF(R47="Validar cadastro",6,0)))))) -> 3 | V47: =CHOOSE(U47+1,IF(R47="Planejar revisão","Incluir no plano anual de revisão",IF(R47="Inativo","Sem ação","Monitorar")),"Revisar ou prorrogar validade","Confirmar status no NDocs","Acompanhar revisão","Concluir elaboração","Iniciar revisão (≤ 90 dias)","Validar aplicabilidade") -> Acompanhar revisão | W47: =(OR(fArea="Todas",ISNUMBER(SEARCH(fArea,G47))))*(OR(fStatus="Todos",N47=fStatus))*(OR(fSit="Todas",R47=fSit))*(OR(fResp="Todos",P47=fResp))*(OR(fHor="Todos",S47=fHor)) -> 1 | X47: =IF(AND(W47=1,U47>0),(7-U47)*100000+50000-IF(ISNUMBER(Q47),Q47,0)+ROW()/1000,0) -> 449795.05 | Y47: =UPPER(A47&" "&TRIM(SUBSTITUTE(C47,CHAR(160)," "))&" "&TRIM(SUBSTITUTE(D47,CHAR(160)," "))) -> BRK-INS-01-018898-PT IT 5020-00211 DETERMINAÇÃO DE ÓLEOS E GRAXAS | Z47: =IF(qBusca="","",IF(ISNUMBER(SEARCH(TRIM(qBusca),Y47)),ROW(),""))
A48: BRK-INS-01-021077-PT | B48: 1.0 | C48: - | D48: DETERMINAÇÃO DE SOLÚVEIS TOTAIS EM XILENO POR VIA ÚMIDA | E48: Aprovado | F48: 47974 | G48: Q4 | I48: LARISSA VICENTE CARDOSO GUEDES | J48: ASTM 5492-10 - Standard Test Method for Determination of Xylene Solubles in Propylene Plastics. | L48: NDocs Q4!46 | M48: 1 | N48: =IF(TRIM(SUBSTITUTE(E48,CHAR(160)," "))="Avaiação de uso","Avaliação de uso",IF(TRIM(SUBSTITUTE(E48,CHAR(160)," "))="Cancelada","Cancelado",TRIM(SUBSTITUTE(E48,CHAR(160)," ")))) -> Aprovado | O48: =IF(ISNUMBER(F48),F48,IFERROR(DATE(RIGHT(RIGHT(TRIM(F48),10),4),MID(RIGHT(TRIM(F48),10),4,2),LEFT(RIGHT(TRIM(F48),10),2)),"")) -> 47974 | P48: =PROPER(TRIM(SUBSTITUTE(I48,CHAR(160)," "))) -> Larissa Vicente Cardoso Guedes | Q48: =IF(O48="","",O48-DataRef) -> 1673 | R48: =IF(OR(N48="Cancelado",N48="Fora de Uso"),"Inativo",IF(OR(N48="Revisão",N48="Em Elaboração"),"Em tratamento",IF(OR(N48<>"Aprovado",O48=""),"Validar cadastro",IF(O48<DataRef,"Ação imediata",IF(O48<=EDATE(DataRef,12),"Planejar revisão","Regular"))))) -> Regular | S48: =IF(R48="Inativo","Inativo",IF(O48="","Sem validade",IF(O48<DataRef,"Vencida",IF(O48<=DataRef+90,"Até 90 dias",IF(O48<=EDATE(DataRef,12),"91 dias a 12 meses","Após 12 meses"))))) -> Após 12 meses | T48: =IF(O48="","",DATE(YEAR(O48),MONTH(O48),1)) -> 47969 | U48: =IF(R48="Ação imediata",1,IF(N48="Não encontrado",2,IF(N48="Revisão",3,IF(N48="Em Elaboração",4,IF(S48="Até 90 dias",5,IF(R48="Validar cadastro",6,0)))))) -> 0 | V48: =CHOOSE(U48+1,IF(R48="Planejar revisão","Incluir no plano anual de revisão",IF(R48="Inativo","Sem ação","Monitorar")),"Revisar ou prorrogar validade","Confirmar status no NDocs","Acompanhar revisão","Concluir elaboração","Iniciar revisão (≤ 90 dias)","Validar aplicabilidade") -> Monitorar | W48: =(OR(fArea="Todas",ISNUMBER(SEARCH(fArea,G48))))*(OR(fStatus="Todos",N48=fStatus))*(OR(fSit="Todas",R48=fSit))*(OR(fResp="Todos",P48=fResp))*(OR(fHor="Todos",S48=fHor)) -> 1 | X48: =IF(AND(W48=1,U48>0),(7-U48)*100000+50000-IF(ISNUMBER(Q48),Q48,0)+ROW()/1000,0) -> 0 | Y48: =UPPER(A48&" "&TRIM(SUBSTITUTE(C48,CHAR(160)," "))&" "&TRIM(SUBSTITUTE(D48,CHAR(160)," "))) -> BRK-INS-01-021077-PT - DETERMINAÇÃO DE SOLÚVEIS TOTAIS EM XILENO POR VIA ÚMIDA | Z48: =IF(qBusca="","",IF(ISNUMBER(SEARCH(TRIM(qBusca),Y48)),ROW(),""))
A49: BRK-INS-01-018900-PT | B49: 7.0 | C49: IT 5020-00218 | D49: DETERMINAÇÃO DA COR REAL OU APARENTE | E49: Aprovado | F49: 46689 | G49: Q4 | I49: Ana CARLA DA CRUZ ARAUJO | L49: NDocs Q4!47 | M49: 1 | N49: =IF(TRIM(SUBSTITUTE(E49,CHAR(160)," "))="Avaiação de uso","Avaliação de uso",IF(TRIM(SUBSTITUTE(E49,CHAR(160)," "))="Cancelada","Cancelado",TRIM(SUBSTITUTE(E49,CHAR(160)," ")))) -> Aprovado | O49: =IF(ISNUMBER(F49),F49,IFERROR(DATE(RIGHT(RIGHT(TRIM(F49),10),4),MID(RIGHT(TRIM(F49),10),4,2),LEFT(RIGHT(TRIM(F49),10),2)),"")) -> 46689 | P49: =PROPER(TRIM(SUBSTITUTE(I49,CHAR(160)," "))) -> Ana Carla Da Cruz Araujo | Q49: =IF(O49="","",O49-DataRef) -> 388 | R49: =IF(OR(N49="Cancelado",N49="Fora de Uso"),"Inativo",IF(OR(N49="Revisão",N49="Em Elaboração"),"Em tratamento",IF(OR(N49<>"Aprovado",O49=""),"Validar cadastro",IF(O49<DataRef,"Ação imediata",IF(O49<=EDATE(DataRef,12),"Planejar revisão","Regular"))))) -> Regular | S49: =IF(R49="Inativo","Inativo",IF(O49="","Sem validade",IF(O49<DataRef,"Vencida",IF(O49<=DataRef+90,"Até 90 dias",IF(O49<=EDATE(DataRef,12),"91 dias a 12 meses","Após 12 meses"))))) -> Após 12 meses | T49: =IF(O49="","",DATE(YEAR(O49),MONTH(O49),1)) -> 46661 | U49: =IF(R49="Ação imediata",1,IF(N49="Não encontrado",2,IF(N49="Revisão",3,IF(N49="Em Elaboração",4,IF(S49="Até 90 dias",5,IF(R49="Validar cadastro",6,0)))))) -> 0 | V49: =CHOOSE(U49+1,IF(R49="Planejar revisão","Incluir no plano anual de revisão",IF(R49="Inativo","Sem ação","Monitorar")),"Revisar ou prorrogar validade","Confirmar status no NDocs","Acompanhar revisão","Concluir elaboração","Iniciar revisão (≤ 90 dias)","Validar aplicabilidade") -> Monitorar | W49: =(OR(fArea="Todas",ISNUMBER(SEARCH(fArea,G49))))*(OR(fStatus="Todos",N49=fStatus))*(OR(fSit="Todas",R49=fSit))*(OR(fResp="Todos",P49=fResp))*(OR(fHor="Todos",S49=fHor)) -> 1 | X49: =IF(AND(W49=1,U49>0),(7-U49)*100000+50000-IF(ISNUMBER(Q49),Q49,0)+ROW()/1000,0) -> 0 | Y49: =UPPER(A49&" "&TRIM(SUBSTITUTE(C49,CHAR(160)," "))&" "&TRIM(SUBSTITUTE(D49,CHAR(160)," "))) -> BRK-INS-01-018900-PT IT 5020-00218 DETERMINAÇÃO DA COR REAL OU APARENTE | Z49: =IF(qBusca="","",IF(ISNUMBER(SEARCH(TRIM(qBusca),Y49)),ROW(),""))
A50: BRK-INS-01-021191-PT | B50: 1.0 | C50: - | D50: ANÁLISE DE TOXICIDADE AGUDA EM EFLUENTES INDUSTRIAIS - ECOTOXICIDADE DCX | E50: Aprovado | F50: 48093 | G50: Q4 | I50: LARISSA VICENTE CARDOSO GUEDES | L50: NDocs Q4!48 | M50: 1 | N50: =IF(TRIM(SUBSTITUTE(E50,CHAR(160)," "))="Avaiação de uso","Avaliação de uso",IF(TRIM(SUBSTITUTE(E50,CHAR(160)," "))="Cancelada","Cancelado",TRIM(SUBSTITUTE(E50,CHAR(160)," ")))) -> Aprovado | O50: =IF(ISNUMBER(F50),F50,IFERROR(DATE(RIGHT(RIGHT(TRIM(F50),10),4),MID(RIGHT(TRIM(F50),10),4,2),LEFT(RIGHT(TRIM(F50),10),2)),"")) -> 48093 | P50: =PROPER(TRIM(SUBSTITUTE(I50,CHAR(160)," "))) -> Larissa Vicente Cardoso Guedes | Q50: =IF(O50="","",O50-DataRef) -> 1792 | R50: =IF(OR(N50="Cancelado",N50="Fora de Uso"),"Inativo",IF(OR(N50="Revisão",N50="Em Elaboração"),"Em tratamento",IF(OR(N50<>"Aprovado",O50=""),"Validar cadastro",IF(O50<DataRef,"Ação imediata",IF(O50<=EDATE(DataRef,12),"Planejar revisão","Regular"))))) -> Regular | S50: =IF(R50="Inativo","Inativo",IF(O50="","Sem validade",IF(O50<DataRef,"Vencida",IF(O50<=DataRef+90,"Até 90 dias",IF(O50<=EDATE(DataRef,12),"91 dias a 12 meses","Após 12 meses"))))) -> Após 12 meses | T50: =IF(O50="","",DATE(YEAR(O50),MONTH(O50),1)) -> 48092 | U50: =IF(R50="Ação imediata",1,IF(N50="Não encontrado",2,IF(N50="Revisão",3,IF(N50="Em Elaboração",4,IF(S50="Até 90 dias",5,IF(R50="Validar cadastro",6,0)))))) -> 0 | V50: =CHOOSE(U50+1,IF(R50="Planejar revisão","Incluir no plano anual de revisão",IF(R50="Inativo","Sem ação","Monitorar")),"Revisar ou prorrogar validade","Confirmar status no NDocs","Acompanhar revisão","Concluir elaboração","Iniciar revisão (≤ 90 dias)","Validar aplicabilidade") -> Monitorar | W50: =(OR(fArea="Todas",ISNUMBER(SEARCH(fArea,G50))))*(OR(fStatus="Todos",N50=fStatus))*(OR(fSit="Todas",R50=fSit))*(OR(fResp="Todos",P50=fResp))*(OR(fHor="Todos",S50=fHor)) -> 1 | X50: =IF(AND(W50=1,U50>0),(7-U50)*100000+50000-IF(ISNUMBER(Q50),Q50,0)+ROW()/1000,0) -> 0 | Y50: =UPPER(A50&" "&TRIM(SUBSTITUTE(C50,CHAR(160)," "))&" "&TRIM(SUBSTITUTE(D50,CHAR(160)," "))) -> BRK-INS-01-021191-PT - ANÁLISE DE TOXICIDADE AGUDA EM EFLUENTES INDUSTRIAIS - ECOTOXICIDADE DCX | Z50: =IF(qBusca="","",IF(ISNUMBER(SEARCH(TRIM(qBusca),Y50)),ROW(),""))
A51: BRK-INS-01-014036-PT | B51: 7.0 | C51: IT 5020-02043 | D51: DETERMINAÇÃO DE GOMA EM GASOLINAS E SOLVENTES | E51: Aprovado | F51: 47785 | G51: Q4 | H51: UNIFICADA | I51: Tainara Starssbuger | J51: ASTM D381 - STANDARD TEST METHOD FOR GUM CONTENT IN FUELS BY JET EVAPORATION. | L51: NDocs Q4!49 | M51: 1 | N51: =IF(TRIM(SUBSTITUTE(E51,CHAR(160)," "))="Avaiação de uso","Avaliação de uso",IF(TRIM(SUBSTITUTE(E51,CHAR(160)," "))="Cancelada","Cancelado",TRIM(SUBSTITUTE(E51,CHAR(160)," ")))) -> Aprovado | O51: =IF(ISNUMBER(F51),F51,IFERROR(DATE(RIGHT(RIGHT(TRIM(F51),10),4),MID(RIGHT(TRIM(F51),10),4,2),LEFT(RIGHT(TRIM(F51),10),2)),"")) -> 47785 | P51: =PROPER(TRIM(SUBSTITUTE(I51,CHAR(160)," "))) -> Tainara Starssbuger | Q51: =IF(O51="","",O51-DataRef) -> 1484 | R51: =IF(OR(N51="Cancelado",N51="Fora de Uso"),"Inativo",IF(OR(N51="Revisão",N51="Em Elaboração"),"Em tratamento",IF(OR(N51<>"Aprovado",O51=""),"Validar cadastro",IF(O51<DataRef,"Ação imediata",IF(O51<=EDATE(DataRef,12),"Planejar revisão","Regular"))))) -> Regular | S51: =IF(R51="Inativo","Inativo",IF(O51="","Sem validade",IF(O51<DataRef,"Vencida",IF(O51<=DataRef+90,"Até 90 dias",IF(O51<=EDATE(DataRef,12),"91 dias a 12 meses","Após 12 meses"))))) -> Após 12 meses | T51: =IF(O51="","",DATE(YEAR(O51),MONTH(O51),1)) -> 47757 | U51: =IF(R51="Ação imediata",1,IF(N51="Não encontrado",2,IF(N51="Revisão",3,IF(N51="Em Elaboração",4,IF(S51="Até 90 dias",5,IF(R51="Validar cadastro",6,0)))))) -> 0 | V51: =CHOOSE(U51+1,IF(R51="Planejar revisão","Incluir no plano anual de revisão",IF(R51="Inativo","Sem ação","Monitorar")),"Revisar ou prorrogar validade","Confirmar status no NDocs","Acompanhar revisão","Concluir elaboração","Iniciar revisão (≤ 90 dias)","Validar aplicabilidade") -> Monitorar | W51: =(OR(fArea="Todas",ISNUMBER(SEARCH(fArea,G51))))*(OR(fStatus="Todos",N51=fStatus))*(OR(fSit="Todas",R51=fSit))*(OR(fResp="Todos",P51=fResp))*(OR(fHor="Todos",S51=fHor)) -> 1 | X51: =IF(AND(W51=1,U51>0),(7-U51)*100000+50000-IF(ISNUMBER(Q51),Q51,0)+ROW()/1000,0) -> 0 | Y51: =UPPER(A51&" "&TRIM(SUBSTITUTE(C51,CHAR(160)," "))&" "&TRIM(SUBSTITUTE(D51,CHAR(160)," "))) -> BRK-INS-01-014036-PT IT 5020-02043 DETERMINAÇÃO DE GOMA EM GASOLINAS E SOLVENTES | Z51: =IF(qBusca="","",IF(ISNUMBER(SEARCH(TRIM(qBusca),Y51)),ROW(),""))
A52: BRK-INS-01-010120-PT | B52: 8.0 | C52: IT 5020-00249 | D52: DETERMINAÇÃO DE HIDROGÊNIO E/ OU OUTROS GASES FIXOS POR CROMATOGRAFIA EM FASE GASOSA | E52: Aprovado | F52: 47864 | G52: Q4 | H52: UNIFICADA | I52: FATIMA MOURA GUTERRES | J52: ASTM D2504; ASTM D1946 | L52: NDocs Q4!50 | M52: 1 | N52: =IF(TRIM(SUBSTITUTE(E52,CHAR(160)," "))="Avaiação de uso","Avaliação de uso",IF(TRIM(SUBSTITUTE(E52,CHAR(160)," "))="Cancelada","Cancelado",TRIM(SUBSTITUTE(E52,CHAR(160)," ")))) -> Aprovado | O52: =IF(ISNUMBER(F52),F52,IFERROR(DATE(RIGHT(RIGHT(TRIM(F52),10),4),MID(RIGHT(TRIM(F52),10),4,2),LEFT(RIGHT(TRIM(F52),10),2)),"")) -> 47864 | P52: =PROPER(TRIM(SUBSTITUTE(I52,CHAR(160)," "))) -> Fatima Moura Guterres | Q52: =IF(O52="","",O52-DataRef) -> 1563 | R52: =IF(OR(N52="Cancelado",N52="Fora de Uso"),"Inativo",IF(OR(N52="Revisão",N52="Em Elaboração"),"Em tratamento",IF(OR(N52<>"Aprovado",O52=""),"Validar cadastro",IF(O52<DataRef,"Ação imediata",IF(O52<=EDATE(DataRef,12),"Planejar revisão","Regular"))))) -> Regular | S52: =IF(R52="Inativo","Inativo",IF(O52="","Sem validade",IF(O52<DataRef,"Vencida",IF(O52<=DataRef+90,"Até 90 dias",IF(O52<=EDATE(DataRef,12),"91 dias a 12 meses","Após 12 meses"))))) -> Após 12 meses | T52: =IF(O52="","",DATE(YEAR(O52),MONTH(O52),1)) -> 47849 | U52: =IF(R52="Ação imediata",1,IF(N52="Não encontrado",2,IF(N52="Revisão",3,IF(N52="Em Elaboração",4,IF(S52="Até 90 dias",5,IF(R52="Validar cadastro",6,0)))))) -> 0 | V52: =CHOOSE(U52+1,IF(R52="Planejar revisão","Incluir no plano anual de revisão",IF(R52="Inativo","Sem ação","Monitorar")),"Revisar ou prorrogar validade","Confirmar status no NDocs","Acompanhar revisão","Concluir elaboração","Iniciar revisão (≤ 90 dias)","Validar aplicabilidade") -> Monitorar | W52: =(OR(fArea="Todas",ISNUMBER(SEARCH(fArea,G52))))*(OR(fStatus="Todos",N52=fStatus))*(OR(fSit="Todas",R52=fSit))*(OR(fResp="Todos",P52=fResp))*(OR(fHor="Todos",S52=fHor)) -> 1 | X52: =IF(AND(W52=1,U52>0),(7-U52)*100000+50000-IF(ISNUMBER(Q52),Q52,0)+ROW()/1000,0) -> 0 | Y52: =UPPER(A52&" "&TRIM(SUBSTITUTE(C52,CHAR(160)," "))&" "&TRIM(SUBSTITUTE(D52,CHAR(160)," "))) -> BRK-INS-01-010120-PT IT 5020-00249 DETERMINAÇÃO DE HIDROGÊNIO E/ OU OUTROS GASES FIXOS POR CROMATOGRAFIA EM FASE GASOSA | Z52: =IF(qBusca="","",IF(ISNUMBER(SEARCH(TRIM(qBusca),Y52)),ROW(),""))
A53: BRK-INS-01-010835-PT | B53: 6.0 | C53: IT 5020-01060 | D53: COMPOSTOS OXIGENADOS EM HIDROCARBONETOS LÍQUIDOS POR CROMATOGRAFIA GASOSA E DETECTOR FID | E53: Fora de Uso | F53: 48074 | G53: Q4 | H53: UNIFICADA | I53: Daniel Cesar De Abreu | J53: ASTM D7423 - STANDARD TEST METHOD FOR DETERMINATION OF OXYGENATES IN C2, C3, C4, AND C5 HYDROCARBON MATRICES BY GAS CHROMATOGRAPHY AND FLAME IONIZATION DETECTION. | L53: NDocs Q4!51 | M53: 1 | N53: =IF(TRIM(SUBSTITUTE(E53,CHAR(160)," "))="Avaiação de uso","Avaliação de uso",IF(TRIM(SUBSTITUTE(E53,CHAR(160)," "))="Cancelada","Cancelado",TRIM(SUBSTITUTE(E53,CHAR(160)," ")))) -> Fora de Uso | O53: =IF(ISNUMBER(F53),F53,IFERROR(DATE(RIGHT(RIGHT(TRIM(F53),10),4),MID(RIGHT(TRIM(F53),10),4,2),LEFT(RIGHT(TRIM(F53),10),2)),"")) -> 48074 | P53: =PROPER(TRIM(SUBSTITUTE(I53,CHAR(160)," "))) -> Daniel Cesar De Abreu | Q53: =IF(O53="","",O53-DataRef) -> 1773 | R53: =IF(OR(N53="Cancelado",N53="Fora de Uso"),"Inativo",IF(OR(N53="Revisão",N53="Em Elaboração"),"Em tratamento",IF(OR(N53<>"Aprovado",O53=""),"Validar cadastro",IF(O53<DataRef,"Ação imediata",IF(O53<=EDATE(DataRef,12),"Planejar revisão","Regular"))))) -> Inativo | S53: =IF(R53="Inativo","Inativo",IF(O53="","Sem validade",IF(O53<DataRef,"Vencida",IF(O53<=DataRef+90,"Até 90 dias",IF(O53<=EDATE(DataRef,12),"91 dias a 12 meses","Após 12 meses"))))) -> Inativo | T53: =IF(O53="","",DATE(YEAR(O53),MONTH(O53),1)) -> 48061 | U53: =IF(R53="Ação imediata",1,IF(N53="Não encontrado",2,IF(N53="Revisão",3,IF(N53="Em Elaboração",4,IF(S53="Até 90 dias",5,IF(R53="Validar cadastro",6,0)))))) -> 0 | V53: =CHOOSE(U53+1,IF(R53="Planejar revisão","Incluir no plano anual de revisão",IF(R53="Inativo","Sem ação","Monitorar")),"Revisar ou prorrogar validade","Confirmar status no NDocs","Acompanhar revisão","Concluir elaboração","Iniciar revisão (≤ 90 dias)","Validar aplicabilidade") -> Sem ação | W53: =(OR(fArea="Todas",ISNUMBER(SEARCH(fArea,G53))))*(OR(fStatus="Todos",N53=fStatus))*(OR(fSit="Todas",R53=fSit))*(OR(fResp="Todos",P53=fResp))*(OR(fHor="Todos",S53=fHor)) -> 1 | X53: =IF(AND(W53=1,U53>0),(7-U53)*100000+50000-IF(ISNUMBER(Q53),Q53,0)+ROW()/1000,0) -> 0 | Y53: =UPPER(A53&" "&TRIM(SUBSTITUTE(C53,CHAR(160)," "))&" "&TRIM(SUBSTITUTE(D53,CHAR(160)," "))) -> BRK-INS-01-010835-PT IT 5020-01060 COMPOSTOS OXIGENADOS EM HIDROCARBONETOS LÍQUIDOS POR CROMATOGRAFIA GASOSA E DETECTOR FID | Z53: =IF(qBusca="","",IF(ISNUMBER(SEARCH(TRIM(qBusca),Y53)),ROW(),""))
A54: BRK-INS-01-011537-PT | B54: 6.0 | C54: IT 5020-01254 | D54: DETERMINAÇÃO DE COMPOSTOS SULFURADOS EM HC GASOSOS OU LIQUEFEITOS POR CG E DETECÇÃO POR QUIMILUMINÊSCENCIA | E54: Aprovado | F54: 46754 | G54: Q4 | H54: UNIFICADA | I54: FATIMA MOURA GUTERRES | J54: ASTM D5504 | L54: NDocs Q4!52 | M54: 1 | N54: =IF(TRIM(SUBSTITUTE(E54,CHAR(160)," "))="Avaiação de uso","Avaliação de uso",IF(TRIM(SUBSTITUTE(E54,CHAR(160)," "))="Cancelada","Cancelado",TRIM(SUBSTITUTE(E54,CHAR(160)," ")))) -> Aprovado | O54: =IF(ISNUMBER(F54),F54,IFERROR(DATE(RIGHT(RIGHT(TRIM(F54),10),4),MID(RIGHT(TRIM(F54),10),4,2),LEFT(RIGHT(TRIM(F54),10),2)),"")) -> 46754 | P54: =PROPER(TRIM(SUBSTITUTE(I54,CHAR(160)," "))) -> Fatima Moura Guterres | Q54: =IF(O54="","",O54-DataRef) -> 453 | R54: =IF(OR(N54="Cancelado",N54="Fora de Uso"),"Inativo",IF(OR(N54="Revisão",N54="Em Elaboração"),"Em tratamento",IF(OR(N54<>"Aprovado",O54=""),"Validar cadastro",IF(O54<DataRef,"Ação imediata",IF(O54<=EDATE(DataRef,12),"Planejar revisão","Regular"))))) -> Regular | S54: =IF(R54="Inativo","Inativo",IF(O54="","Sem validade",IF(O54<DataRef,"Vencida",IF(O54<=DataRef+90,"Até 90 dias",IF(O54<=EDATE(DataRef,12),"91 dias a 12 meses","Após 12 meses"))))) -> Após 12 meses | T54: =IF(O54="","",DATE(YEAR(O54),MONTH(O54),1)) -> 46753 | U54: =IF(R54="Ação imediata",1,IF(N54="Não encontrado",2,IF(N54="Revisão",3,IF(N54="Em Elaboração",4,IF(S54="Até 90 dias",5,IF(R54="Validar cadastro",6,0)))))) -> 0 | V54: =CHOOSE(U54+1,IF(R54="Planejar revisão","Incluir no plano anual de revisão",IF(R54="Inativo","Sem ação","Monitorar")),"Revisar ou prorrogar validade","Confirmar status no NDocs","Acompanhar revisão","Concluir elaboração","Iniciar revisão (≤ 90 dias)","Validar aplicabilidade") -> Monitorar | W54: =(OR(fArea="Todas",ISNUMBER(SEARCH(fArea,G54))))*(OR(fStatus="Todos",N54=fStatus))*(OR(fSit="Todas",R54=fSit))*(OR(fResp="Todos",P54=fResp))*(OR(fHor="Todos",S54=fHor)) -> 1 | X54: =IF(AND(W54=1,U54>0),(7-U54)*100000+50000-IF(ISNUMBER(Q54),Q54,0)+ROW()/1000,0) -> 0 | Y54: =UPPER(A54&" "&TRIM(SUBSTITUTE(C54,CHAR(160)," "))&" "&TRIM(SUBSTITUTE(D54,CHAR(160)," "))) -> BRK-INS-01-011537-PT IT 5020-01254 DETERMINAÇÃO DE COMPOSTOS SULFURADOS EM HC GASOSOS OU LIQUEFEITOS POR CG E DETECÇÃO POR QUIMILUMINÊSCENCIA | Z54: =IF(qBusca="","",IF(ISNUMBER(SEARCH(TRIM(qBusca),Y54)),ROW(),""))
A55: BRK-INS-01-016214-PT | B55: 9.0 | C55: IT 5020-00169 | D55: DETERMINAÇÃO DE ENXOFRE TOTAL POR FLUORESCÊNCIA | E55: Aprovado | F55: 47982 | G55: Q4 | H55: UNIFICADA | I55: FATIMA MOURA GUTERRES | J55: ASTM D5453; ASTM D6667; ASTM D7183 - STANDARD TEST METHOD FOR DETERMINATION OF TOTAL SULFUR IN AROMATIC HYDROCARBONS AND RELATED CHEMICALS BY ULTRAVIOLET FLUORESCENCE. | L55: NDocs Q4!53 | M55: 1 | N55: =IF(TRIM(SUBSTITUTE(E55,CHAR(160)," "))="Avaiação de uso","Avaliação de uso",IF(TRIM(SUBSTITUTE(E55,CHAR(160)," "))="Cancelada","Cancelado",TRIM(SUBSTITUTE(E55,CHAR(160)," ")))) -> Aprovado | O55: =IF(ISNUMBER(F55),F55,IFERROR(DATE(RIGHT(RIGHT(TRIM(F55),10),4),MID(RIGHT(TRIM(F55),10),4,2),LEFT(RIGHT(TRIM(F55),10),2)),"")) -> 47982 | P55: =PROPER(TRIM(SUBSTITUTE(I55,CHAR(160)," "))) -> Fatima Moura Guterres | Q55: =IF(O55="","",O55-DataRef) -> 1681 | R55: =IF(OR(N55="Cancelado",N55="Fora de Uso"),"Inativo",IF(OR(N55="Revisão",N55="Em Elaboração"),"Em tratamento",IF(OR(N55<>"Aprovado",O55=""),"Validar cadastro",IF(O55<DataRef,"Ação imediata",IF(O55<=EDATE(DataRef,12),"Planejar revisão","Regular"))))) -> Regular | S55: =IF(R55="Inativo","Inativo",IF(O55="","Sem validade",IF(O55<DataRef,"Vencida",IF(O55<=DataRef+90,"Até 90 dias",IF(O55<=EDATE(DataRef,12),"91 dias a 12 meses","Após 12 meses"))))) -> Após 12 meses | T55: =IF(O55="","",DATE(YEAR(O55),MONTH(O55),1)) -> 47969 | U55: =IF(R55="Ação imediata",1,IF(N55="Não encontrado",2,IF(N55="Revisão",3,IF(N55="Em Elaboração",4,IF(S55="Até 90 dias",5,IF(R55="Validar cadastro",6,0)))))) -> 0 | V55: =CHOOSE(U55+1,IF(R55="Planejar revisão","Incluir no plano anual de revisão",IF(R55="Inativo","Sem ação","Monitorar")),"Revisar ou prorrogar validade","Confirmar status no NDocs","Acompanhar revisão","Concluir elaboração","Iniciar revisão (≤ 90 dias)","Validar aplicabilidade") -> Monitorar | W55: =(OR(fArea="Todas",ISNUMBER(SEARCH(fArea,G55))))*(OR(fStatus="Todos",N55=fStatus))*(OR(fSit="Todas",R55=fSit))*(OR(fResp="Todos",P55=fResp))*(OR(fHor="Todos",S55=fHor)) -> 1 | X55: =IF(AND(W55=1,U55>0),(7-U55)*100000+50000-IF(ISNUMBER(Q55),Q55,0)+ROW()/1000,0) -> 0 | Y55: =UPPER(A55&" "&TRIM(SUBSTITUTE(C55,CHAR(160)," "))&" "&TRIM(SUBSTITUTE(D55,CHAR(160)," "))) -> BRK-INS-01-016214-PT IT 5020-00169 DETERMINAÇÃO DE ENXOFRE TOTAL POR FLUORESCÊNCIA | Z55: =IF(qBusca="","",IF(ISNUMBER(SEARCH(TRIM(qBusca),Y55)),ROW(),""))
A56: BRK-INS-01-016270-PT | B56: 8.0 | C56: IT 5020-00183 | D56: DETERMINAÇÃO DE OXIDOS DE CARBONO POR CROMATOGRAFIA GASOSA | E56: Aprovado | F56: 48032 | G56: Q4 | H56: UNIFICADA | I56: FATIMA MOURA GUTERRES | J56: UOP 603 - TRACE CO AND CO2 IN HYDROGEN AND LIGHT GASEOUS HYDROCARBONS BY GC. | L56: NDocs Q4!54 | M56: 1 | N56: =IF(TRIM(SUBSTITUTE(E56,CHAR(160)," "))="Avaiação de uso","Avaliação de uso",IF(TRIM(SUBSTITUTE(E56,CHAR(160)," "))="Cancelada","Cancelado",TRIM(SUBSTITUTE(E56,CHAR(160)," ")))) -> Aprovado | O56: =IF(ISNUMBER(F56),F56,IFERROR(DATE(RIGHT(RIGHT(TRIM(F56),10),4),MID(RIGHT(TRIM(F56),10),4,2),LEFT(RIGHT(TRIM(F56),10),2)),"")) -> 48032 | P56: =PROPER(TRIM(SUBSTITUTE(I56,CHAR(160)," "))) -> Fatima Moura Guterres | Q56: =IF(O56="","",O56-DataRef) -> 1731 | R56: =IF(OR(N56="Cancelado",N56="Fora de Uso"),"Inativo",IF(OR(N56="Revisão",N56="Em Elaboração"),"Em tratamento",IF(OR(N56<>"Aprovado",O56=""),"Validar cadastro",IF(O56<DataRef,"Ação imediata",IF(O56<=EDATE(DataRef,12),"Planejar revisão","Regular"))))) -> Regular | S56: =IF(R56="Inativo","Inativo",IF(O56="","Sem validade",IF(O56<DataRef,"Vencida",IF(O56<=DataRef+90,"Até 90 dias",IF(O56<=EDATE(DataRef,12),"91 dias a 12 meses","Após 12 meses"))))) -> Após 12 meses | T56: =IF(O56="","",DATE(YEAR(O56),MONTH(O56),1)) -> 48030 | U56: =IF(R56="Ação imediata",1,IF(N56="Não encontrado",2,IF(N56="Revisão",3,IF(N56="Em Elaboração",4,IF(S56="Até 90 dias",5,IF(R56="Validar cadastro",6,0)))))) -> 0 | V56: =CHOOSE(U56+1,IF(R56="Planejar revisão","Incluir no plano anual de revisão",IF(R56="Inativo","Sem ação","Monitorar")),"Revisar ou prorrogar validade","Confirmar status no NDocs","Acompanhar revisão","Concluir elaboração","Iniciar revisão (≤ 90 dias)","Validar aplicabilidade") -> Monitorar | W56: =(OR(fArea="Todas",ISNUMBER(SEARCH(fArea,G56))))*(OR(fStatus="Todos",N56=fStatus))*(OR(fSit="Todas",R56=fSit))*(OR(fResp="Todos",P56=fResp))*(OR(fHor="Todos",S56=fHor)) -> 1 | X56: =IF(AND(W56=1,U56>0),(7-U56)*100000+50000-IF(ISNUMBER(Q56),Q56,0)+ROW()/1000,0) -> 0 | Y56: =UPPER(A56&" "&TRIM(SUBSTITUTE(C56,CHAR(160)," "))&" "&TRIM(SUBSTITUTE(D56,CHAR(160)," "))) -> BRK-INS-01-016270-PT IT 5020-00183 DETERMINAÇÃO DE OXIDOS DE CARBONO POR CROMATOGRAFIA GASOSA | Z56: =IF(qBusca="","",IF(ISNUMBER(SEARCH(TRIM(qBusca),Y56)),ROW(),""))
A57: BRK-INS-01-018920-PT | B57: 7.0 | C57: IT 5020-01083 | D57: RESÍDUO NÃO-VOLÁTIL EM GASES LIQUEFEITOS DE PETRÓLEO | E57: Aprovado | F57: 47937 | G57: Q4 | H57: UNIFICADA | I57: Gabrielle Cristina Candido Pereira | L57: NDocs Q4!55 | M57: 1 | N57: =IF(TRIM(SUBSTITUTE(E57,CHAR(160)," "))="Avaiação de uso","Avaliação de uso",IF(TRIM(SUBSTITUTE(E57,CHAR(160)," "))="Cancelada","Cancelado",TRIM(SUBSTITUTE(E57,CHAR(160)," ")))) -> Aprovado | O57: =IF(ISNUMBER(F57),F57,IFERROR(DATE(RIGHT(RIGHT(TRIM(F57),10),4),MID(RIGHT(TRIM(F57),10),4,2),LEFT(RIGHT(TRIM(F57),10),2)),"")) -> 47937 | P57: =PROPER(TRIM(SUBSTITUTE(I57,CHAR(160)," "))) -> Gabrielle Cristina Candido Pereira | Q57: =IF(O57="","",O57-DataRef) -> 1636 | R57: =IF(OR(N57="Cancelado",N57="Fora de Uso"),"Inativo",IF(OR(N57="Revisão",N57="Em Elaboração"),"Em tratamento",IF(OR(N57<>"Aprovado",O57=""),"Validar cadastro",IF(O57<DataRef,"Ação imediata",IF(O57<=EDATE(DataRef,12),"Planejar revisão","Regular"))))) -> Regular | S57: =IF(R57="Inativo","Inativo",IF(O57="","Sem validade",IF(O57<DataRef,"Vencida",IF(O57<=DataRef+90,"Até 90 dias",IF(O57<=EDATE(DataRef,12),"91 dias a 12 meses","Após 12 meses"))))) -> Após 12 meses | T57: =IF(O57="","",DATE(YEAR(O57),MONTH(O57),1)) -> 47908 | U57: =IF(R57="Ação imediata",1,IF(N57="Não encontrado",2,IF(N57="Revisão",3,IF(N57="Em Elaboração",4,IF(S57="Até 90 dias",5,IF(R57="Validar cadastro",6,0)))))) -> 0 | V57: =CHOOSE(U57+1,IF(R57="Planejar revisão","Incluir no plano anual de revisão",IF(R57="Inativo","Sem ação","Monitorar")),"Revisar ou prorrogar validade","Confirmar status no NDocs","Acompanhar revisão","Concluir elaboração","Iniciar revisão (≤ 90 dias)","Validar aplicabilidade") -> Monitorar | W57: =(OR(fArea="Todas",ISNUMBER(SEARCH(fArea,G57))))*(OR(fStatus="Todos",N57=fStatus))*(OR(fSit="Todas",R57=fSit))*(OR(fResp="Todos",P57=fResp))*(OR(fHor="Todos",S57=fHor)) -> 1 | X57: =IF(AND(W57=1,U57>0),(7-U57)*100000+50000-IF(ISNUMBER(Q57),Q57,0)+ROW()/1000,0) -> 0 | Y57: =UPPER(A57&" "&TRIM(SUBSTITUTE(C57,CHAR(160)," "))&" "&TRIM(SUBSTITUTE(D57,CHAR(160)," "))) -> BRK-INS-01-018920-PT IT 5020-01083 RESÍDUO NÃO-VOLÁTIL EM GASES LIQUEFEITOS DE PETRÓLEO | Z57: =IF(qBusca="","",IF(ISNUMBER(SEARCH(TRIM(qBusca),Y57)),ROW(),""))
A58: BRK-INS-01-011759-PT | B58: 6.0 | C58: IT 5020-01328 | D58: DETERMINAÇÃO DE HIDROCARBONETOS CONTAMINANTES NO PROPENO POR CROMATOGRAFIA GASOSA | E58: Aprovado | F58: 46461 | G58: Q4 | H58: UNIFICADA | I58: FATIMA MOURA GUTERRES | J58: ASTM D2712; ASTM D2163 | L58: NDocs Q4!56 | M58: 1 | N58: =IF(TRIM(SUBSTITUTE(E58,CHAR(160)," "))="Avaiação de uso","Avaliação de uso",IF(TRIM(SUBSTITUTE(E58,CHAR(160)," "))="Cancelada","Cancelado",TRIM(SUBSTITUTE(E58,CHAR(160)," ")))) -> Aprovado | O58: =IF(ISNUMBER(F58),F58,IFERROR(DATE(RIGHT(RIGHT(TRIM(F58),10),4),MID(RIGHT(TRIM(F58),10),4,2),LEFT(RIGHT(TRIM(F58),10),2)),"")) -> 46461 | P58: =PROPER(TRIM(SUBSTITUTE(I58,CHAR(160)," "))) -> Fatima Moura Guterres | Q58: =IF(O58="","",O58-DataRef) -> 160 | R58: =IF(OR(N58="Cancelado",N58="Fora de Uso"),"Inativo",IF(OR(N58="Revisão",N58="Em Elaboração"),"Em tratamento",IF(OR(N58<>"Aprovado",O58=""),"Validar cadastro",IF(O58<DataRef,"Ação imediata",IF(O58<=EDATE(DataRef,12),"Planejar revisão","Regular"))))) -> Planejar revisão | S58: =IF(R58="Inativo","Inativo",IF(O58="","Sem validade",IF(O58<DataRef,"Vencida",IF(O58<=DataRef+90,"Até 90 dias",IF(O58<=EDATE(DataRef,12),"91 dias a 12 meses","Após 12 meses"))))) -> 91 dias a 12 meses | T58: =IF(O58="","",DATE(YEAR(O58),MONTH(O58),1)) -> 46447 | U58: =IF(R58="Ação imediata",1,IF(N58="Não encontrado",2,IF(N58="Revisão",3,IF(N58="Em Elaboração",4,IF(S58="Até 90 dias",5,IF(R58="Validar cadastro",6,0)))))) -> 0 | V58: =CHOOSE(U58+1,IF(R58="Planejar revisão","Incluir no plano anual de revisão",IF(R58="Inativo","Sem ação","Monitorar")),"Revisar ou prorrogar validade","Confirmar status no NDocs","Acompanhar revisão","Concluir elaboração","Iniciar revisão (≤ 90 dias)","Validar aplicabilidade") -> Incluir no plano anual de revisão | W58: =(OR(fArea="Todas",ISNUMBER(SEARCH(fArea,G58))))*(OR(fStatus="Todos",N58=fStatus))*(OR(fSit="Todas",R58=fSit))*(OR(fResp="Todos",P58=fResp))*(OR(fHor="Todos",S58=fHor)) -> 1 | X58: =IF(AND(W58=1,U58>0),(7-U58)*100000+50000-IF(ISNUMBER(Q58),Q58,0)+ROW()/1000,0) -> 0 | Y58: =UPPER(A58&" "&TRIM(SUBSTITUTE(C58,CHAR(160)," "))&" "&TRIM(SUBSTITUTE(D58,CHAR(160)," "))) -> BRK-INS-01-011759-PT IT 5020-01328 DETERMINAÇÃO DE HIDROCARBONETOS CONTAMINANTES NO PROPENO POR CROMATOGRAFIA GASOSA | Z58: =IF(qBusca="","",IF(ISNUMBER(SEARCH(TRIM(qBusca),Y58)),ROW(),""))
A59: BRK-INS-01-011784-PT | B59: 7.0 | C59: IT 5020-01334 | D59: DETERMINAÇÃO DA PRESSÃO DE VAPOR EM PRODUTOS DE PETRÓLEO | E59: Aprovado | F59: 46886 | G59: Q4 | H59: UNIFICADA | I59: FATIMA MOURA GUTERRES | J59: ASTM D5191 - STANDARD TEST METHOD FOR VAPOR PRESSURE OF PETROLEUM PRODUCTS (MINI METHOD); ASTM D6378 - STANDARD TEST METHOD FOR DETERMINATION OF VAPOR PRESSURE (VPX) OF PETROLEUM PRODUCTS, HYDROCARBONS, AND HYDROCARBON-OXYGENATE MIXTURES (TRIPLE EXPANSION METHOD); ASTM D4953 - STANDARD TEST METHOD FOR VAPOR PRESSURE OF GASOLINE AND GASOLINE-OXYGENATE BLENDS (DRY METHOD).; ASTM D323 - STANDARD TEST METHOD FOR SALTS IN CRUDE OIL (ELECTROMETRIC METHOD). | L59: NDocs Q4!57 | M59: 1 | N59: =IF(TRIM(SUBSTITUTE(E59,CHAR(160)," "))="Avaiação de uso","Avaliação de uso",IF(TRIM(SUBSTITUTE(E59,CHAR(160)," "))="Cancelada","Cancelado",TRIM(SUBSTITUTE(E59,CHAR(160)," ")))) -> Aprovado | O59: =IF(ISNUMBER(F59),F59,IFERROR(DATE(RIGHT(RIGHT(TRIM(F59),10),4),MID(RIGHT(TRIM(F59),10),4,2),LEFT(RIGHT(TRIM(F59),10),2)),"")) -> 46886 | P59: =PROPER(TRIM(SUBSTITUTE(I59,CHAR(160)," "))) -> Fatima Moura Guterres | Q59: =IF(O59="","",O59-DataRef) -> 585 | R59: =IF(OR(N59="Cancelado",N59="Fora de Uso"),"Inativo",IF(OR(N59="Revisão",N59="Em Elaboração"),"Em tratamento",IF(OR(N59<>"Aprovado",O59=""),"Validar cadastro",IF(O59<DataRef,"Ação imediata",IF(O59<=EDATE(DataRef,12),"Planejar revisão","Regular"))))) -> Regular | S59: =IF(R59="Inativo","Inativo",IF(O59="","Sem validade",IF(O59<DataRef,"Vencida",IF(O59<=DataRef+90,"Até 90 dias",IF(O59<=EDATE(DataRef,12),"91 dias a 12 meses","Após 12 meses"))))) -> Após 12 meses | T59: =IF(O59="","",DATE(YEAR(O59),MONTH(O59),1)) -> 46874 | U59: =IF(R59="Ação imediata",1,IF(N59="Não encontrado",2,IF(N59="Revisão",3,IF(N59="Em Elaboração",4,IF(S59="Até 90 dias",5,IF(R59="Validar cadastro",6,0)))))) -> 0 | V59: =CHOOSE(U59+1,IF(R59="Planejar revisão","Incluir no plano anual de revisão",IF(R59="Inativo","Sem ação","Monitorar")),"Revisar ou prorrogar validade","Confirmar status no NDocs","Acompanhar revisão","Concluir elaboração","Iniciar revisão (≤ 90 dias)","Validar aplicabilidade") -> Monitorar | W59: =(OR(fArea="Todas",ISNUMBER(SEARCH(fArea,G59))))*(OR(fStatus="Todos",N59=fStatus))*(OR(fSit="Todas",R59=fSit))*(OR(fResp="Todos",P59=fResp))*(OR(fHor="Todos",S59=fHor)) -> 1 | X59: =IF(AND(W59=1,U59>0),(7-U59)*100000+50000-IF(ISNUMBER(Q59),Q59,0)+ROW()/1000,0) -> 0 | Y59: =UPPER(A59&" "&TRIM(SUBSTITUTE(C59,CHAR(160)," "))&" "&TRIM(SUBSTITUTE(D59,CHAR(160)," "))) -> BRK-INS-01-011784-PT IT 5020-01334 DETERMINAÇÃO DA PRESSÃO DE VAPOR EM PRODUTOS DE PETRÓLEO | Z59: =IF(qBusca="","",IF(ISNUMBER(SEARCH(TRIM(qBusca),Y59)),ROW(),""))
A60: BRK-INS-01-011812-PT | B60: 6.0 | C60: IT 5020-01340 | D60: DETERMINAÇÃO DE OXIGÊNIO PPM MOL EM GASES | E60: Aprovado | F60: 47688 | G60: Q4 | H60: UNIFICADA | I60: Camila Moraes De Oliveira | L60: NDocs Q4!58 | M60: 1 | N60: =IF(TRIM(SUBSTITUTE(E60,CHAR(160)," "))="Avaiação de uso","Avaliação de uso",IF(TRIM(SUBSTITUTE(E60,CHAR(160)," "))="Cancelada","Cancelado",TRIM(SUBSTITUTE(E60,CHAR(160)," ")))) -> Aprovado | O60: =IF(ISNUMBER(F60),F60,IFERROR(DATE(RIGHT(RIGHT(TRIM(F60),10),4),MID(RIGHT(TRIM(F60),10),4,2),LEFT(RIGHT(TRIM(F60),10),2)),"")) -> 47688 | P60: =PROPER(TRIM(SUBSTITUTE(I60,CHAR(160)," "))) -> Camila Moraes De Oliveira | Q60: =IF(O60="","",O60-DataRef) -> 1387 | R60: =IF(OR(N60="Cancelado",N60="Fora de Uso"),"Inativo",IF(OR(N60="Revisão",N60="Em Elaboração"),"Em tratamento",IF(OR(N60<>"Aprovado",O60=""),"Validar cadastro",IF(O60<DataRef,"Ação imediata",IF(O60<=EDATE(DataRef,12),"Planejar revisão","Regular"))))) -> Regular | S60: =IF(R60="Inativo","Inativo",IF(O60="","Sem validade",IF(O60<DataRef,"Vencida",IF(O60<=DataRef+90,"Até 90 dias",IF(O60<=EDATE(DataRef,12),"91 dias a 12 meses","Após 12 meses"))))) -> Após 12 meses | T60: =IF(O60="","",DATE(YEAR(O60),MONTH(O60),1)) -> 47665 | U60: =IF(R60="Ação imediata",1,IF(N60="Não encontrado",2,IF(N60="Revisão",3,IF(N60="Em Elaboração",4,IF(S60="Até 90 dias",5,IF(R60="Validar cadastro",6,0)))))) -> 0 | V60: =CHOOSE(U60+1,IF(R60="Planejar revisão","Incluir no plano anual de revisão",IF(R60="Inativo","Sem ação","Monitorar")),"Revisar ou prorrogar validade","Confirmar status no NDocs","Acompanhar revisão","Concluir elaboração","Iniciar revisão (≤ 90 dias)","Validar aplicabilidade") -> Monitorar | W60: =(OR(fArea="Todas",ISNUMBER(SEARCH(fArea,G60))))*(OR(fStatus="Todos",N60=fStatus))*(OR(fSit="Todas",R60=fSit))*(OR(fResp="Todos",P60=fResp))*(OR(fHor="Todos",S60=fHor)) -> 1 | X60: =IF(AND(W60=1,U60>0),(7-U60)*100000+50000-IF(ISNUMBER(Q60),Q60,0)+ROW()/1000,0) -> 0 | Y60: =UPPER(A60&" "&TRIM(SUBSTITUTE(C60,CHAR(160)," "))&" "&TRIM(SUBSTITUTE(D60,CHAR(160)," "))) -> BRK-INS-01-011812-PT IT 5020-01340 DETERMINAÇÃO DE OXIGÊNIO PPM MOL EM GASES | Z60: =IF(qBusca="","",IF(ISNUMBER(SEARCH(TRIM(qBusca),Y60)),ROW(),"")) -> 60
A61: BRK-INS-01-011875-PT | B61: 8.0 | C61: IT 5020-01372 | D61: DESTILAÇÃO DE HC’S LÍQUIDOS - ASTM D86 | E61: Aprovado | F61: 47864 | G61: Q4 | H61: UNIFICADA | I61: FATIMA MOURA GUTERRES | J61: ASTM D86 - STANDARD TEST METHOD FOR DISTILLATION OF PETROLEUM PRODUCTS AND LIQUID FUELS AT ATMOSPHERIC PRESSURE | L61: NDocs Q4!59 | M61: 1 | N61: =IF(TRIM(SUBSTITUTE(E61,CHAR(160)," "))="Avaiação de uso","Avaliação de uso",IF(TRIM(SUBSTITUTE(E61,CHAR(160)," "))="Cancelada","Cancelado",TRIM(SUBSTITUTE(E61,CHAR(160)," ")))) -> Aprovado | O61: =IF(ISNUMBER(F61),F61,IFERROR(DATE(RIGHT(RIGHT(TRIM(F61),10),4),MID(RIGHT(TRIM(F61),10),4,2),LEFT(RIGHT(TRIM(F61),10),2)),"")) -> 47864 | P61: =PROPER(TRIM(SUBSTITUTE(I61,CHAR(160)," "))) -> Fatima Moura Guterres | Q61: =IF(O61="","",O61-DataRef) -> 1563 | R61: =IF(OR(N61="Cancelado",N61="Fora de Uso"),"Inativo",IF(OR(N61="Revisão",N61="Em Elaboração"),"Em tratamento",IF(OR(N61<>"Aprovado",O61=""),"Validar cadastro",IF(O61<DataRef,"Ação imediata",IF(O61<=EDATE(DataRef,12),"Planejar revisão","Regular"))))) -> Regular | S61: =IF(R61="Inativo","Inativo",IF(O61="","Sem validade",IF(O61<DataRef,"Vencida",IF(O61<=DataRef+90,"Até 90 dias",IF(O61<=EDATE(DataRef,12),"91 dias a 12 meses","Após 12 meses"))))) -> Após 12 meses | T61: =IF(O61="","",DATE(YEAR(O61),MONTH(O61),1)) -> 47849 | U61: =IF(R61="Ação imediata",1,IF(N61="Não encontrado",2,IF(N61="Revisão",3,IF(N61="Em Elaboração",4,IF(S61="Até 90 dias",5,IF(R61="Validar cadastro",6,0)))))) -> 0 | V61: =CHOOSE(U61+1,IF(R61="Planejar revisão","Incluir no plano anual de revisão",IF(R61="Inativo","Sem ação","Monitorar")),"Revisar ou prorrogar validade","Confirmar status no NDocs","Acompanhar revisão","Concluir elaboração","Iniciar revisão (≤ 90 dias)","Validar aplicabilidade") -> Monitorar | W61: =(OR(fArea="Todas",ISNUMBER(SEARCH(fArea,G61))))*(OR(fStatus="Todos",N61=fStatus))*(OR(fSit="Todas",R61=fSit))*(OR(fResp="Todos",P61=fResp))*(OR(fHor="Todos",S61=fHor)) -> 1 | X61: =IF(AND(W61=1,U61>0),(7-U61)*100000+50000-IF(ISNUMBER(Q61),Q61,0)+ROW()/1000,0) -> 0 | Y61: =UPPER(A61&" "&TRIM(SUBSTITUTE(C61,CHAR(160)," "))&" "&TRIM(SUBSTITUTE(D61,CHAR(160)," "))) -> BRK-INS-01-011875-PT IT 5020-01372 DESTILAÇÃO DE HC’S LÍQUIDOS - ASTM D86 | Z61: =IF(qBusca="","",IF(ISNUMBER(SEARCH(TRIM(qBusca),Y61)),ROW(),""))
A62: BRK-INS-01-011948-PT | B62: 8.0 | C62: IT 5020-01396 | D62: DETERMINAÇÃO DE POLÍMEROS EM SOLUÇÕES CÁUSTICAS | E62: Aprovado | F62: 47791 | G62: Q4 | H62: UNIFICADA | I62: FATIMA MOURA GUTERRES | L62: NDocs Q4!60 | M62: 1 | N62: =IF(TRIM(SUBSTITUTE(E62,CHAR(160)," "))="Avaiação de uso","Avaliação de uso",IF(TRIM(SUBSTITUTE(E62,CHAR(160)," "))="Cancelada","Cancelado",TRIM(SUBSTITUTE(E62,CHAR(160)," ")))) -> Aprovado | O62: =IF(ISNUMBER(F62),F62,IFERROR(DATE(RIGHT(RIGHT(TRIM(F62),10),4),MID(RIGHT(TRIM(F62),10),4,2),LEFT(RIGHT(TRIM(F62),10),2)),"")) -> 47791 | P62: =PROPER(TRIM(SUBSTITUTE(I62,CHAR(160)," "))) -> Fatima Moura Guterres | Q62: =IF(O62="","",O62-DataRef) -> 1490 | R62: =IF(OR(N62="Cancelado",N62="Fora de Uso"),"Inativo",IF(OR(N62="Revisão",N62="Em Elaboração"),"Em tratamento",IF(OR(N62<>"Aprovado",O62=""),"Validar cadastro",IF(O62<DataRef,"Ação imediata",IF(O62<=EDATE(DataRef,12),"Planejar revisão","Regular"))))) -> Regular | S62: =IF(R62="Inativo","Inativo",IF(O62="","Sem validade",IF(O62<DataRef,"Vencida",IF(O62<=DataRef+90,"Até 90 dias",IF(O62<=EDATE(DataRef,12),"91 dias a 12 meses","Após 12 meses"))))) -> Após 12 meses | T62: =IF(O62="","",DATE(YEAR(O62),MONTH(O62),1)) -> 47788 | U62: =IF(R62="Ação imediata",1,IF(N62="Não encontrado",2,IF(N62="Revisão",3,IF(N62="Em Elaboração",4,IF(S62="Até 90 dias",5,IF(R62="Validar cadastro",6,0)))))) -> 0 | V62: =CHOOSE(U62+1,IF(R62="Planejar revisão","Incluir no plano anual de revisão",IF(R62="Inativo","Sem ação","Monitorar")),"Revisar ou prorrogar validade","Confirmar status no NDocs","Acompanhar revisão","Concluir elaboração","Iniciar revisão (≤ 90 dias)","Validar aplicabilidade") -> Monitorar | W62: =(OR(fArea="Todas",ISNUMBER(SEARCH(fArea,G62))))*(OR(fStatus="Todos",N62=fStatus))*(OR(fSit="Todas",R62=fSit))*(OR(fResp="Todos",P62=fResp))*(OR(fHor="Todos",S62=fHor)) -> 1 | X62: =IF(AND(W62=1,U62>0),(7-U62)*100000+50000-IF(ISNUMBER(Q62),Q62,0)+ROW()/1000,0) -> 0 | Y62: =UPPER(A62&" "&TRIM(SUBSTITUTE(C62,CHAR(160)," "))&" "&TRIM(SUBSTITUTE(D62,CHAR(160)," "))) -> BRK-INS-01-011948-PT IT 5020-01396 DETERMINAÇÃO DE POLÍMEROS EM SOLUÇÕES CÁUSTICAS | Z62: =IF(qBusca="","",IF(ISNUMBER(SEARCH(TRIM(qBusca),Y62)),ROW(),""))
A63: BRK-INS-01-013884-PT | B63: 5.0 | C63: IT 5020-01991 | D63: HIDROCARBONETOS LÍQUIDOS, LIQUEFEITOS E GASOSOS: DETERMINAÇÃO DE TRAÇOS DE NITROGENIO TOTAL POR COMBUSTÃO OXIDANTE E DETECÇÃO POR QUIMILUMINESCÊNCIA | E63: Aprovado | F63: 46676 | G63: Q4 | H63: UNIFICADA | I63: FATIMA MOURA GUTERRES | J63: ASTM D4629 | L63: NDocs Q4!61 | M63: 1 | N63: =IF(TRIM(SUBSTITUTE(E63,CHAR(160)," "))="Avaiação de uso","Avaliação de uso",IF(TRIM(SUBSTITUTE(E63,CHAR(160)," "))="Cancelada","Cancelado",TRIM(SUBSTITUTE(E63,CHAR(160)," ")))) -> Aprovado | O63: =IF(ISNUMBER(F63),F63,IFERROR(DATE(RIGHT(RIGHT(TRIM(F63),10),4),MID(RIGHT(TRIM(F63),10),4,2),LEFT(RIGHT(TRIM(F63),10),2)),"")) -> 46676 | P63: =PROPER(TRIM(SUBSTITUTE(I63,CHAR(160)," "))) -> Fatima Moura Guterres | Q63: =IF(O63="","",O63-DataRef) -> 375 | R63: =IF(OR(N63="Cancelado",N63="Fora de Uso"),"Inativo",IF(OR(N63="Revisão",N63="Em Elaboração"),"Em tratamento",IF(OR(N63<>"Aprovado",O63=""),"Validar cadastro",IF(O63<DataRef,"Ação imediata",IF(O63<=EDATE(DataRef,12),"Planejar revisão","Regular"))))) -> Regular | S63: =IF(R63="Inativo","Inativo",IF(O63="","Sem validade",IF(O63<DataRef,"Vencida",IF(O63<=DataRef+90,"Até 90 dias",IF(O63<=EDATE(DataRef,12),"91 dias a 12 meses","Após 12 meses"))))) -> Após 12 meses | T63: =IF(O63="","",DATE(YEAR(O63),MONTH(O63),1)) -> 46661 | U63: =IF(R63="Ação imediata",1,IF(N63="Não encontrado",2,IF(N63="Revisão",3,IF(N63="Em Elaboração",4,IF(S63="Até 90 dias",5,IF(R63="Validar cadastro",6,0)))))) -> 0 | V63: =CHOOSE(U63+1,IF(R63="Planejar revisão","Incluir no plano anual de revisão",IF(R63="Inativo","Sem ação","Monitorar")),"Revisar ou prorrogar validade","Confirmar status no NDocs","Acompanhar revisão","Concluir elaboração","Iniciar revisão (≤ 90 dias)","Validar aplicabilidade") -> Monitorar | W63: =(OR(fArea="Todas",ISNUMBER(SEARCH(fArea,G63))))*(OR(fStatus="Todos",N63=fStatus))*(OR(fSit="Todas",R63=fSit))*(OR(fResp="Todos",P63=fResp))*(OR(fHor="Todos",S63=fHor)) -> 1 | X63: =IF(AND(W63=1,U63>0),(7-U63)*100000+50000-IF(ISNUMBER(Q63),Q63,0)+ROW()/1000,0) -> 0 | Y63: =UPPER(A63&" "&TRIM(SUBSTITUTE(C63,CHAR(160)," "))&" "&TRIM(SUBSTITUTE(D63,CHAR(160)," "))) -> BRK-INS-01-013884-PT IT 5020-01991 HIDROCARBONETOS LÍQUIDOS, LIQUEFEITOS E GASOSOS: DETERMINAÇÃO DE TRAÇOS DE NITROGENIO TOTAL POR COMBUSTÃO OXIDANTE E DETECÇÃO POR QUIMILUMINESCÊNCIA | Z63: =IF(qBusca="","",IF(ISNUMBER(SEARCH(TRIM(qBusca),Y63)),ROW(),""))
A64: BRK-INS-01-014293-PT | B64: 7.0 | C64: IT 5020-02155 | D64: ANÁLISE DE ÁGUA POR KARL-FISCHER | E64: Aprovado | F64: 46649 | G64: Q4 | H64: UNIFICADA | I64: FATIMA MOURA GUTERRES | J64: NOR ASTM E203 2008 Ex.1; ASTM D1744 - STANDARD TEST METHOD FOR DETERMINATION OF WATER IN LIQUID PETROLEUM PRODUCTS | L64: NDocs Q4!62 | M64: 1 | N64: =IF(TRIM(SUBSTITUTE(E64,CHAR(160)," "))="Avaiação de uso","Avaliação de uso",IF(TRIM(SUBSTITUTE(E64,CHAR(160)," "))="Cancelada","Cancelado",TRIM(SUBSTITUTE(E64,CHAR(160)," ")))) -> Aprovado | O64: =IF(ISNUMBER(F64),F64,IFERROR(DATE(RIGHT(RIGHT(TRIM(F64),10),4),MID(RIGHT(TRIM(F64),10),4,2),LEFT(RIGHT(TRIM(F64),10),2)),"")) -> 46649 | P64: =PROPER(TRIM(SUBSTITUTE(I64,CHAR(160)," "))) -> Fatima Moura Guterres | Q64: =IF(O64="","",O64-DataRef) -> 348 | R64: =IF(OR(N64="Cancelado",N64="Fora de Uso"),"Inativo",IF(OR(N64="Revisão",N64="Em Elaboração"),"Em tratamento",IF(OR(N64<>"Aprovado",O64=""),"Validar cadastro",IF(O64<DataRef,"Ação imediata",IF(O64<=EDATE(DataRef,12),"Planejar revisão","Regular"))))) -> Planejar revisão | S64: =IF(R64="Inativo","Inativo",IF(O64="","Sem validade",IF(O64<DataRef,"Vencida",IF(O64<=DataRef+90,"Até 90 dias",IF(O64<=EDATE(DataRef,12),"91 dias a 12 meses","Após 12 meses"))))) -> 91 dias a 12 meses | T64: =IF(O64="","",DATE(YEAR(O64),MONTH(O64),1)) -> 46631 | U64: =IF(R64="Ação imediata",1,IF(N64="Não encontrado",2,IF(N64="Revisão",3,IF(N64="Em Elaboração",4,IF(S64="Até 90 dias",5,IF(R64="Validar cadastro",6,0)))))) -> 0 | V64: =CHOOSE(U64+1,IF(R64="Planejar revisão","Incluir no plano anual de revisão",IF(R64="Inativo","Sem ação","Monitorar")),"Revisar ou prorrogar validade","Confirmar status no NDocs","Acompanhar revisão","Concluir elaboração","Iniciar revisão (≤ 90 dias)","Validar aplicabilidade") -> Incluir no plano anual de revisão | W64: =(OR(fArea="Todas",ISNUMBER(SEARCH(fArea,G64))))*(OR(fStatus="Todos",N64=fStatus))*(OR(fSit="Todas",R64=fSit))*(OR(fResp="Todos",P64=fResp))*(OR(fHor="Todos",S64=fHor)) -> 1 | X64: =IF(AND(W64=1,U64>0),(7-U64)*100000+50000-IF(ISNUMBER(Q64),Q64,0)+ROW()/1000,0) -> 0 | Y64: =UPPER(A64&" "&TRIM(SUBSTITUTE(C64,CHAR(160)," "))&" "&TRIM(SUBSTITUTE(D64,CHAR(160)," "))) -> BRK-INS-01-014293-PT IT 5020-02155 ANÁLISE DE ÁGUA POR KARL-FISCHER | Z64: =IF(qBusca="","",IF(ISNUMBER(SEARCH(TRIM(qBusca),Y64)),ROW(),""))
A65: BRK-INS-01-014989-PT | B65: 6.0 | C65: IT 5020-02404 | D65: DETERMINAÇÃO DE UMIDADE EM HIDROCARBONETOS GASOSOS | E65: Aprovado | F65: 48106 | G65: Q4 | H65: UNIFICADA | I65: Cintia Bernardo De Vargas | L65: NDocs Q4!63 | M65: 1 | N65: =IF(TRIM(SUBSTITUTE(E65,CHAR(160)," "))="Avaiação de uso","Avaliação de uso",IF(TRIM(SUBSTITUTE(E65,CHAR(160)," "))="Cancelada","Cancelado",TRIM(SUBSTITUTE(E65,CHAR(160)," ")))) -> Aprovado | O65: =IF(ISNUMBER(F65),F65,IFERROR(DATE(RIGHT(RIGHT(TRIM(F65),10),4),MID(RIGHT(TRIM(F65),10),4,2),LEFT(RIGHT(TRIM(F65),10),2)),"")) -> 48106 | P65: =PROPER(TRIM(SUBSTITUTE(I65,CHAR(160)," "))) -> Cintia Bernardo De Vargas | Q65: =IF(O65="","",O65-DataRef) -> 1805 | R65: =IF(OR(N65="Cancelado",N65="Fora de Uso"),"Inativo",IF(OR(N65="Revisão",N65="Em Elaboração"),"Em tratamento",IF(OR(N65<>"Aprovado",O65=""),"Validar cadastro",IF(O65<DataRef,"Ação imediata",IF(O65<=EDATE(DataRef,12),"Planejar revisão","Regular"))))) -> Regular | S65: =IF(R65="Inativo","Inativo",IF(O65="","Sem validade",IF(O65<DataRef,"Vencida",IF(O65<=DataRef+90,"Até 90 dias",IF(O65<=EDATE(DataRef,12),"91 dias a 12 meses","Após 12 meses"))))) -> Após 12 meses | T65: =IF(O65="","",DATE(YEAR(O65),MONTH(O65),1)) -> 48092 | U65: =IF(R65="Ação imediata",1,IF(N65="Não encontrado",2,IF(N65="Revisão",3,IF(N65="Em Elaboração",4,IF(S65="Até 90 dias",5,IF(R65="Validar cadastro",6,0)))))) -> 0 | V65: =CHOOSE(U65+1,IF(R65="Planejar revisão","Incluir no plano anual de revisão",IF(R65="Inativo","Sem ação","Monitorar")),"Revisar ou prorrogar validade","Confirmar status no NDocs","Acompanhar revisão","Concluir elaboração","Iniciar revisão (≤ 90 dias)","Validar aplicabilidade") -> Monitorar | W65: =(OR(fArea="Todas",ISNUMBER(SEARCH(fArea,G65))))*(OR(fStatus="Todos",N65=fStatus))*(OR(fSit="Todas",R65=fSit))*(OR(fResp="Todos",P65=fResp))*(OR(fHor="Todos",S65=fHor)) -> 1 | X65: =IF(AND(W65=1,U65>0),(7-U65)*100000+50000-IF(ISNUMBER(Q65),Q65,0)+ROW()/1000,0) -> 0 | Y65: =UPPER(A65&" "&TRIM(SUBSTITUTE(C65,CHAR(160)," "))&" "&TRIM(SUBSTITUTE(D65,CHAR(160)," "))) -> BRK-INS-01-014989-PT IT 5020-02404 DETERMINAÇÃO DE UMIDADE EM HIDROCARBONETOS GASOSOS | Z65: =IF(qBusca="","",IF(ISNUMBER(SEARCH(TRIM(qBusca),Y65)),ROW(),""))
A66: BRK-INS-01-010058-PT | B66: 6.0 | C66: IT 5020-00227 | D66: EXTRAÍVEIS EM POLIETILENO POR RMN | E66: Aprovado | F66: 46907 | G66: PE | I66: Ana CARLA DA CRUZ ARAUJO | L66: NDocs PE_PP!3 | M66: 1 | N66: =IF(TRIM(SUBSTITUTE(E66,CHAR(160)," "))="Avaiação de uso","Avaliação de uso",IF(TRIM(SUBSTITUTE(E66,CHAR(160)," "))="Cancelada","Cancelado",TRIM(SUBSTITUTE(E66,CHAR(160)," ")))) -> Aprovado | O66: =IF(ISNUMBER(F66),F66,IFERROR(DATE(RIGHT(RIGHT(TRIM(F66),10),4),MID(RIGHT(TRIM(F66),10),4,2),LEFT(RIGHT(TRIM(F66),10),2)),"")) -> 46907 | P66: =PROPER(TRIM(SUBSTITUTE(I66,CHAR(160)," "))) -> Ana Carla Da Cruz Araujo | Q66: =IF(O66="","",O66-DataRef) -> 606 | R66: =IF(OR(N66="Cancelado",N66="Fora de Uso"),"Inativo",IF(OR(N66="Revisão",N66="Em Elaboração"),"Em tratamento",IF(OR(N66<>"Aprovado",O66=""),"Validar cadastro",IF(O66<DataRef,"Ação imediata",IF(O66<=EDATE(DataRef,12),"Planejar revisão","Regular"))))) -> Regular | S66: =IF(R66="Inativo","Inativo",IF(O66="","Sem validade",IF(O66<DataRef,"Vencida",IF(O66<=DataRef+90,"Até 90 dias",IF(O66<=EDATE(DataRef,12),"91 dias a 12 meses","Após 12 meses"))))) -> Após 12 meses | T66: =IF(O66="","",DATE(YEAR(O66),MONTH(O66),1)) -> 46905 | U66: =IF(R66="Ação imediata",1,IF(N66="Não encontrado",2,IF(N66="Revisão",3,IF(N66="Em Elaboração",4,IF(S66="Até 90 dias",5,IF(R66="Validar cadastro",6,0)))))) -> 0 | V66: =CHOOSE(U66+1,IF(R66="Planejar revisão","Incluir no plano anual de revisão",IF(R66="Inativo","Sem ação","Monitorar")),"Revisar ou prorrogar validade","Confirmar status no NDocs","Acompanhar revisão","Concluir elaboração","Iniciar revisão (≤ 90 dias)","Validar aplicabilidade") -> Monitorar | W66: =(OR(fArea="Todas",ISNUMBER(SEARCH(fArea,G66))))*(OR(fStatus="Todos",N66=fStatus))*(OR(fSit="Todas",R66=fSit))*(OR(fResp="Todos",P66=fResp))*(OR(fHor="Todos",S66=fHor)) -> 1 | X66: =IF(AND(W66=1,U66>0),(7-U66)*100000+50000-IF(ISNUMBER(Q66),Q66,0)+ROW()/1000,0) -> 0 | Y66: =UPPER(A66&" "&TRIM(SUBSTITUTE(C66,CHAR(160)," "))&" "&TRIM(SUBSTITUTE(D66,CHAR(160)," "))) -> BRK-INS-01-010058-PT IT 5020-00227 EXTRAÍVEIS EM POLIETILENO POR RMN | Z66: =IF(qBusca="","",IF(ISNUMBER(SEARCH(TRIM(qBusca),Y66)),ROW(),""))
A67: BRK-INS-01-012382-PT | B67: 5.0 | C67: IT 5020-01543 | D67: DETERMINAÇÃO DA DENSIDADE APARENTE EM PÓ OU GRÃOS DE POLIETILENO E POLIPROPILENO | E67: Aprovado | F67: 47987 | G67: PE/PP | I67: LARISSA VICENTE CARDOSO GUEDES | L67: NDocs PE_PP!4 | M67: 1 | N67: =IF(TRIM(SUBSTITUTE(E67,CHAR(160)," "))="Avaiação de uso","Avaliação de uso",IF(TRIM(SUBSTITUTE(E67,CHAR(160)," "))="Cancelada","Cancelado",TRIM(SUBSTITUTE(E67,CHAR(160)," ")))) -> Aprovado | O67: =IF(ISNUMBER(F67),F67,IFERROR(DATE(RIGHT(RIGHT(TRIM(F67),10),4),MID(RIGHT(TRIM(F67),10),4,2),LEFT(RIGHT(TRIM(F67),10),2)),"")) -> 47987 | P67: =PROPER(TRIM(SUBSTITUTE(I67,CHAR(160)," "))) -> Larissa Vicente Cardoso Guedes | Q67: =IF(O67="","",O67-DataRef) -> 1686 | R67: =IF(OR(N67="Cancelado",N67="Fora de Uso"),"Inativo",IF(OR(N67="Revisão",N67="Em Elaboração"),"Em tratamento",IF(OR(N67<>"Aprovado",O67=""),"Validar cadastro",IF(O67<DataRef,"Ação imediata",IF(O67<=EDATE(DataRef,12),"Planejar revisão","Regular"))))) -> Regular | S67: =IF(R67="Inativo","Inativo",IF(O67="","Sem validade",IF(O67<DataRef,"Vencida",IF(O67<=DataRef+90,"Até 90 dias",IF(O67<=EDATE(DataRef,12),"91 dias a 12 meses","Após 12 meses"))))) -> Após 12 meses | T67: =IF(O67="","",DATE(YEAR(O67),MONTH(O67),1)) -> 47969 | U67: =IF(R67="Ação imediata",1,IF(N67="Não encontrado",2,IF(N67="Revisão",3,IF(N67="Em Elaboração",4,IF(S67="Até 90 dias",5,IF(R67="Validar cadastro",6,0)))))) -> 0 | V67: =CHOOSE(U67+1,IF(R67="Planejar revisão","Incluir no plano anual de revisão",IF(R67="Inativo","Sem ação","Monitorar")),"Revisar ou prorrogar validade","Confirmar status no NDocs","Acompanhar revisão","Concluir elaboração","Iniciar revisão (≤ 90 dias)","Validar aplicabilidade") -> Monitorar | W67: =(OR(fArea="Todas",ISNUMBER(SEARCH(fArea,G67))))*(OR(fStatus="Todos",N67=fStatus))*(OR(fSit="Todas",R67=fSit))*(OR(fResp="Todos",P67=fResp))*(OR(fHor="Todos",S67=fHor)) -> 1 | X67: =IF(AND(W67=1,U67>0),(7-U67)*100000+50000-IF(ISNUMBER(Q67),Q67,0)+ROW()/1000,0) -> 0 | Y67: =UPPER(A67&" "&TRIM(SUBSTITUTE(C67,CHAR(160)," "))&" "&TRIM(SUBSTITUTE(D67,CHAR(160)," "))) -> BRK-INS-01-012382-PT IT 5020-01543 DETERMINAÇÃO DA DENSIDADE APARENTE EM PÓ OU GRÃOS DE POLIETILENO E POLIPROPILENO | Z67: =IF(qBusca="","",IF(ISNUMBER(SEARCH(TRIM(qBusca),Y67)),ROW(),""))
A68: BRK-INS-01-013366-PT | B68: 5.0 | C68: IT 5020-01820 | D68: DETERMINAÇÃO DA GRANULOMETRIA EM PÓ DE POLIPROPILENO | E68: Aprovado | F68: 48106 | G68: PP | I68: LARISSA VICENTE CARDOSO GUEDES | L68: NDocs PE_PP!5 | M68: 1 | N68: =IF(TRIM(SUBSTITUTE(E68,CHAR(160)," "))="Avaiação de uso","Avaliação de uso",IF(TRIM(SUBSTITUTE(E68,CHAR(160)," "))="Cancelada","Cancelado",TRIM(SUBSTITUTE(E68,CHAR(160)," ")))) -> Aprovado | O68: =IF(ISNUMBER(F68),F68,IFERROR(DATE(RIGHT(RIGHT(TRIM(F68),10),4),MID(RIGHT(TRIM(F68),10),4,2),LEFT(RIGHT(TRIM(F68),10),2)),"")) -> 48106 | P68: =PROPER(TRIM(SUBSTITUTE(I68,CHAR(160)," "))) -> Larissa Vicente Cardoso Guedes | Q68: =IF(O68="","",O68-DataRef) -> 1805 | R68: =IF(OR(N68="Cancelado",N68="Fora de Uso"),"Inativo",IF(OR(N68="Revisão",N68="Em Elaboração"),"Em tratamento",IF(OR(N68<>"Aprovado",O68=""),"Validar cadastro",IF(O68<DataRef,"Ação imediata",IF(O68<=EDATE(DataRef,12),"Planejar revisão","Regular"))))) -> Regular | S68: =IF(R68="Inativo","Inativo",IF(O68="","Sem validade",IF(O68<DataRef,"Vencida",IF(O68<=DataRef+90,"Até 90 dias",IF(O68<=EDATE(DataRef,12),"91 dias a 12 meses","Após 12 meses"))))) -> Após 12 meses | T68: =IF(O68="","",DATE(YEAR(O68),MONTH(O68),1)) -> 48092 | U68: =IF(R68="Ação imediata",1,IF(N68="Não encontrado",2,IF(N68="Revisão",3,IF(N68="Em Elaboração",4,IF(S68="Até 90 dias",5,IF(R68="Validar cadastro",6,0)))))) -> 0 | V68: =CHOOSE(U68+1,IF(R68="Planejar revisão","Incluir no plano anual de revisão",IF(R68="Inativo","Sem ação","Monitorar")),"Revisar ou prorrogar validade","Confirmar status no NDocs","Acompanhar revisão","Concluir elaboração","Iniciar revisão (≤ 90 dias)","Validar aplicabilidade") -> Monitorar | W68: =(OR(fArea="Todas",ISNUMBER(SEARCH(fArea,G68))))*(OR(fStatus="Todos",N68=fStatus))*(OR(fSit="Todas",R68=fSit))*(OR(fResp="Todos",P68=fResp))*(OR(fHor="Todos",S68=fHor)) -> 1 | X68: =IF(AND(W68=1,U68>0),(7-U68)*100000+50000-IF(ISNUMBER(Q68),Q68,0)+ROW()/1000,0) -> 0 | Y68: =UPPER(A68&" "&TRIM(SUBSTITUTE(C68,CHAR(160)," "))&" "&TRIM(SUBSTITUTE(D68,CHAR(160)," "))) -> BRK-INS-01-013366-PT IT 5020-01820 DETERMINAÇÃO DA GRANULOMETRIA EM PÓ DE POLIPROPILENO | Z68: =IF(qBusca="","",IF(ISNUMBER(SEARCH(TRIM(qBusca),Y68)),ROW(),""))
A69: BRK-INS-01-016106-PT | B69: 6.0 | C69: IT 5020-00146 | D69: PREPARAÇÃO DE PLACAS POR MOLDAGEM EM PRENSA | E69: Aprovado | F69: 46907 | G69: PE/PP | I69: Ana CARLA DA CRUZ ARAUJO | J69: ASTM D4703 - Standard Practice for Compression Molding Thermoplastic Materials into Test Specimens, Plaques, or Sheets | L69: NDocs PE_PP!6 | M69: 1 | N69: =IF(TRIM(SUBSTITUTE(E69,CHAR(160)," "))="Avaiação de uso","Avaliação de uso",IF(TRIM(SUBSTITUTE(E69,CHAR(160)," "))="Cancelada","Cancelado",TRIM(SUBSTITUTE(E69,CHAR(160)," ")))) -> Aprovado | O69: =IF(ISNUMBER(F69),F69,IFERROR(DATE(RIGHT(RIGHT(TRIM(F69),10),4),MID(RIGHT(TRIM(F69),10),4,2),LEFT(RIGHT(TRIM(F69),10),2)),"")) -> 46907 | P69: =PROPER(TRIM(SUBSTITUTE(I69,CHAR(160)," "))) -> Ana Carla Da Cruz Araujo | Q69: =IF(O69="","",O69-DataRef) -> 606 | R69: =IF(OR(N69="Cancelado",N69="Fora de Uso"),"Inativo",IF(OR(N69="Revisão",N69="Em Elaboração"),"Em tratamento",IF(OR(N69<>"Aprovado",O69=""),"Validar cadastro",IF(O69<DataRef,"Ação imediata",IF(O69<=EDATE(DataRef,12),"Planejar revisão","Regular"))))) -> Regular | S69: =IF(R69="Inativo","Inativo",IF(O69="","Sem validade",IF(O69<DataRef,"Vencida",IF(O69<=DataRef+90,"Até 90 dias",IF(O69<=EDATE(DataRef,12),"91 dias a 12 meses","Após 12 meses"))))) -> Após 12 meses | T69: =IF(O69="","",DATE(YEAR(O69),MONTH(O69),1)) -> 46905 | U69: =IF(R69="Ação imediata",1,IF(N69="Não encontrado",2,IF(N69="Revisão",3,IF(N69="Em Elaboração",4,IF(S69="Até 90 dias",5,IF(R69="Validar cadastro",6,0)))))) -> 0 | V69: =CHOOSE(U69+1,IF(R69="Planejar revisão","Incluir no plano anual de revisão",IF(R69="Inativo","Sem ação","Monitorar")),"Revisar ou prorrogar validade","Confirmar status no NDocs","Acompanhar revisão","Concluir elaboração","Iniciar revisão (≤ 90 dias)","Validar aplicabilidade") -> Monitorar | W69: =(OR(fArea="Todas",ISNUMBER(SEARCH(fArea,G69))))*(OR(fStatus="Todos",N69=fStatus))*(OR(fSit="Todas",R69=fSit))*(OR(fResp="Todos",P69=fResp))*(OR(fHor="Todos",S69=fHor)) -> 1 | X69: =IF(AND(W69=1,U69>0),(7-U69)*100000+50000-IF(ISNUMBER(Q69),Q69,0)+ROW()/1000,0) -> 0 | Y69: =UPPER(A69&" "&TRIM(SUBSTITUTE(C69,CHAR(160)," "))&" "&TRIM(SUBSTITUTE(D69,CHAR(160)," "))) -> BRK-INS-01-016106-PT IT 5020-00146 PREPARAÇÃO DE PLACAS POR MOLDAGEM EM PRENSA | Z69: =IF(qBusca="","",IF(ISNUMBER(SEARCH(TRIM(qBusca),Y69)),ROW(),""))
A70: BRK-INS-01-016114-PT | B70: 6.0 | C70: IT 5020-00148 | D70: DETERMINAÇÃO DA DENSIDADE POR EMPUXO NO POLIETILENO | E70: Aprovado | F70: 47987 | G70: PE | I70: Ana CARLA DA CRUZ ARAUJO | J70: ASTM D792 - STANDARD SPECIFICATION FOR POLYETHYLENE PLASTICS PIPE AND FITTINGS MATERIALS | L70: NDocs PE_PP!7 | M70: 1 | N70: =IF(TRIM(SUBSTITUTE(E70,CHAR(160)," "))="Avaiação de uso","Avaliação de uso",IF(TRIM(SUBSTITUTE(E70,CHAR(160)," "))="Cancelada","Cancelado",TRIM(SUBSTITUTE(E70,CHAR(160)," ")))) -> Aprovado | O70: =IF(ISNUMBER(F70),F70,IFERROR(DATE(RIGHT(RIGHT(TRIM(F70),10),4),MID(RIGHT(TRIM(F70),10),4,2),LEFT(RIGHT(TRIM(F70),10),2)),"")) -> 47987 | P70: =PROPER(TRIM(SUBSTITUTE(I70,CHAR(160)," "))) -> Ana Carla Da Cruz Araujo | Q70: =IF(O70="","",O70-DataRef) -> 1686 | R70: =IF(OR(N70="Cancelado",N70="Fora de Uso"),"Inativo",IF(OR(N70="Revisão",N70="Em Elaboração"),"Em tratamento",IF(OR(N70<>"Aprovado",O70=""),"Validar cadastro",IF(O70<DataRef,"Ação imediata",IF(O70<=EDATE(DataRef,12),"Planejar revisão","Regular"))))) -> Regular | S70: =IF(R70="Inativo","Inativo",IF(O70="","Sem validade",IF(O70<DataRef,"Vencida",IF(O70<=DataRef+90,"Até 90 dias",IF(O70<=EDATE(DataRef,12),"91 dias a 12 meses","Após 12 meses"))))) -> Após 12 meses | T70: =IF(O70="","",DATE(YEAR(O70),MONTH(O70),1)) -> 47969 | U70: =IF(R70="Ação imediata",1,IF(N70="Não encontrado",2,IF(N70="Revisão",3,IF(N70="Em Elaboração",4,IF(S70="Até 90 dias",5,IF(R70="Validar cadastro",6,0)))))) -> 0 | V70: =CHOOSE(U70+1,IF(R70="Planejar revisão","Incluir no plano anual de revisão",IF(R70="Inativo","Sem ação","Monitorar")),"Revisar ou prorrogar validade","Confirmar status no NDocs","Acompanhar revisão","Concluir elaboração","Iniciar revisão (≤ 90 dias)","Validar aplicabilidade") -> Monitorar | W70: =(OR(fArea="Todas",ISNUMBER(SEARCH(fArea,G70))))*(OR(fStatus="Todos",N70=fStatus))*(OR(fSit="Todas",R70=fSit))*(OR(fResp="Todos",P70=fResp))*(OR(fHor="Todos",S70=fHor)) -> 1 | X70: =IF(AND(W70=1,U70>0),(7-U70)*100000+50000-IF(ISNUMBER(Q70),Q70,0)+ROW()/1000,0) -> 0 | Y70: =UPPER(A70&" "&TRIM(SUBSTITUTE(C70,CHAR(160)," "))&" "&TRIM(SUBSTITUTE(D70,CHAR(160)," "))) -> BRK-INS-01-016114-PT IT 5020-00148 DETERMINAÇÃO DA DENSIDADE POR EMPUXO NO POLIETILENO | Z70: =IF(qBusca="","",IF(ISNUMBER(SEARCH(TRIM(qBusca),Y70)),ROW(),""))
A71: BRK-INS-01-016121-PT | B71: 6.0 | C71: IT 5020-00150 | D71: AVALIAÇÃO DE FILME EM RESINA DE POLIETILENO | E71: Aprovado | F71: 46846 | G71: PE | I71: Ana CARLA DA CRUZ ARAUJO | L71: NDocs PE_PP!8 | M71: 1 | N71: =IF(TRIM(SUBSTITUTE(E71,CHAR(160)," "))="Avaiação de uso","Avaliação de uso",IF(TRIM(SUBSTITUTE(E71,CHAR(160)," "))="Cancelada","Cancelado",TRIM(SUBSTITUTE(E71,CHAR(160)," ")))) -> Aprovado | O71: =IF(ISNUMBER(F71),F71,IFERROR(DATE(RIGHT(RIGHT(TRIM(F71),10),4),MID(RIGHT(TRIM(F71),10),4,2),LEFT(RIGHT(TRIM(F71),10),2)),"")) -> 46846 | P71: =PROPER(TRIM(SUBSTITUTE(I71,CHAR(160)," "))) -> Ana Carla Da Cruz Araujo | Q71: =IF(O71="","",O71-DataRef) -> 545 | R71: =IF(OR(N71="Cancelado",N71="Fora de Uso"),"Inativo",IF(OR(N71="Revisão",N71="Em Elaboração"),"Em tratamento",IF(OR(N71<>"Aprovado",O71=""),"Validar cadastro",IF(O71<DataRef,"Ação imediata",IF(O71<=EDATE(DataRef,12),"Planejar revisão","Regular"))))) -> Regular | S71: =IF(R71="Inativo","Inativo",IF(O71="","Sem validade",IF(O71<DataRef,"Vencida",IF(O71<=DataRef+90,"Até 90 dias",IF(O71<=EDATE(DataRef,12),"91 dias a 12 meses","Após 12 meses"))))) -> Após 12 meses | T71: =IF(O71="","",DATE(YEAR(O71),MONTH(O71),1)) -> 46844 | U71: =IF(R71="Ação imediata",1,IF(N71="Não encontrado",2,IF(N71="Revisão",3,IF(N71="Em Elaboração",4,IF(S71="Até 90 dias",5,IF(R71="Validar cadastro",6,0)))))) -> 0 | V71: =CHOOSE(U71+1,IF(R71="Planejar revisão","Incluir no plano anual de revisão",IF(R71="Inativo","Sem ação","Monitorar")),"Revisar ou prorrogar validade","Confirmar status no NDocs","Acompanhar revisão","Concluir elaboração","Iniciar revisão (≤ 90 dias)","Validar aplicabilidade") -> Monitorar | W71: =(OR(fArea="Todas",ISNUMBER(SEARCH(fArea,G71))))*(OR(fStatus="Todos",N71=fStatus))*(OR(fSit="Todas",R71=fSit))*(OR(fResp="Todos",P71=fResp))*(OR(fHor="Todos",S71=fHor)) -> 1 | X71: =IF(AND(W71=1,U71>0),(7-U71)*100000+50000-IF(ISNUMBER(Q71),Q71,0)+ROW()/1000,0) -> 0 | Y71: =UPPER(A71&" "&TRIM(SUBSTITUTE(C71,CHAR(160)," "))&" "&TRIM(SUBSTITUTE(D71,CHAR(160)," "))) -> BRK-INS-01-016121-PT IT 5020-00150 AVALIAÇÃO DE FILME EM RESINA DE POLIETILENO | Z71: =IF(qBusca="","",IF(ISNUMBER(SEARCH(TRIM(qBusca),Y71)),ROW(),""))
A72: BRK-INS-01-016130-PT | B72: 7.0 | C72: IT 5020-00151 | D72: DETERMINAÇÃO DE CONTAMINAÇÃO, COR-OFF, UNIFORMIDADE, CONTAGEM DE PELLETS E ODOR EM RESINA DE POLIETILENO | E72: Aprovado | F72: 46914 | G72: PE | I72: Ana CARLA DA CRUZ ARAUJO | L72: NDocs PE_PP!9 | M72: 1 | N72: =IF(TRIM(SUBSTITUTE(E72,CHAR(160)," "))="Avaiação de uso","Avaliação de uso",IF(TRIM(SUBSTITUTE(E72,CHAR(160)," "))="Cancelada","Cancelado",TRIM(SUBSTITUTE(E72,CHAR(160)," ")))) -> Aprovado | O72: =IF(ISNUMBER(F72),F72,IFERROR(DATE(RIGHT(RIGHT(TRIM(F72),10),4),MID(RIGHT(TRIM(F72),10),4,2),LEFT(RIGHT(TRIM(F72),10),2)),"")) -> 46914 | P72: =PROPER(TRIM(SUBSTITUTE(I72,CHAR(160)," "))) -> Ana Carla Da Cruz Araujo | Q72: =IF(O72="","",O72-DataRef) -> 613 | R72: =IF(OR(N72="Cancelado",N72="Fora de Uso"),"Inativo",IF(OR(N72="Revisão",N72="Em Elaboração"),"Em tratamento",IF(OR(N72<>"Aprovado",O72=""),"Validar cadastro",IF(O72<DataRef,"Ação imediata",IF(O72<=EDATE(DataRef,12),"Planejar revisão","Regular"))))) -> Regular | S72: =IF(R72="Inativo","Inativo",IF(O72="","Sem validade",IF(O72<DataRef,"Vencida",IF(O72<=DataRef+90,"Até 90 dias",IF(O72<=EDATE(DataRef,12),"91 dias a 12 meses","Após 12 meses"))))) -> Após 12 meses | T72: =IF(O72="","",DATE(YEAR(O72),MONTH(O72),1)) -> 46905 | U72: =IF(R72="Ação imediata",1,IF(N72="Não encontrado",2,IF(N72="Revisão",3,IF(N72="Em Elaboração",4,IF(S72="Até 90 dias",5,IF(R72="Validar cadastro",6,0)))))) -> 0 | V72: =CHOOSE(U72+1,IF(R72="Planejar revisão","Incluir no plano anual de revisão",IF(R72="Inativo","Sem ação","Monitorar")),"Revisar ou prorrogar validade","Confirmar status no NDocs","Acompanhar revisão","Concluir elaboração","Iniciar revisão (≤ 90 dias)","Validar aplicabilidade") -> Monitorar | W72: =(OR(fArea="Todas",ISNUMBER(SEARCH(fArea,G72))))*(OR(fStatus="Todos",N72=fStatus))*(OR(fSit="Todas",R72=fSit))*(OR(fResp="Todos",P72=fResp))*(OR(fHor="Todos",S72=fHor)) -> 1 | X72: =IF(AND(W72=1,U72>0),(7-U72)*100000+50000-IF(ISNUMBER(Q72),Q72,0)+ROW()/1000,0) -> 0 | Y72: =UPPER(A72&" "&TRIM(SUBSTITUTE(C72,CHAR(160)," "))&" "&TRIM(SUBSTITUTE(D72,CHAR(160)," "))) -> BRK-INS-01-016130-PT IT 5020-00151 DETERMINAÇÃO DE CONTAMINAÇÃO, COR-OFF, UNIFORMIDADE, CONTAGEM DE PELLETS E ODOR EM RESINA DE POLIETILENO | Z72: =IF(qBusca="","",IF(ISNUMBER(SEARCH(TRIM(qBusca),Y72)),ROW(),""))
A73: BRK-INS-01-016142-PT | B73: 6.0 | C73: IT 5020-00153 | D73: DETERMINAÇÃO DE CINZAS EM POLIETILENO E POLIPROPILENO | E73: Aprovado | F73: 46907 | G73: PE/PP | I73: Ana CARLA DA CRUZ ARAUJO | L73: NDocs PE_PP!10 | M73: 1 | N73: =IF(TRIM(SUBSTITUTE(E73,CHAR(160)," "))="Avaiação de uso","Avaliação de uso",IF(TRIM(SUBSTITUTE(E73,CHAR(160)," "))="Cancelada","Cancelado",TRIM(SUBSTITUTE(E73,CHAR(160)," ")))) -> Aprovado | O73: =IF(ISNUMBER(F73),F73,IFERROR(DATE(RIGHT(RIGHT(TRIM(F73),10),4),MID(RIGHT(TRIM(F73),10),4,2),LEFT(RIGHT(TRIM(F73),10),2)),"")) -> 46907 | P73: =PROPER(TRIM(SUBSTITUTE(I73,CHAR(160)," "))) -> Ana Carla Da Cruz Araujo | Q73: =IF(O73="","",O73-DataRef) -> 606 | R73: =IF(OR(N73="Cancelado",N73="Fora de Uso"),"Inativo",IF(OR(N73="Revisão",N73="Em Elaboração"),"Em tratamento",IF(OR(N73<>"Aprovado",O73=""),"Validar cadastro",IF(O73<DataRef,"Ação imediata",IF(O73<=EDATE(DataRef,12),"Planejar revisão","Regular"))))) -> Regular | S73: =IF(R73="Inativo","Inativo",IF(O73="","Sem validade",IF(O73<DataRef,"Vencida",IF(O73<=DataRef+90,"Até 90 dias",IF(O73<=EDATE(DataRef,12),"91 dias a 12 meses","Após 12 meses"))))) -> Após 12 meses | T73: =IF(O73="","",DATE(YEAR(O73),MONTH(O73),1)) -> 46905 | U73: =IF(R73="Ação imediata",1,IF(N73="Não encontrado",2,IF(N73="Revisão",3,IF(N73="Em Elaboração",4,IF(S73="Até 90 dias",5,IF(R73="Validar cadastro",6,0)))))) -> 0 | V73: =CHOOSE(U73+1,IF(R73="Planejar revisão","Incluir no plano anual de revisão",IF(R73="Inativo","Sem ação","Monitorar")),"Revisar ou prorrogar validade","Confirmar status no NDocs","Acompanhar revisão","Concluir elaboração","Iniciar revisão (≤ 90 dias)","Validar aplicabilidade") -> Monitorar | W73: =(OR(fArea="Todas",ISNUMBER(SEARCH(fArea,G73))))*(OR(fStatus="Todos",N73=fStatus))*(OR(fSit="Todas",R73=fSit))*(OR(fResp="Todos",P73=fResp))*(OR(fHor="Todos",S73=fHor)) -> 1 | X73: =IF(AND(W73=1,U73>0),(7-U73)*100000+50000-IF(ISNUMBER(Q73),Q73,0)+ROW()/1000,0) -> 0 | Y73: =UPPER(A73&" "&TRIM(SUBSTITUTE(C73,CHAR(160)," "))&" "&TRIM(SUBSTITUTE(D73,CHAR(160)," "))) -> BRK-INS-01-016142-PT IT 5020-00153 DETERMINAÇÃO DE CINZAS EM POLIETILENO E POLIPROPILENO | Z73: =IF(qBusca="","",IF(ISNUMBER(SEARCH(TRIM(qBusca),Y73)),ROW(),""))
